Workbook

Sheet Legenda e Metodologia
A1: LEGENDA E METODOLOGIA — Aba "Indicadores"
A3: Esta aba explica como cada número da aba "Indicadores" é calculado e quais critérios foram usados, para que você possa auditar e ajustar quando precisar.
A5: Como funciona
A6: Todos os valores da aba "Indicadores" são fórmulas que buscam direto nas abas mensais (Janeiro 2026, Fevereiro 2026, etc.). Não digite números à mão nessa aba — se digitar, a fórmula é perdida.
A7: Quando você criar a aba de um novo mês (ex: "Setembro 2026"), copie a fórmula de um mês já pronto (ex: coluna I, referente a Agosto) para a coluna do novo mês e troque o nome da aba dentro da fórmula.
A8: Todas as fórmulas ignoram maiúsculas/minúsculas e espaços extras no início/fim do texto (TRIM/UPPER), para não quebrar por causa de digitação diferente.
A10: Indicadores excluídos a pedido do usuário
A11: "ASR irregular", "ASR negada" e "Total de protocolos SAC" NÃO foram incluídos, pois você indicou que não são calculados a partir desta base.
A13: Critério de cada indicador
A14: QUANTIDADE DE ASR PAGA (recebida): conta o número de linhas com "N° Solicitação" preenchido em cada mês.
A15: VALOR DE REEMBOLSO SOLICITADO / PAGO: soma as colunas "VALOR SOLICITADO" / "VALOR PAGO", apenas nas linhas com "N° Solicitação" preenchido (algumas abas mensais têm uma linha de subtotal solta, sem número de solicitação — essa linha é ignorada de propósito).
A16: BENEFICIÁRIOS COM REEMBOLSOS PAGOS: conta valores únicos (não vazios) da coluna "COD. DO BENEFICIÁRIO".
... A42: As fórmulas de SANTANDER R$ PAGO, ITAÚ R$ PAGO e PREMIUM FREE R$ (e as versões em quantidade) foram reescritas para não usar mais SOMARPRODUTO(CORRESP(...)) diretamente. Em vez disso, cada aba mensal ganhou uma coluna auxiliar "SEGMENTO" (coluna AC) que já classifica cada linha (SANTANDER / ITAU / PREMIUM FREE / vazio), e a aba Indicadores só soma/conta essa coluna com SOMASES/CONT.SES. Isso evita um comportamento do Excel (inserção automática do operador @) que fazia o SOMARPRODUTO somar só uma célula em vez da coluna inteira, gerando totais errados.

Sheet Códigos Santander (ref)
A1: CÓD. EMPRESA | B1: RAZÃO SOCIAL | D1: Fonte: arquivo "Santander_e_Itau_empresas.xlsx" (aba SANTANDER) enviado pela usuária em 21/09/2026 - lista de códigos de empresa do grupo Santander, usada nos indicadores "Santander R$ pago" e "Santander - Qtd ASR paga".
A2: 1RUGW | B2: BANCO SANTANDER BRASIL SA
A3: 0LDEA | B3: SUPER PAG ADM MEIOS ELETRONICOS SA
A4: 0KQ1R | B4: F1RST TECNOLOGIA E INOVACAO LTDA
A5: 0KGE5 | B5: BANCO SANTANDER BRASIL SA
A6: 0KRU9 | B6: SANB PROMOTORA DE VENDAS E COBRANCA SA
A7: 0KRUA | B7: SX TOOLS SOLUC SERV COMPARTILHADOS LTDA
A8: 1UX41 | B8: BANCO SANTANDER SA
A9: 1T5GA | B9: BANCO SANTANDER SA
A10: 1RUAW | B10: SANTANDER FINANCE ARRENDAMENTO MERCANTIL SA
A11: 1RUAY | B11: ATUAL SERVICOS RECUP DE CREDITOS E MEIOS DIGI
A12: 1RUAX | B12: ESFERA FIDELIDADE SA
A13: 1RUB0 | B13: BANCO SANTANDER BRASIL SA
... A40: 1RUF2 | B40: BANESPA SA CORRETORA DE CAMBIO E TITULOS
A41: 1RNXU
A42: 1RUF3 | B42: SANTANDER COMPANHIA SECUR DE CREDITOS FINANCE
A43: 1RUF4 | B43: AYMORE CREDITO FINANCIAMENTO E INVESTIMENTO S
A44: 1RUF5 | B44: REAL MICROCREDITO ASSESSORIA FINANCEIRA SA
A45: 1RU6Z | B45: F1RST TECNOLOGIA E INOVACAO LTDA
A46: 1RU70 | B46: SANTANDER SEC SERV BR DIST TIT VAL IMOB SA
A47: 1RU71 | B47: SANTANDER HOLDING IMOBILIARIA SA
A48: 1RU72 | B48: SANTANDER BRASIL TECNOLOGIA SA
A49: 1RU73 | B49: BANCO SANTANDER BRASIL SA
A50: 1RU74 | B50: SANTANDER BRASIL INVESTIMENTOS E SERVICOS SA
A51: 1RU75 | B51: BANCO SANTANDER BRASIL SA
A52: 1RU76 | B52: BANCO SANTANDER BRASIL SA
A53: 1RU77 | B53: SANTANDER BANESPA ASSET MANAGEMENT LTDA
... A79: S21FQ | B79: SANTANDER SERVICOS DIGITAIS BRASIL LTDA

Sheet Códigos Itaú (ref)
A1: CÓD. EMPRESA | B1: RAZÃO SOCIAL | D1: Fonte: arquivo "Santander_e_Itau_empresas.xlsx" (aba ITAU) enviado pela usuária em 21/09/2026 - lista de códigos de empresa do grupo Itaú, usada nos indicadores "Itaú R$ pago" e "Itaú - Qtd ASR paga" (substitui a busca por texto "ITAU" no nome da empresa).
A2: 1RSLN
A3: 1RSX6
A4: 1RT70
A5: 1RT73
A6: 1RT7A
A7: 1RU23
A8: 1RT8Z
A9: 1RT95
A10: 1RTSM
A11: 1RT1I
A12: 1RT1T
A13: 1RTAL
... A44: IMM5N

Sheet Indicadores
A1: QUANTIDADE DE ASR PAGA
A3: Mês | B3: Jan | C3: Fev | D3: Mar | E3: Abr | F3: Mai | G3: Jun | H3: Jul | I3: Ago | J3: Set | K3: Out | L3: Nov | M3: Dez | N3: Acumulado | O3: Média
A4: Ano
A5: ASR paga 2026 | B5: =COUNTA('Janeiro 2026'!$B$2:$B$3000) | C5: =COUNTA('Fevereiro 2026'!$B$2:$B$2999) | D5: =COUNTA('Março 2026'!$B$2:$B$2999) | E5: =COUNTA('Abril 2026 '!$B$2:$B$3000) | F5: =COUNTA('Maio 2026'!$B$2:$B$3000) | G5: =COUNTA('Junho 2026'!$B$2:$B$3000) | H5: =COUNTA('Julho 2026'!$B$2:$B$3000) | I5: =COUNTA('Agosto 2026'!$B$2:$B$3000) | J5: =COUNTA('Setembro 2026'!$B$2:$B$2998) | N5: =SUM(B5:M5) | O5: =IFERROR(AVERAGE(B5:M5),0)
A8: VALOR DE REEMBOLSO SOLICITADO (R$)
A10: Mês | B10: Jan | C10: Fev | D10: Mar | E10: Abr | F10: Mai | G10: Jun | H10: Jul | I10: Ago | J10: Set | K10: Out | L10: Nov | M10: Dez | N10: Acumulado | O10: Média
A11: Ano
A12: R$ solicitado 2026 | B12: =SUMIFS('Janeiro 2026'!$G$2:$G$3000,'Janeiro 2026'!$B$2:$B$3000,"<>") | C12: =SUMIFS('Fevereiro 2026'!$G$2:$G$2999,'Fevereiro 2026'!$B$2:$B$2999,"<>") | D12: =SUMIFS('Março 2026'!$G$2:$G$2999,'Março 2026'!$B$2:$B$2999,"<>") | E12: =SUMIFS('Abril 2026 '!$G$2:$G$3000,'Abril 2026 '!$B$2:$B$3000,"<>") | F12: =SUMIFS('Maio 2026'!$G$2:$G$3000,'Maio 2026'!$B$2:$B$3000,"<>") | G12: =SUMIFS('Junho 2026'!$G$2:$G$3000,'Junho 2026'!$B$2:$B$3000,"<>") | H12: =SUMIFS('Julho 2026'!$G$2:$G$3000,'Julho 2026'!$B$2:$B$3000,"<>") | I12: =SUMIFS('Agosto 2026'!$G$2:$G$3000,'Agosto 2026'!$B$2:$B$3000,"<>") | J12: =SUMIFS('Setembro 2026'!$G$2:$G$2998,'Setembro 2026'!$B$2:$B$2998,"<>") | N12: =SUM(B12:M12) | O12: =IFERROR(AVERAGE(B12:M12),0)
A15: VALOR DE REEMBOLSO PAGO (R$)
A17: Mês | B17: Jan | C17: Fev | D17: Mar | E17: Abr | F17: Mai | G17: Jun | H17: Jul | I17: Ago | J17: Set | K17: Out | L17: Nov | M17: Dez | N17: Acumulado | O17: Média
A18: Ano
A19: R$ pago 2026 | B19: =SUMIFS('Janeiro 2026'!$H$2:$H$3000,'Janeiro 2026'!$B$2:$B$3000,"<>") | C19: =SUMIFS('Fevereiro 2026'!$H$2:$H$2999,'Fevereiro 2026'!$B$2:$B$2999,"<>") | D19: =SUMIFS('Março 2026'!$H$2:$H$2999,'Março 2026'!$B$2:$B$2999,"<>") | E19: =SUMIFS('Abril 2026 '!$H$2:$H$3000,'Abril 2026 '!$B$2:$B$3000,"<>") | F19: =SUMIFS('Maio 2026'!$H$2:$H$3000,'Maio 2026'!$B$2:$B$3000,"<>") | G19: =SUMIFS('Junho 2026'!$H$2:$H$3000,'Junho 2026'!$B$2:$B$3000,"<>") | H19: =SUMIFS('Julho 2026'!$H$2:$H$3000,'Julho 2026'!$B$2:$B$3000,"<>") | I19: =SUMIFS('Agosto 2026'!$H$2:$H$3000,'Agosto 2026'!$B$2:$B$3000,"<>") | J19: =SUMIFS('Setembro 2026'!$H$2:$H$2998,'Setembro 2026'!$B$2:$B$2998,"<>") | N19: =SUM(B19:M19) | O19: =IFERROR(AVERAGE(B19:M19),0)
A22: QUANTIDADE DE BENEFICIÁRIOS COM REEMBOLSOS PAGOS
A24: Mês | B24: Jan | C24: Fev | D24: Mar | E24: Abr | F24: Mai | G24: Jun | H24: Jul | I24: Ago | J24: Set | K24: Out | L24: Nov | M24: Dez | N24: Acumulado | O24: Média
A25: Ano
A26: 2026 | B26: =SUMPRODUCT(('Janeiro 2026'!$F$2:$F$3000<>"")/COUNTIF('Janeiro 2026'!$F$2:$F$3000,'Janeiro 2026'!$F$2:$F$3000&"")) | C26: =SUMPRODUCT(('Fevereiro 2026'!$F$2:$F$2999<>"")/COUNTIF('Fevereiro 2026'!$F$2:$F$2999,'Fevereiro 2026'!$F$2:$F$2999&"")) | D26: =SUMPRODUCT(('Março 2026'!$F$2:$F$2999<>"")/COUNTIF('Março 2026'!$F$2:$F$2999,'Março 2026'!$F$2:$F$2999&"")) | E26: =SUMPRODUCT(('Abril 2026 '!$F$2:$F$3000<>"")/COUNTIF('Abril 2026 '!$F$2:$F$3000,'Abril 2026 '!$F$2:$F$3000&"")) | F26: =SUMPRODUCT(('Maio 2026'!$F$2:$F$3000<>"")/COUNTIF('Maio 2026'!$F$2:$F$3000,'Maio 2026'!$F$2:$F$3000&"")) | G26: =SUMPRODUCT(('Junho 2026'!$F$2:$F$3000<>"")/COUNTIF('Junho 2026'!$F$2:$F$3000,'Junho 2026'!$F$2:$F$3000&"")) | H26: =SUMPRODUCT(('Julho 2026'!$F$2:$F$3000<>"")/COUNTIF('Julho 2026'!$F$2:$F$3000,'Julho 2026'!$F$2:$F$3000&"")) | I26: {=SUMPRODUCT(('Agosto 2026'!$F$2:$F$3000<>"")/COUNTIF('Agosto 2026'!$F$2:$F$3000,'Agosto 2026'!$F$2:$F$3000&""))} | J26: {=SUMPRODUCT(('Setembro 2026'!$F$2:$F$2998<>"")/COUNTIF('Setembro 2026'!$F$2:$F$2998,'Setembro 2026'!$F$2:$F$2998&""))} | N26: =SUM(B26:M26) | O26: =IFERROR(AVERAGE(B26:M26),0)
A29: EMPRESAS COM MAIORES VALORES (R$) DE REEMBOLSO + PRODUTO PREMIUM FREE
A31: Mês | B31: Jan | C31: Fev | D31: Mar | E31: Abr | F31: Mai | G31: Jun | H31: Jul | I31: Ago | J31: Set | K31: Out | L31: Nov | M31: Dez | N31: Acumulado | O31: Média
A32: Empresas
A33: Santander R$ pago 2026 | B33: =SUMIFS('Janeiro 2026'!$H$2:$H$5000,'Janeiro 2026'!$AC$2:$AC$5000,"SANTANDER") | C33: =SUMIFS('Fevereiro 2026'!$H$2:$H$5000,'Fevereiro 2026'!$AC$2:$AC$5000,"SANTANDER") | D33: =SUMIFS('Março 2026'!$H$2:$H$5000,'Março 2026'!$AC$2:$AC$5000,"SANTANDER") | E33: =SUMIFS('Abril 2026 '!$H$2:$H$5000,'Abril 2026 '!$AC$2:$AC$5000,"SANTANDER") | F33: =SUMIFS('Maio 2026'!$H$2:$H$5000,'Maio 2026'!$AC$2:$AC$5000,"SANTANDER") | G33: =SUMIFS('Junho 2026'!$H$2:$H$5000,'Junho 2026'!$AC$2:$AC$5000,"SANTANDER") | H33: =SUMIFS('Julho 2026'!$H$2:$H$5000,'Julho 2026'!$AC$2:$AC$5000,"SANTANDER") | I33: =SUMIFS('Agosto 2026'!$H$2:$H$5000,'Agosto 2026'!$AC$2:$AC$5000,"SANTANDER") | J33: =SUMIFS('Setembro 2026'!$H$2:$H$5000,'Setembro 2026'!$AC$2:$AC$5000,"SANTANDER") | N33: =SUM(B33:M33) | O33: =IFERROR(AVERAGE(B33:M33),0)
A34: Itaú R$ pago 2026 | B34: =SUMIFS('Janeiro 2026'!$H$2:$H$5000,'Janeiro 2026'!$AC$2:$AC$5000,"ITAU") | C34: =SUMIFS('Fevereiro 2026'!$H$2:$H$5000,'Fevereiro 2026'!$AC$2:$AC$5000,"ITAU") | D34: =SUMIFS('Março 2026'!$H$2:$H$5000,'Março 2026'!$AC$2:$AC$5000,"ITAU") | E34: =SUMIFS('Abril 2026 '!$H$2:$H$5000,'Abril 2026 '!$AC$2:$AC$5000,"ITAU") | F34: =SUMIFS('Maio 2026'!$H$2:$H$5000,'Maio 2026'!$AC$2:$AC$5000,"ITAU") | G34: =SUMIFS('Junho 2026'!$H$2:$H$5000,'Junho 2026'!$AC$2:$AC$5000,"ITAU") | H34: =SUMIFS('Julho 2026'!$H$2:$H$5000,'Julho 2026'!$AC$2:$AC$5000,"ITAU") | I34: =SUMIFS('Agosto 2026'!$H$2:$H$5000,'Agosto 2026'!$AC$2:$AC$5000,"ITAU") | J34: =SUMIFS('Setembro 2026'!$H$2:$H$5000,'Setembro 2026'!$AC$2:$AC$5000,"ITAU") | N34: =SUM(B34:M34) | O34: =IFERROR(AVERAGE(B34:M34),0)
A35: Premium free R$ 2026 | B35: =SUMIFS('Janeiro 2026'!$H$2:$H$5000,'Janeiro 2026'!$AC$2:$AC$5000,"PREMIUM FREE") | C35: =SUMIFS('Fevereiro 2026'!$H$2:$H$5000,'Fevereiro 2026'!$AC$2:$AC$5000,"PREMIUM FREE") | D35: =SUMIFS('Março 2026'!$H$2:$H$5000,'Março 2026'!$AC$2:$AC$5000,"PREMIUM FREE") | E35: =SUMIFS('Abril 2026 '!$H$2:$H$5000,'Abril 2026 '!$AC$2:$AC$5000,"PREMIUM FREE") | F35: =SUMIFS('Maio 2026'!$H$2:$H$5000,'Maio 2026'!$AC$2:$AC$5000,"PREMIUM FREE") | G35: =SUMIFS('Junho 2026'!$H$2:$H$5000,'Junho 2026'!$AC$2:$AC$5000,"PREMIUM FREE") | H35: =SUMIFS('Julho 2026'!$H$2:$H$5000,'Julho 2026'!$AC$2:$AC$5000,"PREMIUM FREE") | I35: =SUMIFS('Agosto 2026'!$H$2:$H$5000,'Agosto 2026'!$AC$2:$AC$5000,"PREMIUM FREE") | J35: =SUMIFS('Setembro 2026'!$H$2:$H$5000,'Setembro 2026'!$AC$2:$AC$5000,"PREMIUM FREE") | N35: =SUM(B35:M35) | O35: =IFERROR(AVERAGE(B35:M35),0)
A38: ASRs PAGAS DENTRO DO PRAZO CONTRATUAL
A40: Mês | B40: Jan | C40: Fev | D40: Mar | E40: Abr | F40: Mai | G40: Jun | H40: Jul | I40: Ago | J40: Set | K40: Out | L40: Nov | M40: Dez | N40: Acumulado | O40: Média
A41: Ano
A42: ASRs dentro do prazo 2026 | B42: =SUMPRODUCT((TRIM(UPPER('Janeiro 2026'!$Y$2:$Y$3000))="SIM")*1) | C42: =SUMPRODUCT((TRIM(UPPER('Fevereiro 2026'!$Y$2:$Y$2999))="SIM")*1) | D42: =SUMPRODUCT((TRIM(UPPER('Março 2026'!$Y$2:$Y$2999))="SIM")*1) | E42: =SUMPRODUCT((TRIM(UPPER('Abril 2026 '!$Y$2:$Y$3000))="SIM")*1) | F42: =SUMPRODUCT((TRIM(UPPER('Maio 2026'!$Y$2:$Y$3000))="SIM")*1) | G42: =SUMPRODUCT((TRIM(UPPER('Junho 2026'!$Y$2:$Y$3000))="SIM")*1) | H42: {=SUMPRODUCT((TRIM(UPPER('Julho 2026'!$Y$2:$Y$3000))="SIM")*1)} | I42: {=SUMPRODUCT((TRIM(UPPER('Agosto 2026'!$Y$2:$Y$3000))="SIM")*1)} | J42: {=SUMPRODUCT((TRIM(UPPER('Setembro 2026'!$Y$2:$Y$2998))="SIM")*1)} | N42: =SUM(B42:M42)
A43: % sobre ASR recebida no mês | B43: =IFERROR(B42/B$5,"") | C43: =IFERROR(C42/C$5,"") | D43: =IFERROR(D42/D$5,"") | E43: =IFERROR(E42/E$5,"") | F43: =IFERROR(F42/F$5,"") | G43: =IFERROR(G42/G$5,"") | H43: =IFERROR(H42/H$5,"") | I43: =IFERROR(I42/I$5,"") | J43: =IFERROR(J42/J$5,"")
A45: ASRs PAGAS FORA DO PRAZO CONTRATUAL
A47: Mês | B47: Jan | C47: Fev | D47: Mar | E47: Abr | F47: Mai | G47: Jun | H47: Jul | I47: Ago | J47: Set | K47: Out | L47: Nov | M47: Dez | N47: Acumulado | O47: Média
A48: Ano
A49: ASRs fora do prazo 2026 | B49: =SUMPRODUCT((TRIM(UPPER('Janeiro 2026'!$Y$2:$Y$3000))="NÃO")*1) | C49: =SUMPRODUCT((TRIM(UPPER('Fevereiro 2026'!$Y$2:$Y$2999))="NÃO")*1) | D49: =SUMPRODUCT((TRIM(UPPER('Março 2026'!$Y$2:$Y$2999))="NÃO")*1) | E49: =SUMPRODUCT((TRIM(UPPER('Abril 2026 '!$Y$2:$Y$3000))="NÃO")*1) | F49: =SUMPRODUCT((TRIM(UPPER('Maio 2026'!$Y$2:$Y$3000))="NÃO")*1) | G49: =SUMPRODUCT((TRIM(UPPER('Junho 2026'!$Y$2:$Y$3000))="NÃO")*1) | H49: {=SUMPRODUCT((TRIM(UPPER('Julho 2026'!$Y$2:$Y$3000))="NÃO")*1)} | I49: {=SUMPRODUCT((TRIM(UPPER('Agosto 2026'!$Y$2:$Y$3000))="NÃO")*1)} | J49: {=SUMPRODUCT((TRIM(UPPER('Setembro 2026'!$Y$2:$Y$3000))="NÃO")*1)} | N49: =SUM(B49:M49)
A50: % sobre ASR recebida no mês | B50: =IFERROR(B49/B$5,"") | C50: =IFERROR(C49/C$5,"") | D50: =IFERROR(D49/D$5,"") | E50: =IFERROR(E49/E$5,"") | F50: =IFERROR(F49/F$5,"") | G50: =IFERROR(G49/G$5,"") | H50: =IFERROR(H49/H$5,"") | I50: =IFERROR(I49/I$5,"") | J50: =IFERROR(J49/J$5,"")
A52: SOLICITAÇÃO DE CADASTRO ASTREIN (DADOS BANCÁRIOS)
A54: Mês | B54: Jan | C54: Fev | D54: Mar | E54: Abr | F54: Mai | G54: Jun | H54: Jul | I54: Ago | J54: Set | K54: Out | L54: Nov | M54: Dez | N54: Acumulado | O54: Média
A55: Ano
A56: Ano 2026 | B56: =SUMPRODUCT((TRIM('Janeiro 2026'!$O$2:$O$3000)<>"")*(TRIM(UPPER('Janeiro 2026'!$O$2:$O$3000))<>"JA POSSUI")) | C56: =SUMPRODUCT((TRIM('Fevereiro 2026'!$O$2:$O$2999)<>"")*(TRIM(UPPER('Fevereiro 2026'!$O$2:$O$2999))<>"JA POSSUI")) | D56: =SUMPRODUCT((TRIM('Março 2026'!$O$2:$O$2999)<>"")*(TRIM(UPPER('Março 2026'!$O$2:$O$2999))<>"JA POSSUI")) | E56: =SUMPRODUCT((TRIM('Abril 2026 '!$O$2:$O$3000)<>"")*(TRIM(UPPER('Abril 2026 '!$O$2:$O$3000))<>"JA POSSUI")) | F56: =SUMPRODUCT((TRIM('Maio 2026'!$O$2:$O$3000)<>"")*(TRIM(UPPER('Maio 2026'!$O$2:$O$3000))<>"JA POSSUI")) | G56: =SUMPRODUCT((TRIM('Junho 2026'!$O$2:$O$3000)<>"")*(TRIM(UPPER('Junho 2026'!$O$2:$O$3000))<>"JA POSSUI")) | H56: {=SUMPRODUCT((TRIM('Julho 2026'!$O$2:$O$3000)<>"")*(TRIM(UPPER('Julho 2026'!$O$2:$O$3000))<>"JA POSSUI"))} | I56: {=SUMPRODUCT((TRIM('Agosto 2026'!$O$2:$O$3000)<>"")*(TRIM(UPPER('Agosto 2026'!$O$2:$O$3000))<>"JA POSSUI"))} | J56: {=SUMPRODUCT((TRIM('Setembro 2026'!$O$2:$O$2998)<>"")*(TRIM(UPPER('Setembro 2026'!$O$2:$O$2998))<>"JA POSSUI"))} | N56: =SUM(B56:M56) | O56: =IFERROR(AVERAGE(B56:M56),0)
A59: REEMBOLSO INSUFICIÊNCIA DE REDE EM R$
A61: Mês | B61: Jan | C61: Fev | D61: Mar | E61: Abr | F61: Mai | G61: Jun | H61: Jul | I61: Ago | J61: Set | K61: Out | L61: Nov | M61: Dez | N61: Acumulado | O61: Média
A62: Ano
A63: Ano 2026 | B63: =SUMIFS('Janeiro 2026'!$H$2:$H$5000,'Janeiro 2026'!$I$2:$I$5000,"*INSUFICIÊNCIA DE REDE*") | C63: =SUMIFS('Fevereiro 2026'!$H$2:$H$5000,'Fevereiro 2026'!$I$2:$I$5000,"*INSUFICIÊNCIA DE REDE*") | D63: =SUMIFS('Março 2026'!$H$2:$H$5000,'Março 2026'!$I$2:$I$5000,"*INSUFICIÊNCIA DE REDE*") | E63: =SUMIFS('Abril 2026 '!$H$2:$H$5000,'Abril 2026 '!$I$2:$I$5000,"*INSUFICIÊNCIA DE REDE*") | F63: =SUMIFS('Maio 2026'!$H$2:$H$5000,'Maio 2026'!$I$2:$I$5000,"*INSUFICIÊNCIA DE REDE*") | G63: =SUMIFS('Junho 2026'!$H$2:$H$5000,'Junho 2026'!$I$2:$I$5000,"*INSUFICIÊNCIA DE REDE*") | H63: =SUMIFS('Julho 2026'!$H$2:$H$5000,'Julho 2026'!$I$2:$I$5000,"*INSUFICIÊNCIA DE REDE*") | I63: =SUMIFS('Agosto 2026'!$H$2:$H$5000,'Agosto 2026'!$I$2:$I$5000,"*INSUFICIÊNCIA DE REDE*") | J63: =SUMIFS('Setembro 2026'!$H$2:$H$5000,'Setembro 2026'!$I$2:$I$5000,"*INSUFICIÊNCIA DE REDE*") | N63: =SUM(B63:M63) | O63: =IFERROR(AVERAGE(B63:M63),0)
A66: REEMBOLSO COBRANÇA INDEVIDA EM R$
A68: Mês | B68: Jan | C68: Fev | D68: Mar | E68: Abr | F68: Mai | G68: Jun | H68: Jul | I68: Ago | J68: Set | K68: Out | L68: Nov | M68: Dez | N68: Acumulado | O68: Média
A69: Ano
A70: Ano 2026 | B70: =SUMIFS('Janeiro 2026'!$H$2:$H$5000,'Janeiro 2026'!$I$2:$I$5000,"*COBRANÇA INDEVIDA*") | C70: =SUMIFS('Fevereiro 2026'!$H$2:$H$5000,'Fevereiro 2026'!$I$2:$I$5000,"*COBRANÇA INDEVIDA*") | D70: =SUMIFS('Março 2026'!$H$2:$H$5000,'Março 2026'!$I$2:$I$5000,"*COBRANÇA INDEVIDA*") | E70: =SUMIFS('Abril 2026 '!$H$2:$H$5000,'Abril 2026 '!$I$2:$I$5000,"*COBRANÇA INDEVIDA*") | F70: =SUMIFS('Maio 2026'!$H$2:$H$5000,'Maio 2026'!$I$2:$I$5000,"*COBRANÇA INDEVIDA*") | G70: =SUMIFS('Junho 2026'!$H$2:$H$5000,'Junho 2026'!$I$2:$I$5000,"*COBRANÇA INDEVIDA*") | H70: =SUMIFS('Julho 2026'!$H$2:$H$5000,'Julho 2026'!$I$2:$I$5000,"*COBRANÇA INDEVIDA*") | I70: =SUMIFS('Agosto 2026'!$H$2:$H$5000,'Agosto 2026'!$I$2:$I$5000,"*COBRANÇA INDEVIDA*") | J70: =SUMIFS('Setembro 2026'!$H$2:$H$5000,'Setembro 2026'!$I$2:$I$5000,"*COBRANÇA INDEVIDA*") | N70: =SUM(B70:M70) | O70: =IFERROR(AVERAGE(B70:M70),0)
A73: REEMBOLSO DESLOCAMENTO EM R$
A75: Mês | B75: Jan | C75: Fev | D75: Mar | E75: Abr | F75: Mai | G75: Jun | H75: Jul | I75: Ago | J75: Set | K75: Out | L75: Nov | M75: Dez | N75: Acumulado | O75: Média
A76: Ano
A77: Ano 2026 | B77: =SUMIFS('Janeiro 2026'!$H$2:$H$5000,'Janeiro 2026'!$I$2:$I$5000,"*DESLOCAMENTO*") | C77: =SUMIFS('Fevereiro 2026'!$H$2:$H$5000,'Fevereiro 2026'!$I$2:$I$5000,"*DESLOCAMENTO*") | D77: =SUMIFS('Março 2026'!$H$2:$H$5000,'Março 2026'!$I$2:$I$5000,"*DESLOCAMENTO*") | E77: =SUMIFS('Abril 2026 '!$H$2:$H$5000,'Abril 2026 '!$I$2:$I$5000,"*DESLOCAMENTO*") | F77: =SUMIFS('Maio 2026'!$H$2:$H$5000,'Maio 2026'!$I$2:$I$5000,"*DESLOCAMENTO*") | G77: =SUMIFS('Junho 2026'!$H$2:$H$5000,'Junho 2026'!$I$2:$I$5000,"*DESLOCAMENTO*") | H77: =SUMIFS('Julho 2026'!$H$2:$H$5000,'Julho 2026'!$I$2:$I$5000,"*DESLOCAMENTO*") | I77: =SUMIFS('Agosto 2026'!$H$2:$H$5000,'Agosto 2026'!$I$2:$I$5000,"*DESLOCAMENTO*") | J77: =SUMIFS('Setembro 2026'!$H$2:$H$5000,'Setembro 2026'!$I$2:$I$5000,"*DESLOCAMENTO*") | N77: =SUM(B77:M77) | O77: =IFERROR(AVERAGE(B77:M77),0)
A79: QUANTIDADE DE ASR PAGA POR SEGMENTO (Santander / Itaú / Premium Free)
A81: Mês | B81: Jan | C81: Fev | D81: Mar | E81: Abr | F81: Mai | G81: Jun | H81: Jul | I81: Ago | J81: Set | K81: Out | L81: Nov | M81: Dez | N81: Acumulado | O81: Média
A82: Empresas
A83: Santander - Qtd ASR paga 2026 | B83: =COUNTIFS('Janeiro 2026'!$AC$2:$AC$5000,"SANTANDER") | C83: =COUNTIFS('Fevereiro 2026'!$AC$2:$AC$5000,"SANTANDER") | D83: =COUNTIFS('Março 2026'!$AC$2:$AC$5000,"SANTANDER") | E83: =COUNTIFS('Abril 2026 '!$AC$2:$AC$5000,"SANTANDER") | F83: =COUNTIFS('Maio 2026'!$AC$2:$AC$5000,"SANTANDER") | G83: =COUNTIFS('Junho 2026'!$AC$2:$AC$5000,"SANTANDER") | H83: =COUNTIFS('Julho 2026'!$AC$2:$AC$5000,"SANTANDER") | I83: =COUNTIFS('Agosto 2026'!$AC$2:$AC$5000,"SANTANDER") | J83: =COUNTIFS('Setembro 2026'!$AC$2:$AC$5000,"SANTANDER") | N83: =SUM(B83:M83) | O83: =IFERROR(AVERAGE(B83:M83),0)
A84: Itaú - Qtd ASR paga 2026 | B84: =COUNTIFS('Janeiro 2026'!$AC$2:$AC$5000,"ITAU") | C84: =COUNTIFS('Fevereiro 2026'!$AC$2:$AC$5000,"ITAU") | D84: =COUNTIFS('Março 2026'!$AC$2:$AC$5000,"ITAU") | E84: =COUNTIFS('Abril 2026 '!$AC$2:$AC$5000,"ITAU") | F84: =COUNTIFS('Maio 2026'!$AC$2:$AC$5000,"ITAU") | G84: =COUNTIFS('Junho 2026'!$AC$2:$AC$5000,"ITAU") | H84: =COUNTIFS('Julho 2026'!$AC$2:$AC$5000,"ITAU") | I84: =COUNTIFS('Agosto 2026'!$AC$2:$AC$5000,"ITAU") | J84: =COUNTIFS('Setembro 2026'!$AC$2:$AC$5000,"ITAU") | N84: =SUM(B84:M84) | O84: =IFERROR(AVERAGE(B84:M84),0)
A85: Premium free - Qtd ASR paga 2026 | B85: =COUNTIFS('Janeiro 2026'!$AC$2:$AC$5000,"PREMIUM FREE") | C85: =COUNTIFS('Fevereiro 2026'!$AC$2:$AC$5000,"PREMIUM FREE") | D85: =COUNTIFS('Março 2026'!$AC$2:$AC$5000,"PREMIUM FREE") | E85: =COUNTIFS('Abril 2026 '!$AC$2:$AC$5000,"PREMIUM FREE") | F85: =COUNTIFS('Maio 2026'!$AC$2:$AC$5000,"PREMIUM FREE") | G85: =COUNTIFS('Junho 2026'!$AC$2:$AC$5000,"PREMIUM FREE") | H85: =COUNTIFS('Julho 2026'!$AC$2:$AC$5000,"PREMIUM FREE") | I85: =COUNTIFS('Agosto 2026'!$AC$2:$AC$5000,"PREMIUM FREE") | J85: =COUNTIFS('Setembro 2026'!$AC$2:$AC$5000,"PREMIUM FREE") | N85: =SUM(B85:M85) | O85: =IFERROR(AVERAGE(B85:M85),0)
A88: REEMBOLSO INSUFICIÊNCIA DE REDE - QUANTIDADE DE ASR
A90: Mês | B90: Jan | C90: Fev | D90: Mar | E90: Abr | F90: Mai | G90: Jun | H90: Jul | I90: Ago | J90: Set | K90: Out | L90: Nov | M90: Dez | N90: Acumulado | O90: Média
A91: Ano
A92: Qtd ASR 2026 | B92: =COUNTIFS('Janeiro 2026'!$I$2:$I$5000,"*INSUFICIÊNCIA DE REDE*") | C92: =COUNTIFS('Fevereiro 2026'!$I$2:$I$5000,"*INSUFICIÊNCIA DE REDE*") | D92: =COUNTIFS('Março 2026'!$I$2:$I$5000,"*INSUFICIÊNCIA DE REDE*") | E92: =COUNTIFS('Abril 2026 '!$I$2:$I$5000,"*INSUFICIÊNCIA DE REDE*") | F92: =COUNTIFS('Maio 2026'!$I$2:$I$5000,"*INSUFICIÊNCIA DE REDE*") | G92: =COUNTIFS('Junho 2026'!$I$2:$I$5000,"*INSUFICIÊNCIA DE REDE*") | H92: =COUNTIFS('Julho 2026'!$I$2:$I$5000,"*INSUFICIÊNCIA DE REDE*") | I92: =COUNTIFS('Agosto 2026'!$I$2:$I$5000,"*INSUFICIÊNCIA DE REDE*") | J92: =COUNTIFS('Setembro 2026'!$I$2:$I$5000,"*INSUFICIÊNCIA DE REDE*") | N92: =SUM(B92:M92) | O92: =IFERROR(AVERAGE(B92:M92),0)
A95: REEMBOLSO COBRANÇA INDEVIDA - QUANTIDADE DE ASR
A97: Mês | B97: Jan | C97: Fev | D97: Mar | E97: Abr | F97: Mai | G97: Jun | H97: Jul | I97: Ago | J97: Set | K97: Out | L97: Nov | M97: Dez | N97: Acumulado | O97: Média
A98: Ano
A99: Qtd ASR 2026 | B99: =COUNTIFS('Janeiro 2026'!$I$2:$I$5000,"*COBRANÇA INDEVIDA*") | C99: =COUNTIFS('Fevereiro 2026'!$I$2:$I$5000,"*COBRANÇA INDEVIDA*") | D99: =COUNTIFS('Março 2026'!$I$2:$I$5000,"*COBRANÇA INDEVIDA*") | E99: =COUNTIFS('Abril 2026 '!$I$2:$I$5000,"*COBRANÇA INDEVIDA*") | F99: =COUNTIFS('Maio 2026'!$I$2:$I$5000,"*COBRANÇA INDEVIDA*") | G99: =COUNTIFS('Junho 2026'!$I$2:$I$5000,"*COBRANÇA INDEVIDA*") | H99: =COUNTIFS('Julho 2026'!$I$2:$I$5000,"*COBRANÇA INDEVIDA*") | I99: =COUNTIFS('Agosto 2026'!$I$2:$I$5000,"*COBRANÇA INDEVIDA*") | J99: =COUNTIFS('Setembro 2026'!$I$2:$I$5000,"*COBRANÇA INDEVIDA*") | N99: =SUM(B99:M99) | O99: =IFERROR(AVERAGE(B99:M99),0)
A102: REEMBOLSO DESLOCAMENTO - QUANTIDADE DE ASR
A104: Mês | B104: Jan | C104: Fev | D104: Mar | E104: Abr | F104: Mai | G104: Jun | H104: Jul | I104: Ago | J104: Set | K104: Out | L104: Nov | M104: Dez | N104: Acumulado | O104: Média
A105: Ano
A106: Qtd ASR 2026 | B106: =COUNTIFS('Janeiro 2026'!$I$2:$I$5000,"*DESLOCAMENTO*") | C106: =COUNTIFS('Fevereiro 2026'!$I$2:$I$5000,"*DESLOCAMENTO*") | D106: =COUNTIFS('Março 2026'!$I$2:$I$5000,"*DESLOCAMENTO*") | E106: =COUNTIFS('Abril 2026 '!$I$2:$I$5000,"*DESLOCAMENTO*") | F106: =COUNTIFS('Maio 2026'!$I$2:$I$5000,"*DESLOCAMENTO*") | G106: =COUNTIFS('Junho 2026'!$I$2:$I$5000,"*DESLOCAMENTO*") | H106: =COUNTIFS('Julho 2026'!$I$2:$I$5000,"*DESLOCAMENTO*") | I106: =COUNTIFS('Agosto 2026'!$I$2:$I$5000,"*DESLOCAMENTO*") | J106: =COUNTIFS('Setembro 2026'!$I$2:$I$5000,"*DESLOCAMENTO*") | N106: =SUM(B106:M106) | O106: =IFERROR(AVERAGE(B106:M106),0)

Sheet Painel de Indicadores
A1: PAINEL DE INDICADORES DE REEMBOLSO (ASR) | R1: Dados-fonte do painel (ligados à aba "Indicadores" - não precisa mexer aqui)
A2: Auditoria Odontológica · Base 2026 · atualizado automaticamente a partir da aba "Indicadores"
R3: Motivo | S3: Valor 2026 (R$)
A4: ASR PAGA (ACUMULADO 2026) | E4: VALOR PAGO (ACUMULADO 2026) | I4: % DENTRO DO PRAZO CONTRATUAL | M4: TICKET MÉDIO PAGO (R$) | R4: Insuficiência de Rede | S4: ='Indicadores'!N63
A5: ='Indicadores'!N5 | E5: ='Indicadores'!N19 | I5: ='Indicadores'!N42/'Indicadores'!N5 | M5: ='Indicadores'!N19/'Indicadores'!N5 | R5: Cobrança Indevida | S5: ='Indicadores'!N70
R6: Deslocamento | S6: ='Indicadores'!N77
A7: ="Média mensal: "&TEXT('Indicadores'!O5,"#,##0")&" ASR/mês" | E7: ="Solicitado: R$ "&TEXT('Indicadores'!N12,"#,##0") | I7: ="Fora do prazo: "&TEXT('Indicadores'!N49,"#,##0")&" ASR" | M7: ="Beneficiários (soma mensal): "&TEXT('Indicadores'!N26,"#,##0")
A9: DISTRIBUIÇÃO E TENDÊNCIAS — 2026 | R9: Segmento | S9: Valor 2026 (R$)
R10: Santander | S10: ='Indicadores'!N33
R11: Itaú | S11: ='Indicadores'!N34
R12: Premium Free | S12: ='Indicadores'!N35
R13: Outros | S13: ='Indicadores'!N19-S10-S11-S12
R16: Mês | S16: ASR paga
R17: ='Indicadores'!B3 | S17: ='Indicadores'!B5
R18: ='Indicadores'!C3 | S18: ='Indicadores'!C5
R19: ='Indicadores'!D3 | S19: ='Indicadores'!D5
R20: ='Indicadores'!E3 | S20: ='Indicadores'!E5
R21: ='Indicadores'!F3 | S21: ='Indicadores'!F5
R22: ='Indicadores'!G3 | S22: ='Indicadores'!G5
R23: ='Indicadores'!H3 | S23: ='Indicadores'!H5
R24: ='Indicadores'!I3 | S24: ='Indicadores'!I5
R25: ='Indicadores'!J3 | S25: ='Indicadores'!J5
R28: Mês | S28: Dentro do prazo | T28: Fora do prazo
R29: ='Indicadores'!B3 | S29: ='Indicadores'!B42 | T29: ='Indicadores'!B49
R30: ='Indicadores'!C3 | S30: ='Indicadores'!C42 | T30: ='Indicadores'!C49
R31: ='Indicadores'!D3 | S31: ='Indicadores'!D42 | T31: ='Indicadores'!D49
R32: ='Indicadores'!E3 | S32: ='Indicadores'!E42 | T32: ='Indicadores'!E49
R33: ='Indicadores'!F3 | S33: ='Indicadores'!F42 | T33: ='Indicadores'!F49
R34: ='Indicadores'!G3 | S34: ='Indicadores'!G42 | T34: ='Indicadores'!G49
R35: ='Indicadores'!H3 | S35: ='Indicadores'!H42 | T35: ='Indicadores'!H49
R36: ='Indicadores'!I3 | S36: ='Indicadores'!I42 | T36: ='Indicadores'!I49
R37: ='Indicadores'!J3 | S37: ='Indicadores'!J42 | T37: ='Indicadores'!J49

Sheet Janeiro 2026
A1: CANAL | B1: N° SOLICITAÇÃO | C1: CÓD. EMPRESA | D1: EMPRESA | E1: CPF TITULAR | F1: COD. DO BENEFICIÁRIO | G1: VALOR SOLICITADO | H1: VALOR PAGO | I1: MOTIVO | J1: CPF/CNPJ DENTISTA | K1: NOME PRESTADOR DE SERVIÇO | L1: CIDADE PRESTADOR | M1: UF PRESTADOR | N1: AUDITOR | O1: ASTREIN | P1: DT SOLICITAÇÃO ASTREIN | Q1: DT LIBERAÇÃO ASTREIN | R1: STATUS DA SOLICITAÇÃO | S1: PROCESSO | T1: PRAZO CONTRATUAL | U1: DT AUDITORIA | V1: DT APROVAÇÃO | W1: DT PRAZO CONTRATUAL | X1: DATA DE PAGAMENTO SAP | Y1: PRAZO ATENDIDO | Z1: OBS | AC1: SEGMENTO (auxiliar automático)
A2: TELA | B2: 52406 | C2: 1RU51 | D2: BANCO SANTANDER BRASIL SA | E2: 8898809808 | F2: 1RU51000478008 | G2: 950 | H2: 391.95 | I2: CONTRATUAL | J2: 24870458000160 | K2: EDWAL LOBOSCHI | L2: SÃO PAULO | M2: SP | N2: SERGIANA | O2: 519338 | P2: 46014 | Q2: 46020 | R2: AUTORIZADO PAGAMENTO | S2: 8202610637 | T2: 5 DIAS ÚTEIS | U2: 46014 | V2: 46027 | W2: 46034 | X2: 46031 | Y2: =IF(AND(X2<>"",W2<>""),IF(X2<=W2,"SIM","NÃO"),"") | AC2: =IF($C2="","",IF(COUNTIF('Códigos Santander (ref)'!$A$2:$A$79,$C2)>0,"SANTANDER",IF(COUNTIF('Códigos Itaú (ref)'!$A$2:$A$44,$C2)>0,"ITAU",IF(AND(TRIM(UPPER($I2))="CONTRATUAL",ISNUMBER(SEARCH("INDIVIDUAL",SUBSTITUTE(UPPER($D2)," ","")))),"PREMIUM FREE",""))))
A3: TELA | B3: 52332 | C3: 1RUH3 | D3: BANCO SANTANDER BRASIL SA | E3: 35769531835 | F3: 1RUH3011824000 | G3: 1510 | H3: 290.45 | I3: CONTRATUAL | J3: 37709145892 | K3: FLAVIA MARTINS LEAL SEPINHO | L3: JACAREI | M3: SP | N3: SERGIANA | O3: 519341 | P3: 46014 | Q3: 46020 | R3: AUTORIZADO PAGAMENTO | S3: 8202610641 | T3: 5 DIAS ÚTEIS | U3: 46014 | V3: 46027 | W3: 46034 | X3: 46031 | Y3: =IF(AND(X3<>"",W3<>""),IF(X3<=W3,"SIM","NÃO"),"") | AC3: =IF($C3="","",IF(COUNTIF('Códigos Santander (ref)'!$A$2:$A$79,$C3)>0,"SANTANDER",IF(COUNTIF('Códigos Itaú (ref)'!$A$2:$A$44,$C3)>0,"ITAU",IF(AND(TRIM(UPPER($I3))="CONTRATUAL",ISNUMBER(SEARCH("INDIVIDUAL",SUBSTITUTE(UPPER($D3)," ","")))),"PREMIUM FREE",""))))
A4: TELA | B4: 52236 | C4: 1RU51 | D4: BANCO SANTANDER BRASIL SA | E4: 11278282823 | F4: 1RU51000204005 | G4: 609.4 | H4: 164.43 | I4: CONTRATUAL | J4: 42063134820 | K4: JULIO ANTONIO VEIGA SERRASQUEIRO | L4: SÃO PAULO | M4: SP | N4: SERGIANA | O4: 519599 | P4: 46020 | Q4: 46021 | R4: AUTORIZADO PAGAMENTO | S4: 8202610642 | T4: 5 DIAS ÚTEIS | U4: 46015 | V4: 46027 | W4: 46034 | X4: 46031 | Y4: =IF(AND(X4<>"",W4<>""),IF(X4<=W4,"SIM","NÃO"),"") | AC4: =IF($C4="","",IF(COUNTIF('Códigos Santander (ref)'!$A$2:$A$79,$C4)>0,"SANTANDER",IF(COUNTIF('Códigos Itaú (ref)'!$A$2:$A$44,$C4)>0,"ITAU",IF(AND(TRIM(UPPER($I4))="CONTRATUAL",ISNUMBER(SEARCH("INDIVIDUAL",SUBSTITUTE(UPPER($D4)," ","")))),"PREMIUM FREE",""))))
A5: TELA | B5: 52242 | C5: 1RUB1 | D5: F1RST TECNOLOGIA E INOVACAO LTDA | E5: 16384262878 | F5: 1RUB1005723000 | G5: 2850 | H5: 81.66 | I5: CONTRATUAL | J5: 42714999000180 | K5: AFD ODONTOLOGIA LTDA | L5: SÃO PAULO | M5: SP | N5: SERGIANA | O5: JA POSSUI | R5: AUTORIZADO PAGAMENTO | S5: 8202610644 | T5: 5 DIAS ÚTEIS | U5: 46020 | V5: 46027 | W5: 46034 | X5: 46031 | Y5: =IF(AND(X5<>"",W5<>""),IF(X5<=W5,"SIM","NÃO"),"") | AC5: =IF($C5="","",IF(COUNTIF('Códigos Santander (ref)'!$A$2:$A$79,$C5)>0,"SANTANDER",IF(COUNTIF('Códigos Itaú (ref)'!$A$2:$A$44,$C5)>0,"ITAU",IF(AND(TRIM(UPPER($I5))="CONTRATUAL",ISNUMBER(SEARCH("INDIVIDUAL",SUBSTITUTE(UPPER($D5)," ","")))),"PREMIUM FREE",""))))
A6: TELA | B6: 52338 | C6: 1RUB1 | D6: F1RST TECNOLOGIA E INOVACAO LTDA | E6: 35369845840 | F6: 1RUB1002304015 | G6: 175 | H6: 175 | I6: CONTRATUAL | J6: 36897556890 | K6: IINGRID CAROLINE CRUZ BUSSINE | L6: SÃO PAULO | M6: SP | N6: SERGIANA | O6: JA POSSUI | R6: AUTORIZADO PAGAMENTO | S6: 8202610645 | T6: 5 DIAS ÚTEIS | U6: 46020 | V6: 46027 | W6: 46034 | X6: 46031 | Y6: =IF(AND(X6<>"",W6<>""),IF(X6<=W6,"SIM","NÃO"),"") | AC6: =IF($C6="","",IF(COUNTIF('Códigos Santander (ref)'!$A$2:$A$79,$C6)>0,"SANTANDER",IF(COUNTIF('Códigos Itaú (ref)'!$A$2:$A$44,$C6)>0,"ITAU",IF(AND(TRIM(UPPER($I6))="CONTRATUAL",ISNUMBER(SEARCH("INDIVIDUAL",SUBSTITUTE(UPPER($D6)," ","")))),"PREMIUM FREE",""))))
A7: TELA | B7: 52449 | C7: 1RUH3 | D7: BANCO SANTANDER BRASIL SA | E7: 35294731894 | F7: 1RUH3003838030 | G7: 250 | H7: 212.19 | I7: CONTRATUAL | J7: 21621700860 | K7: CAMILA CRISTINA FANTI TAPIA | L7: SÃO PAULO | M7: SP | N7: SERGIANA | O7: JA POSSUI | R7: AUTORIZADO PAGAMENTO | S7: 8202610646 | T7: 5 DIAS ÚTEIS | U7: 46020 | V7: 46027 | W7: 46034 | X7: 46031 | Y7: =IF(AND(X7<>"",W7<>""),IF(X7<=W7,"SIM","NÃO"),"") | AC7: =IF($C7="","",IF(COUNTIF('Códigos Santander (ref)'!$A$2:$A$79,$C7)>0,"SANTANDER",IF(COUNTIF('Códigos Itaú (ref)'!$A$2:$A$44,$C7)>0,"ITAU",IF(AND(TRIM(UPPER($I7))="CONTRATUAL",ISNUMBER(SEARCH("INDIVIDUAL",SUBSTITUTE(UPPER($D7)," ","")))),"PREMIUM FREE",""))))
A8: TELA | B8: 52525 | C8: 1RUH3 | D8: BANCO SANTANDER BRASIL SA | E8: 25547807818 | F8: 1RUH3021267006 | G8: 350 | H8: 243.88 | I8: CONTRATUAL | J8: 24870458000160 | K8: EDWAL LOBOSCHI | L8: SÃO PAULO | M8: SP | N8: SERGIANA | O8: 520010 | P8: 46027 | Q8: 46027 | R8: AUTORIZADO PAGAMENTO | S8: 8202610772 | T8: 5 DIAS ÚTEIS | U8: 46020 | V8: 46028 | W8: 46035 | X8: 46036 | Y8: =IF(AND(X8<>"",W8<>""),IF(X8<=W8,"SIM","NÃO"),"") | AC8: =IF($C8="","",IF(COUNTIF('Códigos Santander (ref)'!$A$2:$A$79,$C8)>0,"SANTANDER",IF(COUNTIF('Códigos Itaú (ref)'!$A$2:$A$44,$C8)>0,"ITAU",IF(AND(TRIM(UPPER($I8))="CONTRATUAL",ISNUMBER(SEARCH("INDIVIDUAL",SUBSTITUTE(UPPER($D8)," ","")))),"PREMIUM FREE",""))))
A9: TELA | B9: 51651 | C9: 1RUH3 | D9: BANCO SANTANDER BRASIL SA | E9: 47036900806 | F9: 1RUH3015381005 | G9: 350 | H9: 243.88 | I9: CONTRATUAL | J9: 24870458000160 | K9: EDWAL LOBOSCHI | L9: SÃO PAULO | M9: SP | N9: SERGIANA | O9: 520012 | P9: 46027 | Q9: 46027 | R9: AUTORIZADO PAGAMENTO | S9: 8202610773 | T9: 5 DIAS ÚTEIS | U9: 46022 | V9: 46028 | W9: 46035 | X9: 46036 | Y9: =IF(AND(X9<>"",W9<>""),IF(X9<=W9,"SIM","NÃO"),"") | AC9: =IF($C9="","",IF(COUNTIF('Códigos Santander (ref)'!$A$2:$A$79,$C9)>0,"SANTANDER",IF(COUNTIF('Códigos Itaú (ref)'!$A$2:$A$44,$C9)>0,"ITAU",IF(AND(TRIM(UPPER($I9))="CONTRATUAL",ISNUMBER(SEARCH("INDIVIDUAL",SUBSTITUTE(UPPER($D9)," ","")))),"PREMIUM FREE",""))))
A10: TELA | B10: 52426 | C10: 1RUH3 | D10: BANCO SANTANDER BRASIL SA | E10: 5748915529 | F10: 1RUH3014267012 | G10: 115 | H10: 115 | I10: CONTRATUAL | J10: 9028521000121 | K10: RADIUM UNIDADE DE SERVICOS DE IMAGENS DA FACE LTDA | L10: JUAZEIRO | M10: BA | N10: SERGIANA | O10: JA POSSUI | R10: AUTORIZADO PAGAMENTO | S10: 8202610647 | T10: 5 DIAS ÚTEIS | U10: 46022 | V10: 46027 | W10: 46034 | X10: 46031 | Y10: =IF(AND(X10<>"",W10<>""),IF(X10<=W10,"SIM","NÃO"),"") | AC10: =IF($C10="","",IF(COUNTIF('Códigos Santander (ref)'!$A$2:$A$79,$C10)>0,"SANTANDER",IF(COUNTIF('Códigos Itaú (ref)'!$A$2:$A$44,$C10)>0,"ITAU",IF(AND(TRIM(UPPER($I10))="CONTRATUAL",ISNUMBER(SEARCH("INDIVIDUAL",SUBSTITUTE(UPPER($D10)," ","")))),"PREMIUM FREE",""))))
A11: TELA | B11: 52628 | C11: S21FQ | D11: SANTANDER SERVICOS DIGITAIS BRASIL LTDA | E11: 21400310830 | F11: S21FQ000899020 | G11: 250 | H11: 212.19 | I11: CONTRATUAL | J11: 11186762896 | K11: ANA CLAUDIA GGUIMARAES COSTA | L11: CAMPINAS | M11: SP | N11: SERGIANA | O11: JA POSSUI | R11: AUTORIZADO PAGAMENTO | S11: 8202610720 | T11: 5 DIAS ÚTEIS | U11: 46027 | V11: 46028 | W11: 46035 | X11: 46031 | Y11: =IF(AND(X11<>"",W11<>""),IF(X11<=W11,"SIM","NÃO"),"") | Z11: SIM | AC11: =IF($C11="","",IF(COUNTIF('Códigos Santander (ref)'!$A$2:$A$79,$C11)>0,"SANTANDER",IF(COUNTIF('Códigos Itaú (ref)'!$A$2:$A$44,$C11)>0,"ITAU",IF(AND(TRIM(UPPER($I11))="CONTRATUAL",ISNUMBER(SEARCH("INDIVIDUAL",SUBSTITUTE(UPPER($D11)," ","")))),"PREMIUM FREE",""))))
A12: TELA | B12: 52607 | C12: 1RUD5 | D12: SANTANDER HOLDING IMOBILIARIA SA | E12: 26534957833 | F12: 1RUD5000037010 | G12: 300 | H12: 212.19 | I12: CONTRATUAL | J12: 21315482819 | K12: CRISTINA YUKA HASSUNUMA | L12: SÃO PAULO | M12: SP | N12: SERGIANA | O12: JA POSSUI | R12: AUTORIZADO PAGAMENTO | S12: 8202610722 | T12: 5 DIAS ÚTEIS | U12: 46027 | V12: 46028 | W12: 46035 | X12: 46031 | Y12: =IF(AND(X12<>"",W12<>""),IF(X12<=W12,"SIM","NÃO"),"") | AC12: =IF($C12="","",IF(COUNTIF('Códigos Santander (ref)'!$A$2:$A$79,$C12)>0,"SANTANDER",IF(COUNTIF('Códigos Itaú (ref)'!$A$2:$A$44,$C12)>0,"ITAU",IF(AND(TRIM(UPPER($I12))="CONTRATUAL",ISNUMBER(SEARCH("INDIVIDUAL",SUBSTITUTE(UPPER($D12)," ","")))),"PREMIUM FREE",""))))
A13: TELA | B13: 52626 | C13: 1RUH3 | D13: BANCO SANTANDER BRASIL SA | E13: 15858127819 | F13: 1RUH3030565030 | G13: 370 | H13: 51.03 | I13: CONTRATUAL | J13: 4116655961 | K13: MELINA VITALI DA SILVA MATOS | L13: LONDRINA | M13: PR | N13: SERGIANA | O13: JA POSSUI | R13: AUTORIZADO PAGAMENTO | S13: 8202610723 | T13: 5 DIAS ÚTEIS | U13: 46027 | V13: 46028 | W13: 46035 | X13: 46031 | Y13: =IF(AND(X13<>"",W13<>""),IF(X13<=W13,"SIM","NÃO"),"") | AC13: =IF($C13="","",IF(COUNTIF('Códigos Santander (ref)'!$A$2:$A$79,$C13)>0,"SANTANDER",IF(COUNTIF('Códigos Itaú (ref)'!$A$2:$A$44,$C13)>0,"ITAU",IF(AND(TRIM(UPPER($I13))="CONTRATUAL",ISNUMBER(SEARCH("INDIVIDUAL",SUBSTITUTE(UPPER($D13)," ","")))),"PREMIUM FREE",""))))
A14: TELA | B14: 52241 | C14: 1RUH3 | D14: BANCO SANTANDER BRASIL SA | E14: 1835147771 | F14: 1RUH3030092000 | G14: 4250 | H14: 2849.21 | I14: CONTRATUAL | J14: 1287115748 | K14: JULIO CESAR FERREIRA RODRIGUES | L14: SÃO GONÇALO | M14: RJ | N14: SERGIANA | O14: JA POSSUI | R14: AUTORIZADO PAGAMENTO | S14: 8202610724 | T14: 5 DIAS ÚTEIS | U14: 46027 | V14: 46028 | W14: 46035 | X14: 46031 | Y14: =IF(AND(X14<>"",W14<>""),IF(X14<=W14,"SIM","NÃO"),"") | AC14: =IF($C14="","",IF(COUNTIF('Códigos Santander (ref)'!$A$2:$A$79,$C14)>0,"SANTANDER",IF(COUNTIF('Códigos Itaú (ref)'!$A$2:$A$44,$C14)>0,"ITAU",IF(AND(TRIM(UPPER($I14))="CONTRATUAL",ISNUMBER(SEARCH("INDIVIDUAL",SUBSTITUTE(UPPER($D14)," ","")))),"PREMIUM FREE",""))))
A15: TELA | B15: 52451 | C15: 60300 | D15: INDIVIDUAL | E15: 2528015208 | F15: 60300911953014 | G15: 600 | H15: 53.4 | I15: CONTRATUAL | J15: 30278271000174 | K15: ARTE DO SORRISO ODONTOLOGIA | L15: MANAUS | M15: AM | N15: SERGIANA | O15: JA POSSUI | R15: AUTORIZADO PAGAMENTO | S15: 8202610725 | T15: 30 DIAS CORRIDOS | U15: 46027 | V15: 46028 | W15: 46059 | X15: 46031 | Y15: =IF(AND(X15<>"",W15<>""),IF(X15<=W15,"SIM","NÃO"),"") | AC15: =IF($C15="","",IF(COUNTIF('Códigos Santander (ref)'!$A$2:$A$79,$C15)>0,"SANTANDER",IF(COUNTIF('Códigos Itaú (ref)'!$A$2:$A$44,$C15)>0,"ITAU",IF(AND(TRIM(UPPER($I15))="CONTRATUAL",ISNUMBER(SEARCH("INDIVIDUAL",SUBSTITUTE(UPPER($D15)," ","")))),"PREMIUM FREE",""))))
A16: TELA | B16: 52181 | C16: 50700 | D16: INDIVIDUAL MAISODONTO | E16: 10028584457 | F16: 50700371165007 | G16: 1080 | H16: 79.8 | I16: CONTRATUAL | J16: 5259219406 | K16: KEILA NASCIMENTO VIEIRA GAUDENCIO | L16: CAMPINA GRANDE | M16: PB | N16: SERGIANA | O16: 520317 | P16: 46028 | Q16: 46028 | R16: AUTORIZADO PAGAMENTO | S16: 8202610779 | T16: 30 DIAS CORRIDOS | U16: 46027 | V16: 46028 | W16: 46059 | X16: 46036 | Y16: =IF(AND(X16<>"",W16<>""),IF(X16<=W16,"SIM","NÃO"),"") | AC16: =IF($C16="","",IF(COUNTIF('Códigos Santander (ref)'!$A$2:$A$79,$C16)>0,"SANTANDER",IF(COUNTIF('Códigos Itaú (ref)'!$A$2:$A$44,$C16)>0,"ITAU",IF(AND(TRIM(UPPER($I16))="CONTRATUAL",ISNUMBER(SEARCH("INDIVIDUAL",SUBSTITUTE(UPPER($D16)," ","")))),"PREMIUM FREE",""))))
A17: TELA | B17: 50949 | C17: 1RUH3 | D17: BANCO SANTANDER BRASIL SA | E17: 28475431801 | F17: 1RUH3031318010 | G17: 140 | H17: 71.81 | I17: CONTRATUAL | J17: 24973449000102 | K17: RAFAEL DESSIMONI DELA COLETA ME | L17: SÃO JOSÉ DO RIO PARDO | M17: SP | N17: SERGIANA | O17: 520327 | P17: 46028 | Q17: 46028 | R17: AUTORIZADO PAGAMENTO | S17: 8202610781 | T17: 5 DIAS ÚTEIS | U17: 46027 | V17: 46028 | W17: 46035 | X17: 46036 | Y17: =IF(AND(X17<>"",W17<>""),IF(X17<=W17,"SIM","NÃO"),"") | AC17: =IF($C17="","",IF(COUNTIF('Códigos Santander (ref)'!$A$2:$A$79,$C17)>0,"SANTANDER",IF(COUNTIF('Códigos Itaú (ref)'!$A$2:$A$44,$C17)>0,"ITAU",IF(AND(TRIM(UPPER($I17))="CONTRATUAL",ISNUMBER(SEARCH("INDIVIDUAL",SUBSTITUTE(UPPER($D17)," ","")))),"PREMIUM FREE",""))))
A18: TELA | B18: 51040 | C18: 1RUH3 | D18: BANCO SANTANDER BRASIL SA | E18: 8248767760 | F18: 1RUH3019582013 | G18: 260 | H18: 212.19 | I18: CONTRATUAL | J18: 5950466730 | K18: ZULMA FLORES BLANCO QUEIROZ | L18: SÃO GONÇALO | M18: RJ | N18: SERGIANA | O18: JA POSSUI | R18: AUTORIZADO PAGAMENTO | S18: 8202610726 | T18: 5 DIAS ÚTEIS | U18: 46027 | V18: 46028 | W18: 46035 | X18: 46031 | Y18: =IF(AND(X18<>"",W18<>""),IF(X18<=W18,"SIM","NÃO"),"") | AC18: =IF($C18="","",IF(COUNTIF('Códigos Santander (ref)'!$A$2:$A$79,$C18)>0,"SANTANDER",IF(COUNTIF('Códigos Itaú (ref)'!$A$2:$A$44,$C18)>0,"ITAU",IF(AND(TRIM(UPPER($I18))="CONTRATUAL",ISNUMBER(SEARCH("INDIVIDUAL",SUBSTITUTE(UPPER($D18)," ","")))),"PREMIUM FREE",""))))
A19: TELA | B19: 52146 | C19: 1RUH3 | D19: BANCO SANTANDER BRASIL SA | E19: 8248767760 | F19: 1RUH3019582013 | G19: 260 | H19: 212.19 | I19: CONTRATUAL | J19: 5950466730 | K19: ZULMA FLORES BLANCO QUEIROZ | L19: SÃO GONÇALO | M19: RJ | N19: SERGIANA | O19: JA POSSUI | R19: AUTORIZADO PAGAMENTO | S19: 8202610727 | T19: 5 DIAS ÚTEIS | U19: 46027 | V19: 46028 | W19: 46035 | X19: 46031 | Y19: =IF(AND(X19<>"",W19<>""),IF(X19<=W19,"SIM","NÃO"),"") | AC19: =IF($C19="","",IF(COUNTIF('Códigos Santander (ref)'!$A$2:$A$79,$C19)>0,"SANTANDER",IF(COUNTIF('Códigos Itaú (ref)'!$A$2:$A$44,$C19)>0,"ITAU",IF(AND(TRIM(UPPER($I19))="CONTRATUAL",ISNUMBER(SEARCH("INDIVIDUAL",SUBSTITUTE(UPPER($D19)," ","")))),"PREMIUM FREE",""))))
A20: TELA | B20: 51903 | C20: 1RUH3 | D20: BANCO SANTANDER BRASIL SA | E20: 1498442714 | F20: 1RUH3030007038 | G20: 260 | H20: 212.19 | I20: CONTRATUAL | J20: 229031781 | K20: LEONARDO LIMA BITTENCOURT COSTA | L20: SÃO GONÇALO | M20: RJ | N20: SERGIANA | O20: JA POSSUI | R20: AUTORIZADO PAGAMENTO | S20: 8202610730 | T20: 5 DIAS ÚTEIS | U20: 46027 | V20: 46028 | W20: 46035 | X20: 46031 | Y20: =IF(AND(X20<>"",W20<>""),IF(X20<=W20,"SIM","NÃO"),"") | AC20: =IF($C20="","",IF(COUNTIF('Códigos Santander (ref)'!$A$2:$A$79,$C20)>0,"SANTANDER",IF(COUNTIF('Códigos Itaú (ref)'!$A$2:$A$44,$C20)>0,"ITAU",IF(AND(TRIM(UPPER($I20))="CONTRATUAL",ISNUMBER(SEARCH("INDIVIDUAL",SUBSTITUTE(UPPER($D20)," ","")))),"PREMIUM FREE",""))))
A21: TELA | B21: 52425 | C21: S21FQ | D21: SANTANDER SERVICOS DIGITAIS BRASIL LTDA | E21: 21400310830 | F21: S21FQ000899011 | G21: 250 | H21: 212.19 | I21: CONTRATUAL | J21: 11186762896 | K21: ANA CLAUDIA GUIMARAES COSTA | L21: CAMPINAS | M21: SP | N21: SERGIANA | O21: JA POSSUI | R21: AUTORIZADO PAGAMENTO | S21: 8202610733 | T21: 5 DIAS ÚTEIS | U21: 46027 | V21: 46028 | W21: 46035 | X21: 46031 | Y21: =IF(AND(X21<>"",W21<>""),IF(X21<=W21,"SIM","NÃO"),"") | AC21: =IF($C21="","",IF(COUNTIF('Códigos Santander (ref)'!$A$2:$A$79,$C21)>0,"SANTANDER",IF(COUNTIF('Códigos Itaú (ref)'!$A$2:$A$44,$C21)>0,"ITAU",IF(AND(TRIM(UPPER($I21))="CONTRATUAL",ISNUMBER(SEARCH("INDIVIDUAL",SUBSTITUTE(UPPER($D21)," ","")))),"PREMIUM FREE",""))))
A22: TELA | B22: 52646 | C22: S21FQ | D22: SANTANDER SERVICOS DIGITAIS BRASIL LTDA | E22: 21400310830 | F22: S21FQ000899011 | G22: 250 | H22: 212.19 | I22: CONTRATUAL | J22: 11186762896 | K22: ANA CLAUDIA GUIMARAES COSTA | L22: CAMPINAS | M22: SP | N22: SERGIANA | O22: JA POSSUI | R22: AUTORIZADO PAGAMENTO | S22: 8202610734 | T22: 5 DIAS ÚTEIS | U22: 46027 | V22: 46028 | W22: 46035 | X22: 46031 | Y22: =IF(AND(X22<>"",W22<>""),IF(X22<=W22,"SIM","NÃO"),"") | AC22: =IF($C22="","",IF(COUNTIF('Códigos Santander (ref)'!$A$2:$A$79,$C22)>0,"SANTANDER",IF(COUNTIF('Códigos Itaú (ref)'!$A$2:$A$44,$C22)>0,"ITAU",IF(AND(TRIM(UPPER($I22))="CONTRATUAL",ISNUMBER(SEARCH("INDIVIDUAL",SUBSTITUTE(UPPER($D22)," ","")))),"PREMIUM FREE",""))))
A23: TELA | B23: 52669 | C23: 1RUH3 | D23: BANCO SANTANDER BRASIL SA | E23: 2243809745 | F23: 1RU55000339024 | G23: 260 | H23: 90.94 | I23: CONTRATUAL | J23: 5950466730 | K23: ZULMA FLORES BLANCO QUEIROZ | L23: SÃO GONÇALO | M23: RJ | N23: SERGIANA | O23: JA POSSUI | R23: AUTORIZADO PAGAMENTO | S23: 8202610787 | T23: 5 DIAS ÚTEIS | U23: 46028 | V23: 46028 | W23: 46035 | X23: 46036 | Y23: =IF(AND(X23<>"",W23<>""),IF(X23<=W23,"SIM","NÃO"),"") | AC23: =IF($C23="","",IF(COUNTIF('Códigos Santander (ref)'!$A$2:$A$79,$C23)>0,"SANTANDER",IF(COUNTIF('Códigos Itaú (ref)'!$A$2:$A$44,$C23)>0,"ITAU",IF(AND(TRIM(UPPER($I23))="CONTRATUAL",ISNUMBER(SEARCH("INDIVIDUAL",SUBSTITUTE(UPPER($D23)," ","")))),"PREMIUM FREE",""))))
A24: TELA | B24: 52668 | C24: 1RUH3 | D24: BANCO SANTANDER BRASIL SA | E24: 2243809745 | F24: 1RU55000339016 | G24: 260 | H24: 90.94 | I24: CONTRATUAL | J24: 5950466730 | K24: ZULMA FLORES BLANCO QUEIROZ | L24: SÃO GONÇALO | M24: RJ | N24: SERGIANA | O24: JA POSSUI | R24: AUTORIZADO PAGAMENTO | S24: 8202610789 | T24: 5 DIAS ÚTEIS | U24: 46028 | V24: 46028 | W24: 46035 | X24: 46036 | Y24: =IF(AND(X24<>"",W24<>""),IF(X24<=W24,"SIM","NÃO"),"") | AC24: =IF($C24="","",IF(COUNTIF('Códigos Santander (ref)'!$A$2:$A$79,$C24)>0,"SANTANDER",IF(COUNTIF('Códigos Itaú (ref)'!$A$2:$A$44,$C24)>0,"ITAU",IF(AND(TRIM(UPPER($I24))="CONTRATUAL",ISNUMBER(SEARCH("INDIVIDUAL",SUBSTITUTE(UPPER($D24)," ","")))),"PREMIUM FREE",""))))
A25: TELA | B25: 52705 | C25: 1RSLN | D25: ITAU UNIBANCO SA | E25: 80214789772 | F25: 1RSLN015975002 | G25: 10100 | H25: 6999.98 | I25: CONTRATUAL | J25: 8186777750 | K25: FERNANDO CAMPOS MOREIRA | L25: SÃO GONÇALO | M25: RJ | N25: SERGIANA | O25: JA POSSUI | R25: AUTORIZADO PAGAMENTO | S25: 8202610790 | T25: 5 DIAS ÚTEIS | U25: 46028 | V25: 46028 | W25: 46035 | X25: 46036 | Y25: =IF(AND(X25<>"",W25<>""),IF(X25<=W25,"SIM","NÃO"),"") | AC25: =IF($C25="","",IF(COUNTIF('Códigos Santander (ref)'!$A$2:$A$79,$C25)>0,"SANTANDER",IF(COUNTIF('Códigos Itaú (ref)'!$A$2:$A$44,$C25)>0,"ITAU",IF(AND(TRIM(UPPER($I25))="CONTRATUAL",ISNUMBER(SEARCH("INDIVIDUAL",SUBSTITUTE(UPPER($D25)," ","")))),"PREMIUM FREE",""))))
A26: TELA | B26: 52339 | C26: 1RUH3 | D26: BANCO SANTANDER BRASIL SA | E26: 29459620809 | F26: 1RUH3037701002 | G26: 150 | H26: 9.91 | I26: CONTRATUAL | J26: 24463831000168 | K26: CLINICA RADIOLOGICA DIAGNOSTIC DENTE LTDA | L26: EMBU-GUAÇU | M26: SP | N26: SERGIANA | O26: 520555 | P26: 46028 | Q26: 46029 | R26: AUTORIZADO PAGAMENTO | S26: 8202610809 | T26: 5 DIAS ÚTEIS | U26: 46028 | V26: 46029 | W26: 46036 | X26: 46036 | Y26: =IF(AND(X26<>"",W26<>""),IF(X26<=W26,"SIM","NÃO"),"") | AC26: =IF($C26="","",IF(COUNTIF('Códigos Santander (ref)'!$A$2:$A$79,$C26)>0,"SANTANDER",IF(COUNTIF('Códigos Itaú (ref)'!$A$2:$A$44,$C26)>0,"ITAU",IF(AND(TRIM(UPPER($I26))="CONTRATUAL",ISNUMBER(SEARCH("INDIVIDUAL",SUBSTITUTE(UPPER($D26)," ","")))),"PREMIUM FREE",""))))
A27: TELA | B27: 52174 | C27: 1RSX8 | D27: ITAU UNIBANCO SA | E27: 50361414749 | F27: 1RSX8000316008 | G27: 1550 | H27: 691.99 | I27: CONTRATUAL | J27: 7959716722 | K27: JULIANA VIEGAS SONEGHETI | L27: NITEROI | M27: RJ | N27: SERGIANA | O27: JA POSSUI | R27: AUTORIZADO PAGAMENTO | S27: 8202610791 | T27: 5 DIAS ÚTEIS | U27: 46028 | V27: 46028 | W27: 46035 | X27: 46036 | Y27: =IF(AND(X27<>"",W27<>""),IF(X27<=W27,"SIM","NÃO"),"") | AC27: =IF($C27="","",IF(COUNTIF('Códigos Santander (ref)'!$A$2:$A$79,$C27)>0,"SANTANDER",IF(COUNTIF('Códigos Itaú (ref)'!$A$2:$A$44,$C27)>0,"ITAU",IF(AND(TRIM(UPPER($I27))="CONTRATUAL",ISNUMBER(SEARCH("INDIVIDUAL",SUBSTITUTE(UPPER($D27)," ","")))),"PREMIUM FREE",""))))
A28: SAC | B28: 51910 | C28: 0GE92 | D28: CRUZEIRO DO SUL EDUCACIONAL SA | E28: 10708058663 | F28: 0GE92005427010 | G28: 1500 | H28: 1500 | I28: INSUFICIÊNCIA DE REDE | J28: 59327485000175 | K28: PASTRE ODONTOLOGIA | L28: ANDRADAS | M28: MG | N28: SERGIANA | O28: 520563 | P28: 46028 | Q28: 46029 | R28: AUTORIZADO PAGAMENTO | S28: 8202610811 | T28: 30 DIAS CORRIDOS | U28: 46028 | V28: 46029 | W28: 46067 | X28: 46036 | Y28: =IF(AND(X28<>"",W28<>""),IF(X28<=W28,"SIM","NÃO"),"") | AC28: =IF($C28="","",IF(COUNTIF('Códigos Santander (ref)'!$A$2:$A$79,$C28)>0,"SANTANDER",IF(COUNTIF('Códigos Itaú (ref)'!$A$2:$A$44,$C28)>0,"ITAU",IF(AND(TRIM(UPPER($I28))="CONTRATUAL",ISNUMBER(SEARCH("INDIVIDUAL",SUBSTITUTE(UPPER($D28)," ","")))),"PREMIUM FREE",""))))
A29: TELA | B29: 51867 | C29: 1RSLY | D29: ITAU SEGUROS SA | E29: 62422758720 | F29: 1RSLY000039004 | G29: 430 | H29: 239.99 | I29: CONTRATUAL | J29: 40465008000148 | K29: ALFA ODONTO FACIAL LTDA | L29: CABO FRIO | M29: RJ | N29: SERGIANA | O29: 520607 | P29: 46028 | Q29: 46029 | R29: AUTORIZADO PAGAMENTO | S29: 8202610816 | T29: 5 DIAS ÚTEIS | U29: 46028 | V29: 46029 | W29: 46036 | X29: 46036 | Y29: =IF(AND(X29<>"",W29<>""),IF(X29<=W29,"SIM","NÃO"),"") | AC29: =IF($C29="","",IF(COUNTIF('Códigos Santander (ref)'!$A$2:$A$79,$C29)>0,"SANTANDER",IF(COUNTIF('Códigos Itaú (ref)'!$A$2:$A$44,$C29)>0,"ITAU",IF(AND(TRIM(UPPER($I29))="CONTRATUAL",ISNUMBER(SEARCH("INDIVIDUAL",SUBSTITUTE(UPPER($D29)," ","")))),"PREMIUM FREE",""))))
A30: TELA | B30: 52630 | C30: 1RUH3 | D30: BANCO SANTANDER BRASIL SA | E30: 46992730843 | F30: 1RUH3006876021 | G30: 150 | H30: 150 | I30: CONTRATUAL | J30: 37710114857 | K30: LARISSA SANDY DA SILVA LEITE | L30: CRUZEIRO | M30: SP | N30: SERGIANA | O30: JA POSSUI | R30: AUTORIZADO PAGAMENTO | S30: 8202610840 | T30: 5 DIAS ÚTEIS | U30: 46028 | V30: 46029 | W30: 46036 | X30: 46036 | Y30: =IF(AND(X30<>"",W30<>""),IF(X30<=W30,"SIM","NÃO"),"") | AC30: =IF($C30="","",IF(COUNTIF('Códigos Santander (ref)'!$A$2:$A$79,$C30)>0,"SANTANDER",IF(COUNTIF('Códigos Itaú (ref)'!$A$2:$A$44,$C30)>0,"ITAU",IF(AND(TRIM(UPPER($I30))="CONTRATUAL",ISNUMBER(SEARCH("INDIVIDUAL",SUBSTITUTE(UPPER($D30)," ","")))),"PREMIUM FREE",""))))
A31: TELA | B31: 52685 | C31: 1RUH3 | D31: BANCO SANTANDER BRASIL SA | E31: 4053432138 | F31: 1RUH3010105000 | G31: 260 | H31: 181.88 | I31: CONTRATUAL | J31: 236694111 | K31: CRISTIANE KAMINSK | L31: JUARA | M31: MT | N31: SERGIANA | O31: JA POSSUI | R31: AUTORIZADO PAGAMENTO | S31: 8202610842 | T31: 5 DIAS ÚTEIS | U31: 46029 | V31: 46029 | W31: 46036 | X31: 46036 | Y31: =IF(AND(X31<>"",W31<>""),IF(X31<=W31,"SIM","NÃO"),"") | AC31: =IF($C31="","",IF(COUNTIF('Códigos Santander (ref)'!$A$2:$A$79,$C31)>0,"SANTANDER",IF(COUNTIF('Códigos Itaú (ref)'!$A$2:$A$44,$C31)>0,"ITAU",IF(AND(TRIM(UPPER($I31))="CONTRATUAL",ISNUMBER(SEARCH("INDIVIDUAL",SUBSTITUTE(UPPER($D31)," ","")))),"PREMIUM FREE",""))))
A32: TELA | B32: 52369 | C32: 1RUH3 | D32: BANCO SANTANDER BRASIL SA | E32: 48016311857 | F32: 1RUH3000218006 | G32: 250 | H32: 51.03 | I32: CONTRATUAL | J32: 46682363000155 | K32: AMEISI ODONTOLOGIA LTDA | L32: SÃO PAULO | M32: SP | N32: SERGIANA | O32: 520673 | P32: 46029 | Q32: 46029 | R32: AUTORIZADO PAGAMENTO | S32: 8202610942 | T32: 5 DIAS ÚTEIS | U32: 46029 | V32: 46031 | W32: 46038 | X32: 46036 | Y32: =IF(AND(X32<>"",W32<>""),IF(X32<=W32,"SIM","NÃO"),"") | AC32: =IF($C32="","",IF(COUNTIF('Códigos Santander (ref)'!$A$2:$A$79,$C32)>0,"SANTANDER",IF(COUNTIF('Códigos Itaú (ref)'!$A$2:$A$44,$C32)>0,"ITAU",IF(AND(TRIM(UPPER($I32))="CONTRATUAL",ISNUMBER(SEARCH("INDIVIDUAL",SUBSTITUTE(UPPER($D32)," ","")))),"PREMIUM FREE",""))))
A33: TELA | B33: 52410 | C33: 60300 | D33: INDIVIDUAL | E33: 2573627543 | F33: 60300897827024 | G33: 70 | H33: 7.5 | I33: CONTRATUAL | J33: 1142614581 | K33: JEANE DANTAS DE MENEZES VIANA | L33: ARACAJU | M33: SE | N33: SERGIANA | O33: 520682 | P33: 46029 | Q33: 46030 | R33: AUTORIZADO PAGAMENTO | S33: 8202610885 | T33: 30 DIAS CORRIDOS | U33: 46029 | V33: 46031 | W33: 46062 | X33: 46036 | Y33: =IF(AND(X33<>"",W33<>""),IF(X33<=W33,"SIM","NÃO"),"") | AC33: =IF($C33="","",IF(COUNTIF('Códigos Santander (ref)'!$A$2:$A$79,$C33)>0,"SANTANDER",IF(COUNTIF('Códigos Itaú (ref)'!$A$2:$A$44,$C33)>0,"ITAU",IF(AND(TRIM(UPPER($I33))="CONTRATUAL",ISNUMBER(SEARCH("INDIVIDUAL",SUBSTITUTE(UPPER($D33)," ","")))),"PREMIUM FREE",""))))
A34: TELA | B34: 51664 | C34: 1RUH3 | D34: BANCO SANTANDER BRASIL SA | E34: 33555194801 | F34: 1RUH3036142000 | G34: 450 | H34: 312.27 | I34: CONTRATUAL | J34: 24870458000160 | K34: EDWAL LOBOSCHI | L34: SÃO PAULO | M34: SP | N34: SERGIANA | O34: JA POSSUI | R34: AUTORIZADO PAGAMENTO | S34: 8202610941 | T34: 5 DIAS ÚTEIS | U34: 46029 | V34: 46030 | W34: 46037 | X34: 46036 | Y34: =IF(AND(X34<>"",W34<>""),IF(X34<=W34,"SIM","NÃO"),"") | AC34: =IF($C34="","",IF(COUNTIF('Códigos Santander (ref)'!$A$2:$A$79,$C34)>0,"SANTANDER",IF(COUNTIF('Códigos Itaú (ref)'!$A$2:$A$44,$C34)>0,"ITAU",IF(AND(TRIM(UPPER($I34))="CONTRATUAL",ISNUMBER(SEARCH("INDIVIDUAL",SUBSTITUTE(UPPER($D34)," ","")))),"PREMIUM FREE",""))))
A35: TELA | B35: 52387 | C35: 1RU51 | D35: BANCO SANTANDER BRASIL SA | E35: 3526964866 | F35: 1RU51000389005 | G35: 2120 | H35: 1595.11 | I35: CONTRATUAL | J35: 67069282672 | K35: LEONE RIBEIRO DE ALMEIDA | L35: SÃO PAULO | M35: SP | N35: SERGIANA | O35: JA POSSUI | R35: AUTORIZADO PAGAMENTO | S35: 8202610847 | T35: 5 DIAS ÚTEIS | U35: 46029 | V35: 46029 | W35: 46036 | X35: 46036 | Y35: =IF(AND(X35<>"",W35<>""),IF(X35<=W35,"SIM","NÃO"),"") | AC35: =IF($C35="","",IF(COUNTIF('Códigos Santander (ref)'!$A$2:$A$79,$C35)>0,"SANTANDER",IF(COUNTIF('Códigos Itaú (ref)'!$A$2:$A$44,$C35)>0,"ITAU",IF(AND(TRIM(UPPER($I35))="CONTRATUAL",ISNUMBER(SEARCH("INDIVIDUAL",SUBSTITUTE(UPPER($D35)," ","")))),"PREMIUM FREE",""))))
A36: TELA | B36: 52611 | C36: 1RUH3 | D36: BANCO SANTANDER BRASIL SA | E36: 14580526805 | F36: 1RUH3030679036 | G36: 180 | H36: 124.6 | I36: CONTRATUAL | J36: 27364022864 | K36: ANA CAROLINA RIZZO | L36: BOTUCATU | M36: SP | N36: SERGIANA | O36: JA POSSUI | R36: AUTORIZADO PAGAMENTO | S36: 8202610848 | T36: 5 DIAS ÚTEIS | U36: 46029 | V36: 46029 | W36: 46036 | X36: 46036 | Y36: =IF(AND(X36<>"",W36<>""),IF(X36<=W36,"SIM","NÃO"),"") | AC36: =IF($C36="","",IF(COUNTIF('Códigos Santander (ref)'!$A$2:$A$79,$C36)>0,"SANTANDER",IF(COUNTIF('Códigos Itaú (ref)'!$A$2:$A$44,$C36)>0,"ITAU",IF(AND(TRIM(UPPER($I36))="CONTRATUAL",ISNUMBER(SEARCH("INDIVIDUAL",SUBSTITUTE(UPPER($D36)," ","")))),"PREMIUM FREE",""))))
A37: TELA | B37: 52765 | C37: 1RUH3 | D37: BANCO SANTANDER BRASIL SA | E37: 2635116776 | F37: 1RUH3032448023 | G37: 730 | H37: 397.34 | I37: CONTRATUAL | J37: 5187127705 | K37: LUCINDA MERCEDES CORDEIRO DE VASCONCELOS OLIVEIRA | L37: SÃO GONÇALO | M37: RJ | N37: SERGIANA | O37: JA POSSUI | R37: AUTORIZADO PAGAMENTO | S37: 8202610918 | T37: 5 DIAS ÚTEIS | U37: 46029 | V37: 46030 | W37: 46037 | X37: 46036 | Y37: =IF(AND(X37<>"",W37<>""),IF(X37<=W37,"SIM","NÃO"),"") | AC37: =IF($C37="","",IF(COUNTIF('Códigos Santander (ref)'!$A$2:$A$79,$C37)>0,"SANTANDER",IF(COUNTIF('Códigos Itaú (ref)'!$A$2:$A$44,$C37)>0,"ITAU",IF(AND(TRIM(UPPER($I37))="CONTRATUAL",ISNUMBER(SEARCH("INDIVIDUAL",SUBSTITUTE(UPPER($D37)," ","")))),"PREMIUM FREE",""))))
A38: TELA | B38: 52613 | C38: 1RUH3 | D38: BANCO SANTANDER BRASIL SA | E38: 26447218811 | F38: 1RUH3032093004 | G38: 200 | H38: 200 | I38: CONTRATUAL | J38: 5389120000146 | K38: K N SERVICOS MEDICOS E ODONTOLOGICOS S/S LTDA | L38: JACAREÍ | M38: SP | N38: SERGIANA | O38: JA POSSUI | R38: AUTORIZADO PAGAMENTO | S38: 8202610919 | T38: 5 DIAS ÚTEIS | U38: 46029 | V38: 46030 | W38: 46037 | X38: 46036 | Y38: =IF(AND(X38<>"",W38<>""),IF(X38<=W38,"SIM","NÃO"),"") | AC38: =IF($C38="","",IF(COUNTIF('Códigos Santander (ref)'!$A$2:$A$79,$C38)>0,"SANTANDER",IF(COUNTIF('Códigos Itaú (ref)'!$A$2:$A$44,$C38)>0,"ITAU",IF(AND(TRIM(UPPER($I38))="CONTRATUAL",ISNUMBER(SEARCH("INDIVIDUAL",SUBSTITUTE(UPPER($D38)," ","")))),"PREMIUM FREE",""))))
A39: TELA | B39: 51385 | C39: 1RSLN | D39: ITAU UNIBANCO SA | E39: 710685700 | F39: 1RSLN018578004 | G39: 1200 | H39: 1200 | I39: CONTRATUAL | J39: 11564355799 | K39: PILLAR CORREA SILVA SARDINHA | L39: CAMPO DOS GOYTACAZES | M39: RJ | N39: SERGIANA | O39: 520940 | P39: 46030 | Q39: 46030 | R39: AUTORIZADO PAGAMENTO | S39: 8202610922 | T39: 5 DIAS ÚTEIS | U39: 46030 | V39: 46030 | W39: 46037 | X39: 46036 | Y39: =IF(AND(X39<>"",W39<>""),IF(X39<=W39,"SIM","NÃO"),"") | AC39: =IF($C39="","",IF(COUNTIF('Códigos Santander (ref)'!$A$2:$A$79,$C39)>0,"SANTANDER",IF(COUNTIF('Códigos Itaú (ref)'!$A$2:$A$44,$C39)>0,"ITAU",IF(AND(TRIM(UPPER($I39))="CONTRATUAL",ISNUMBER(SEARCH("INDIVIDUAL",SUBSTITUTE(UPPER($D39)," ","")))),"PREMIUM FREE",""))))
A40: NIP | B40: 52687 | C40: WXJ2I | D40: HC CONSULTORIA EM GESTAO EMPRESARIAL E AMBIENTAL LTDA | E40: 335513247 | F40: WXJ2I000025003 | G40: 180 | H40: 180 | I40: COBRANÇA INDEVIDA | J40: 32884766000172 | K40: KELLY LEOPOLDINA SOARES FILGUEIRAS COSTA | L40: MANAUS | M40: AM | N40: CIBELY | O40: 520976 | P40: 46030 | Q40: 46030 | R40: AUTORIZADO PAGAMENTO | S40: 8202610923 | T40: 30 DIAS CORRIDOS | U40: 46030 | V40: 46030 | W40: 46061 | X40: 46036 | Y40: =IF(AND(X40<>"",W40<>""),IF(X40<=W40,"SIM","NÃO"),"") | AC40: =IF($C40="","",IF(COUNTIF('Códigos Santander (ref)'!$A$2:$A$79,$C40)>0,"SANTANDER",IF(COUNTIF('Códigos Itaú (ref)'!$A$2:$A$44,$C40)>0,"ITAU",IF(AND(TRIM(UPPER($I40))="CONTRATUAL",ISNUMBER(SEARCH("INDIVIDUAL",SUBSTITUTE(UPPER($D40)," ","")))),"PREMIUM FREE",""))))
A41: TELA | B41: 52405 | C41: 1RUH3 | D41: BANCO SANTANDER BRASIL SA | E41: 48014401859 | F41: 1RUH3003197000 | G41: 250 | H41: 14.58 | I41: CONTRATUAL | J41: 46682363000155 | K41: AMEISI ODONTOLOGIA LTDA | L41: SÃO PAULO | M41: SP | N41: SERGIANA | O41: 521027 | P41: 46030 | Q41: 46030 | R41: AUTORIZADO PAGAMENTO | S41: 8202610924 | T41: 5 DIAS ÚTEIS | U41: 46030 | V41: 46030 | W41: 46037 | X41: 46036 | Y41: =IF(AND(X41<>"",W41<>""),IF(X41<=W41,"SIM","NÃO"),"") | AC41: =IF($C41="","",IF(COUNTIF('Códigos Santander (ref)'!$A$2:$A$79,$C41)>0,"SANTANDER",IF(COUNTIF('Códigos Itaú (ref)'!$A$2:$A$44,$C41)>0,"ITAU",IF(AND(TRIM(UPPER($I41))="CONTRATUAL",ISNUMBER(SEARCH("INDIVIDUAL",SUBSTITUTE(UPPER($D41)," ","")))),"PREMIUM FREE",""))))
A42: TELA | B42: 50493 | C42: 1RUH3 | D42: BANCO SANTANDER BRASIL SA | E42: 28475431801 | F42: 1RUH3031318010 | G42: 500 | H42: 267.6 | I42: CONTRATUAL | J42: 22259762875 | K42: ANELENA SIMOES BRAGHIROLI | L42: SÃO JOSÉ DO RIO PARDO | M42: SP | N42: SERGIANA | O42: JA POSSUI | R42: AUTORIZADO PAGAMENTO | S42: 8202610921 | T42: 5 DIAS ÚTEIS | U42: 46030 | V42: 46030 | W42: 46037 | X42: 46036 | Y42: =IF(AND(X42<>"",W42<>""),IF(X42<=W42,"SIM","NÃO"),"") | AC42: =IF($C42="","",IF(COUNTIF('Códigos Santander (ref)'!$A$2:$A$79,$C42)>0,"SANTANDER",IF(COUNTIF('Códigos Itaú (ref)'!$A$2:$A$44,$C42)>0,"ITAU",IF(AND(TRIM(UPPER($I42))="CONTRATUAL",ISNUMBER(SEARCH("INDIVIDUAL",SUBSTITUTE(UPPER($D42)," ","")))),"PREMIUM FREE",""))))
A43: NIP | B43: 52785 | C43: 0700D | D43: I N D I V I D U A L | E43: 1237725160 | F43: 0700D768248005 | G43: 645.76 | H43: 645.76 | I43: CONTRATUAL | J43: 4898593135 | K43: LETICIA CRISTINA MORAIS SOUZA | L43: ANICUNS | M43: GO | N43: CIBELY | O43: 521118 | P43: 46030 | Q43: 46030 | R43: AUTORIZADO PAGAMENTO | S43: 8202610934 | T43: 30 DIAS CORRIDOS | U43: 46030 | V43: 46031 | W43: 46062 | X43: 46036 | Y43: =IF(AND(X43<>"",W43<>""),IF(X43<=W43,"SIM","NÃO"),"") | AC43: =IF($C43="","",IF(COUNTIF('Códigos Santander (ref)'!$A$2:$A$79,$C43)>0,"SANTANDER",IF(COUNTIF('Códigos Itaú (ref)'!$A$2:$A$44,$C43)>0,"ITAU",IF(AND(TRIM(UPPER($I43))="CONTRATUAL",ISNUMBER(SEARCH("INDIVIDUAL",SUBSTITUTE(UPPER($D43)," ","")))),"PREMIUM FREE",""))))
A44: TELA | B44: 51303 | C44: 60300 | D44: I N D I V I D U A L | E44: 33700078862 | F44: 60300916837012 | G44: 90 | H44: 45 | I44: CONTRATUAL | J44: 5456361000160 | K44: INSTITUTO SAO LUCAS DE RADIOLOGIA | L44: SÃO CARLOS | M44: SP | N44: SERGIANA | O44: 521261 | P44: 46031 | Q44: 46034 | R44: AUTORIZADO PAGAMENTO | S44: 8202611069 | T44: 30 DIAS CORRIDOS | U44: 46030 | V44: 46034 | W44: 46065 | X44: 46038 | Y44: =IF(AND(X44<>"",W44<>""),IF(X44<=W44,"SIM","NÃO"),"") | AC44: =IF($C44="","",IF(COUNTIF('Códigos Santander (ref)'!$A$2:$A$79,$C44)>0,"SANTANDER",IF(COUNTIF('Códigos Itaú (ref)'!$A$2:$A$44,$C44)>0,"ITAU",IF(AND(TRIM(UPPER($I44))="CONTRATUAL",ISNUMBER(SEARCH("INDIVIDUAL",SUBSTITUTE(UPPER($D44)," ","")))),"PREMIUM FREE",""))))
A45: TELA | B45: 52806 | C45: 1RUH3 | D45: BANCO SANTANDER BRASIL SA | E45: 4898151892 | F45: 1RUH3036902004 | G45: 370 | H45: 243.88 | I45: CONTRATUAL | J45: 24870458000160 | K45: EDWAL LOBOSCHI | L45: SÃO PAULO | M45: SP | N45: SERGIANA | O45: JA POSSUI | R45: AUTORIZADO PAGAMENTO | S45: 8202610943 | T45: 5 DIAS ÚTEIS | U45: 46031 | V45: 46031 | W45: 46038 | X45: 46036 | Y45: =IF(AND(X45<>"",W45<>""),IF(X45<=W45,"SIM","NÃO"),"") | AC45: =IF($C45="","",IF(COUNTIF('Códigos Santander (ref)'!$A$2:$A$79,$C45)>0,"SANTANDER",IF(COUNTIF('Códigos Itaú (ref)'!$A$2:$A$44,$C45)>0,"ITAU",IF(AND(TRIM(UPPER($I45))="CONTRATUAL",ISNUMBER(SEARCH("INDIVIDUAL",SUBSTITUTE(UPPER($D45)," ","")))),"PREMIUM FREE",""))))
A46: TELA | B46: 52688 | C46: 1RUB1 | D46: F1RST TECNOLOGIA E INOVACAO LTDA | E46: 35353181816 | F46: 1RUB1001483013 | G46: 230 | H46: 192.85 | I46: CONTRATUAL | J46: 22733506862 | K46: THAIS SIMONE ELIAS | L46: SÃO BERNARDO DO CAMPO | M46: SP | N46: SERGIANA | O46: JA POSSUI | R46: AUTORIZADO PAGAMENTO | S46: 8202611071 | T46: 5 DIAS ÚTEIS | U46: 46031 | V46: 46034 | W46: 46041 | X46: 46038 | Y46: =IF(AND(X46<>"",W46<>""),IF(X46<=W46,"SIM","NÃO"),"") | AC46: =IF($C46="","",IF(COUNTIF('Códigos Santander (ref)'!$A$2:$A$79,$C46)>0,"SANTANDER",IF(COUNTIF('Códigos Itaú (ref)'!$A$2:$A$44,$C46)>0,"ITAU",IF(AND(TRIM(UPPER($I46))="CONTRATUAL",ISNUMBER(SEARCH("INDIVIDUAL",SUBSTITUTE(UPPER($D46)," ","")))),"PREMIUM FREE",""))))
A47: TELA | B47: 28861 | C47: 0700G | D47: I N D I V I D U A L | E47: 9512446120 | F47: 0700G664775002 | G47: 2000 | H47: 156 | I47: CONTRATUAL | J47: 4340252166 | K47: JOÃO VICTOR ROMUALDO CAVALCANTE | L47: SANCLERLÂNDIA | M47: GO | N47: SERGIANA | O47: 521363 | P47: 46031 | Q47: 46034 | R47: AUTORIZADO PAGAMENTO | S47: 8202611072 | T47: 30 DIAS CORRIDOS | U47: 46031 | V47: 46034 | W47: 46065 | X47: 46038 | Y47: =IF(AND(X47<>"",W47<>""),IF(X47<=W47,"SIM","NÃO"),"") | AC47: =IF($C47="","",IF(COUNTIF('Códigos Santander (ref)'!$A$2:$A$79,$C47)>0,"SANTANDER",IF(COUNTIF('Códigos Itaú (ref)'!$A$2:$A$44,$C47)>0,"ITAU",IF(AND(TRIM(UPPER($I47))="CONTRATUAL",ISNUMBER(SEARCH("INDIVIDUAL",SUBSTITUTE(UPPER($D47)," ","")))),"PREMIUM FREE",""))))
A48: TELA | B48: 52233 | C48: 1RUH3 | D48: BANCO SANTANDER BRASIL SA | E48: 17612779870 | F48: 1RUH3027278018 | G48: 950 | H48: 391.95 | I48: CONTRATUAL | J48: 24870458000160 | K48: EDWAL LOBOSCHI | L48: SÃO PAULO | M48: SP | N48: SERGIANA | O48: JA POSSUI | R48: AUTORIZADO PAGAMENTO | S48: 8202610944 | T48: 5 DIAS ÚTEIS | U48: 46031 | V48: 46031 | W48: 46038 | X48: 46036 | Y48: =IF(AND(X48<>"",W48<>""),IF(X48<=W48,"SIM","NÃO"),"") | AC48: =IF($C48="","",IF(COUNTIF('Códigos Santander (ref)'!$A$2:$A$79,$C48)>0,"SANTANDER",IF(COUNTIF('Códigos Itaú (ref)'!$A$2:$A$44,$C48)>0,"ITAU",IF(AND(TRIM(UPPER($I48))="CONTRATUAL",ISNUMBER(SEARCH("INDIVIDUAL",SUBSTITUTE(UPPER($D48)," ","")))),"PREMIUM FREE",""))))
A49: TELA | B49: 52827 | C49: 0700G | D49: I N D I V I D U A L | E49: 1013798201 | F49: 0700G294928017 | G49: 250 | H49: 33.9 | I49: CONTRATUAL | J49: 427256232 | K49: BEATRIZ JATENE OLIVEIRA DE MEDEIROS | L49: BELÉM | M49: PA | N49: SERGIANA | O49: 521864 | P49: 46034 | Q49: 46036 | R49: AUTORIZADO PAGAMENTO | S49: 8202611141 | T49: 30 DIAS CORRIDOS | U49: 46031 | V49: 46036 | W49: 46067 | X49: 46043 | Y49: =IF(AND(X49<>"",W49<>""),IF(X49<=W49,"SIM","NÃO"),"") | AC49: =IF($C49="","",IF(COUNTIF('Códigos Santander (ref)'!$A$2:$A$79,$C49)>0,"SANTANDER",IF(COUNTIF('Códigos Itaú (ref)'!$A$2:$A$44,$C49)>0,"ITAU",IF(AND(TRIM(UPPER($I49))="CONTRATUAL",ISNUMBER(SEARCH("INDIVIDUAL",SUBSTITUTE(UPPER($D49)," ","")))),"PREMIUM FREE",""))))
A50: TELA | B50: 52928 | C50: 1RUGZ | D50: SX TOOLS SOLUC SERV COMPARTILHADOS LTDA | E50: 32684403805 | F50: 1RUGZ000755010 | G50: 139.9 | H50: 90.94 | I50: CONTRATUAL | J50: 22339086000114 | K50: CEORT CLINICA ODONTOLOGICA LTDA | L50: SÃO BERNARDO DO CAMPO | M50: SP | N50: SERGIANA | O50: JA POSSUI | R50: AUTORIZADO PAGAMENTO | S50: 8202611074 | T50: 5 DIAS ÚTEIS | U50: 46034 | V50: 46034 | W50: 46041 | X50: 46038 | Y50: =IF(AND(X50<>"",W50<>""),IF(X50<=W50,"SIM","NÃO"),"") | AC50: =IF($C50="","",IF(COUNTIF('Códigos Santander (ref)'!$A$2:$A$79,$C50)>0,"SANTANDER",IF(COUNTIF('Códigos Itaú (ref)'!$A$2:$A$44,$C50)>0,"ITAU",IF(AND(TRIM(UPPER($I50))="CONTRATUAL",ISNUMBER(SEARCH("INDIVIDUAL",SUBSTITUTE(UPPER($D50)," ","")))),"PREMIUM FREE",""))))
A51: TELA | B51: 52888 | C51: 1RUH3 | D51: BANCO SANTANDER BRASIL SA | E51: 2635116776 | F51: 1RUH3032448015 | G51: 260 | H51: 212.19 | I51: CONTRATUAL | J51: 5950466730 | K51: ZULMA FLORES BLANCO QUEIROZ | L51: SÃO GONÇALO | M51: RJ | N51: SERGIANA | O51: JA POSSUI | R51: AUTORIZADO PAGAMENTO | S51: 8202611076 | T51: 5 DIAS ÚTEIS | U51: 46034 | V51: 46034 | W51: 46041 | X51: 46038 | Y51: =IF(AND(X51<>"",W51<>""),IF(X51<=W51,"SIM","NÃO"),"") | AC51: =IF($C51="","",IF(COUNTIF('Códigos Santander (ref)'!$A$2:$A$79,$C51)>0,"SANTANDER",IF(COUNTIF('Códigos Itaú (ref)'!$A$2:$A$44,$C51)>0,"ITAU",IF(AND(TRIM(UPPER($I51))="CONTRATUAL",ISNUMBER(SEARCH("INDIVIDUAL",SUBSTITUTE(UPPER($D51)," ","")))),"PREMIUM FREE",""))))
A52: TELA | B52: 52947 | C52: 1RUH3 | D52: BANCO SANTANDER BRASIL SA | E52: 646044702 | F52: 1RUH3031002005 | G52: 260 | H52: 212.19 | I52: CONTRATUAL | J52: 5950466730 | K52: ZULMA FLORES BLANCO QUEIROZ | L52: SÃO GONÇALO | M52: RJ | N52: SERGIANA | O52: JA POSSUI | R52: AUTORIZADO PAGAMENTO | S52: 8202611077 | T52: 5 DIAS ÚTEIS | U52: 46034 | V52: 46034 | W52: 46041 | X52: 46038 | Y52: =IF(AND(X52<>"",W52<>""),IF(X52<=W52,"SIM","NÃO"),"") | AC52: =IF($C52="","",IF(COUNTIF('Códigos Santander (ref)'!$A$2:$A$79,$C52)>0,"SANTANDER",IF(COUNTIF('Códigos Itaú (ref)'!$A$2:$A$44,$C52)>0,"ITAU",IF(AND(TRIM(UPPER($I52))="CONTRATUAL",ISNUMBER(SEARCH("INDIVIDUAL",SUBSTITUTE(UPPER($D52)," ","")))),"PREMIUM FREE",""))))
A53: TELA | B53: 52927 | C53: 1RUH3 | D53: BANCO SANTANDER BRASIL SA | E53: 8248767760 | F53: 1RUH3019582005 | G53: 260 | H53: 212.19 | I53: CONTRATUAL | J53: 5950466730 | K53: ZULMA FLORES BLANCO QUEIROZ | L53: SÃO GONÇALO | M53: RJ | N53: SERGIANA | O53: JA POSSUI | R53: AUTORIZADO PAGAMENTO | S53: 8202611078 | T53: 5 DIAS ÚTEIS | U53: 46034 | V53: 46034 | W53: 46041 | X53: 46038 | Y53: =IF(AND(X53<>"",W53<>""),IF(X53<=W53,"SIM","NÃO"),"") | AC53: =IF($C53="","",IF(COUNTIF('Códigos Santander (ref)'!$A$2:$A$79,$C53)>0,"SANTANDER",IF(COUNTIF('Códigos Itaú (ref)'!$A$2:$A$44,$C53)>0,"ITAU",IF(AND(TRIM(UPPER($I53))="CONTRATUAL",ISNUMBER(SEARCH("INDIVIDUAL",SUBSTITUTE(UPPER($D53)," ","")))),"PREMIUM FREE",""))))
A54: TELA | B54: 52907 | C54: 1RUH3 | D54: BANCO SANTANDER BRASIL SA | E54: 8248767760 | F54: 1RUH3019582013 | G54: 260 | H54: 212.19 | I54: CONTRATUAL | J54: 5950466730 | K54: ZULMA FLORES BLANCO QUEIROZ | L54: SÃO GONÇALO | M54: RJ | N54: SERGIANA | O54: JA POSSUI | R54: AUTORIZADO PAGAMENTO | S54: 8202611079 | T54: 5 DIAS ÚTEIS | U54: 46034 | V54: 46034 | W54: 46041 | X54: 46038 | Y54: =IF(AND(X54<>"",W54<>""),IF(X54<=W54,"SIM","NÃO"),"") | AC54: =IF($C54="","",IF(COUNTIF('Códigos Santander (ref)'!$A$2:$A$79,$C54)>0,"SANTANDER",IF(COUNTIF('Códigos Itaú (ref)'!$A$2:$A$44,$C54)>0,"ITAU",IF(AND(TRIM(UPPER($I54))="CONTRATUAL",ISNUMBER(SEARCH("INDIVIDUAL",SUBSTITUTE(UPPER($D54)," ","")))),"PREMIUM FREE",""))))
A55: TELA | B55: 52886 | C55: 1RU54 | D55: BANCO SANTANDER BRASIL SA | E55: 93719264815 | F55: 1RU54000109029 | G55: 350 | H55: 243.88 | I55: CONTRATUAL | J55: 24870458000160 | K55: EDWAL LOBOSCHI | L55: SÃO PAULO | M55: SP | N55: SERGIANA | O55: JA POSSUI | R55: AUTORIZADO PAGAMENTO | S55: 8202611080 | T55: 5 DIAS ÚTEIS | U55: 46034 | V55: 46034 | W55: 46041 | X55: 46038 | Y55: =IF(AND(X55<>"",W55<>""),IF(X55<=W55,"SIM","NÃO"),"") | AC55: =IF($C55="","",IF(COUNTIF('Códigos Santander (ref)'!$A$2:$A$79,$C55)>0,"SANTANDER",IF(COUNTIF('Códigos Itaú (ref)'!$A$2:$A$44,$C55)>0,"ITAU",IF(AND(TRIM(UPPER($I55))="CONTRATUAL",ISNUMBER(SEARCH("INDIVIDUAL",SUBSTITUTE(UPPER($D55)," ","")))),"PREMIUM FREE",""))))
A56: TELA | B56: 52606 | C56: 1RUH3 | D56: BANCO SANTANDER BRASIL SA | E56: 15858127819 | F56: 1RUH3030565030 | G56: 840 | H56: 278.25 | I56: CONTRATUAL | J56: 4435078000190 | K56: RH RADIOLOGIA E DOCUMENTACAO ODONTOLOGICA SS LTDA | L56: LONDRINA | M56: PR | N56: SERGIANA | O56: JA POSSUI | R56: AUTORIZADO PAGAMENTO | S56: 8202611081 | T56: 5 DIAS ÚTEIS | U56: 46034 | V56: 46034 | W56: 46041 | X56: 46038 | Y56: =IF(AND(X56<>"",W56<>""),IF(X56<=W56,"SIM","NÃO"),"") | AC56: =IF($C56="","",IF(COUNTIF('Códigos Santander (ref)'!$A$2:$A$79,$C56)>0,"SANTANDER",IF(COUNTIF('Códigos Itaú (ref)'!$A$2:$A$44,$C56)>0,"ITAU",IF(AND(TRIM(UPPER($I56))="CONTRATUAL",ISNUMBER(SEARCH("INDIVIDUAL",SUBSTITUTE(UPPER($D56)," ","")))),"PREMIUM FREE",""))))
A57: TELA | B57: 52745 | C57: 051CF | D57: CAERN COMPANHIA DE AGUAS E ESGOTOS DO RN | E57: 6421737455 | F57: 051CF000780006 | G57: 1070 | H57: 1070 | I57: CONTRATUAL | J57: 1786172000103 | K57: CENTRO ODONTOMODICO VALE DO ASSU LTDA | L57: ASSU | M57: RN | N57: SERGIANA | O57: JA POSSUI | R57: AUTORIZADO PAGAMENTO | S57: 8202611123 | T57: 30 DIAS CORRIDOS | U57: 46034 | V57: 46036 | W57: 46067 | X57: 46043 | Y57: =IF(AND(X57<>"",W57<>""),IF(X57<=W57,"SIM","NÃO"),"") | AC57: =IF($C57="","",IF(COUNTIF('Códigos Santander (ref)'!$A$2:$A$79,$C57)>0,"SANTANDER",IF(COUNTIF('Códigos Itaú (ref)'!$A$2:$A$44,$C57)>0,"ITAU",IF(AND(TRIM(UPPER($I57))="CONTRATUAL",ISNUMBER(SEARCH("INDIVIDUAL",SUBSTITUTE(UPPER($D57)," ","")))),"PREMIUM FREE",""))))
A58: TELA | B58: 52987 | C58: 1RUH3 | D58: BANCO SANTANDER BRASIL SA | E58: 28239531830 | F58: 1RUH3032075006 | G58: 900 | H58: 688.98 | I58: CONTRATUAL | J58: 48034250000179 | K58: INSTITUTO DE ODONTOLOGIA DR GALIOTTI LTDA | L58: SANTO ANDRÉ | M58: SP | N58: SERGIANA | O58: JA POSSUI | R58: AUTORIZADO PAGAMENTO | S58: 8202611124 | T58: 5 DIAS ÚTEIS | U58: 46034 | V58: 46036 | W58: 46043 | X58: 46043 | Y58: =IF(AND(X58<>"",W58<>""),IF(X58<=W58,"SIM","NÃO"),"") | AC58: =IF($C58="","",IF(COUNTIF('Códigos Santander (ref)'!$A$2:$A$79,$C58)>0,"SANTANDER",IF(COUNTIF('Códigos Itaú (ref)'!$A$2:$A$44,$C58)>0,"ITAU",IF(AND(TRIM(UPPER($I58))="CONTRATUAL",ISNUMBER(SEARCH("INDIVIDUAL",SUBSTITUTE(UPPER($D58)," ","")))),"PREMIUM FREE",""))))
A59: LECOM | B59: 53007 | C59: 1RBDC | D59: SEGURPRO VIGILANCIA PATRIMONIAL SA | E59: 78149703691 | F59: 1RBDC002165007 | G59: 1200 | H59: 1200 | I59: INSUFICIÊNCIA DE REDE | J59: 40758776000190 | K59: ZANETTI & DUTRA ODONTOLOGIA LTDA | L59: CURVELO | M59: MG | N59: RONE | O59: 522065 | P59: 46035 | Q59: 46036 | R59: AUTORIZADO PAGAMENTO | S59: 8202611142 | T59: 30 DIAS CORRIDOS | U59: 46035 | V59: 46036 | W59: 46067 | X59: 46043 | Y59: =IF(AND(X59<>"",W59<>""),IF(X59<=W59,"SIM","NÃO"),"") | Z59: LECOM 1.165.305 | AC59: =IF($C59="","",IF(COUNTIF('Códigos Santander (ref)'!$A$2:$A$79,$C59)>0,"SANTANDER",IF(COUNTIF('Códigos Itaú (ref)'!$A$2:$A$44,$C59)>0,"ITAU",IF(AND(TRIM(UPPER($I59))="CONTRATUAL",ISNUMBER(SEARCH("INDIVIDUAL",SUBSTITUTE(UPPER($D59)," ","")))),"PREMIUM FREE",""))))
A60: TELA | B60: 52932 | C60: 1RUH3 | D60: BANCO SANTANDER BRASIL SA | E60: 6385586464 | F60: 1RUH3026703009 | G60: 200 | H60: 82.65 | I60: CONTRATUAL | J60: 10643929460 | K60: CAMILA FERREIRA DE CARVALHO | L60: CARUARU | M60: PE | N60: SERGIANA | O60: JA POSSUI | R60: AUTORIZADO PAGAMENTO | S60: 8202611125 | T60: 5 DIAS ÚTEIS | U60: 46035 | V60: 46036 | W60: 46043 | X60: 46043 | Y60: =IF(AND(X60<>"",W60<>""),IF(X60<=W60,"SIM","NÃO"),"") | AC60: =IF($C60="","",IF(COUNTIF('Códigos Santander (ref)'!$A$2:$A$79,$C60)>0,"SANTANDER",IF(COUNTIF('Códigos Itaú (ref)'!$A$2:$A$44,$C60)>0,"ITAU",IF(AND(TRIM(UPPER($I60))="CONTRATUAL",ISNUMBER(SEARCH("INDIVIDUAL",SUBSTITUTE(UPPER($D60)," ","")))),"PREMIUM FREE",""))))
A61: TELA | B61: 52887 | C61: 1RSLN | D61: ITAU UNIBANCO SA | E61: 38867117572 | F61: 1RSLN021005001 | G61: 150 | H61: 126 | I61: CONTRATUAL | J61: 46183574000143 | K61: LEANDRO DE OLIVEIRA VALENÇA | L61: RIO REAL | M61: BA | N61: SERGIANA | O61: JA POSSUI | R61: AUTORIZADO PAGAMENTO | S61: 8202611127 | T61: 5 DIAS ÚTEIS | U61: 46035 | V61: 46036 | W61: 46043 | X61: 46043 | Y61: =IF(AND(X61<>"",W61<>""),IF(X61<=W61,"SIM","NÃO"),"") | AC61: =IF($C61="","",IF(COUNTIF('Códigos Santander (ref)'!$A$2:$A$79,$C61)>0,"SANTANDER",IF(COUNTIF('Códigos Itaú (ref)'!$A$2:$A$44,$C61)>0,"ITAU",IF(AND(TRIM(UPPER($I61))="CONTRATUAL",ISNUMBER(SEARCH("INDIVIDUAL",SUBSTITUTE(UPPER($D61)," ","")))),"PREMIUM FREE",""))))
A62: TELA | B62: 52614 | C62: 1RUH3 | D62: BANCO SANTANDER BRASIL SA | E62: 29459620809 | F62: 1RUH3037701002 | G62: 500 | H62: 136 | I62: CONTRATUAL | J62: 30786562846 | K62: DEYZE ZILLIG DE ALMEIDA | L62: EMBU GUAÇU | M62: SP | N62: SERGIANA | O62: JA POSSUI | R62: AUTORIZADO PAGAMENTO | S62: 8202611128 | T62: 5 DIAS ÚTEIS | U62: 46035 | V62: 46036 | W62: 46043 | X62: 46043 | Y62: =IF(AND(X62<>"",W62<>""),IF(X62<=W62,"SIM","NÃO"),"") | AC62: =IF($C62="","",IF(COUNTIF('Códigos Santander (ref)'!$A$2:$A$79,$C62)>0,"SANTANDER",IF(COUNTIF('Códigos Itaú (ref)'!$A$2:$A$44,$C62)>0,"ITAU",IF(AND(TRIM(UPPER($I62))="CONTRATUAL",ISNUMBER(SEARCH("INDIVIDUAL",SUBSTITUTE(UPPER($D62)," ","")))),"PREMIUM FREE",""))))
A63: TELA | B63: 52340 | C63: 1RUD5 | D63: SANTANDER HOLDING IMOBILIARIA SA | E63: 32077546867 | F63: 1RUD5000069019 | G63: 350 | H63: 164.43 | I63: CONTRATUAL | J63: 20609740890 | K63: FABIOLA DOMINGUES | L63: SÃO PAULO | M63: SP | N63: SERGIANA | O63: JA POSSUI | R63: AUTORIZADO PAGAMENTO | S63: 8202611129 | T63: 5 DIAS ÚTEIS | U63: 46035 | V63: 46036 | W63: 46043 | X63: 46043 | Y63: =IF(AND(X63<>"",W63<>""),IF(X63<=W63,"SIM","NÃO"),"") | AC63: =IF($C63="","",IF(COUNTIF('Códigos Santander (ref)'!$A$2:$A$79,$C63)>0,"SANTANDER",IF(COUNTIF('Códigos Itaú (ref)'!$A$2:$A$44,$C63)>0,"ITAU",IF(AND(TRIM(UPPER($I63))="CONTRATUAL",ISNUMBER(SEARCH("INDIVIDUAL",SUBSTITUTE(UPPER($D63)," ","")))),"PREMIUM FREE",""))))
A64: TELA | B64: 52935 | C64: 1RSLN | D64: ITAU UNIBANCO SA | E64: 1010151789 | F64: 1RSLN019627025 | G64: 930 | H64: 637.2 | I64: CONTRATUAL | J64: 5187127705 | K64: LUCINDA MERCEDES CORDEIRO DE VASCONCELOS OLIVEIRA | L64: SÃO GONÇALO | M64: RJ | N64: SERGIANA | O64: JA POSSUI | R64: AUTORIZADO PAGAMENTO | S64: 8202611131 | T64: 5 DIAS ÚTEIS | U64: 46035 | V64: 46036 | W64: 46043 | X64: 46043 | Y64: =IF(AND(X64<>"",W64<>""),IF(X64<=W64,"SIM","NÃO"),"") | AC64: =IF($C64="","",IF(COUNTIF('Códigos Santander (ref)'!$A$2:$A$79,$C64)>0,"SANTANDER",IF(COUNTIF('Códigos Itaú (ref)'!$A$2:$A$44,$C64)>0,"ITAU",IF(AND(TRIM(UPPER($I64))="CONTRATUAL",ISNUMBER(SEARCH("INDIVIDUAL",SUBSTITUTE(UPPER($D64)," ","")))),"PREMIUM FREE",""))))
A65: TELA | B65: 52989 | C65: 1RSLN | D65: ITAU UNIBANCO SA | E65: 1010151789 | F65: 1RSLN019627025 | G65: 900 | H65: 531 | I65: CONTRATUAL | J65: 5950466730 | K65: ZULMA FLORES BLANCO QUEIROZ | L65: SÃO GONÇALO | M65: RJ | N65: SERGIANA | O65: JA POSSUI | R65: AUTORIZADO PAGAMENTO | S65: 8202611132 | T65: 5 DIAS ÚTEIS | U65: 46035 | V65: 46036 | W65: 46043 | X65: 46043 | Y65: =IF(AND(X65<>"",W65<>""),IF(X65<=W65,"SIM","NÃO"),"") | AC65: =IF($C65="","",IF(COUNTIF('Códigos Santander (ref)'!$A$2:$A$79,$C65)>0,"SANTANDER",IF(COUNTIF('Códigos Itaú (ref)'!$A$2:$A$44,$C65)>0,"ITAU",IF(AND(TRIM(UPPER($I65))="CONTRATUAL",ISNUMBER(SEARCH("INDIVIDUAL",SUBSTITUTE(UPPER($D65)," ","")))),"PREMIUM FREE",""))))
A66: TELA | B66: 52990 | C66: 1RUH3 | D66: BANCO SANTANDER BRASIL SA | E66: 1498442714 | F66: 1RUH3030007038 | G66: 260 | H66: 212.19 | I66: CONTRATUAL | J66: 229031781 | K66: LEONARDO LIMA BITTENCOURT COSTA | L66: SÃO GONÇALO | M66: RJ | N66: SERGIANA | O66: JA POSSUI | R66: AUTORIZADO PAGAMENTO | S66: 8202611133 | T66: 5 DIAS ÚTEIS | U66: 46035 | V66: 46036 | W66: 46043 | X66: 46043 | Y66: =IF(AND(X66<>"",W66<>""),IF(X66<=W66,"SIM","NÃO"),"") | AC66: =IF($C66="","",IF(COUNTIF('Códigos Santander (ref)'!$A$2:$A$79,$C66)>0,"SANTANDER",IF(COUNTIF('Códigos Itaú (ref)'!$A$2:$A$44,$C66)>0,"ITAU",IF(AND(TRIM(UPPER($I66))="CONTRATUAL",ISNUMBER(SEARCH("INDIVIDUAL",SUBSTITUTE(UPPER($D66)," ","")))),"PREMIUM FREE",""))))
A67: TELA | B67: 52891 | C67: 0KGE5 | D67: BANCO SANTANDER BRASIL SA | E67: 7898151763 | F67: 0KGE5028783000 | G67: 280 | H67: 212.19 | I67: CONTRATUAL | J67: 229031781 | K67: LEONARDO LIMA BITTENCOURT COSTA | L67: SÃO GONÇALO | M67: RJ | N67: SERGIANA | O67: JA POSSUI | R67: AUTORIZADO PAGAMENTO | S67: 8202611134 | T67: 5 DIAS ÚTEIS | U67: 46035 | V67: 46036 | W67: 46043 | X67: 46043 | Y67: =IF(AND(X67<>"",W67<>""),IF(X67<=W67,"SIM","NÃO"),"") | AC67: =IF($C67="","",IF(COUNTIF('Códigos Santander (ref)'!$A$2:$A$79,$C67)>0,"SANTANDER",IF(COUNTIF('Códigos Itaú (ref)'!$A$2:$A$44,$C67)>0,"ITAU",IF(AND(TRIM(UPPER($I67))="CONTRATUAL",ISNUMBER(SEARCH("INDIVIDUAL",SUBSTITUTE(UPPER($D67)," ","")))),"PREMIUM FREE",""))))
A68: TELA | B68: 52937 | C68: 1RUH3 | D68: BANCO SANTANDER BRASIL SA | E68: 31801933871 | F68: 1RUH3027211029 | G68: 636 | H68: 636 | I68: CONTRATUAL | J68: 5573342000114 | K68: VICENTE ESPERIDIAO ODONTOLOGIA AVANCADA LTDA | L68: SÃO PAULO | M68: SP | N68: SERGIANA | O68: JA POSSUI | R68: AUTORIZADO PAGAMENTO | S68: 8202611211 | T68: 5 DIAS ÚTEIS | U68: 46036 | V68: 46037 | W68: 46044 | X68: 46043 | Y68: =IF(AND(X68<>"",W68<>""),IF(X68<=W68,"SIM","NÃO"),"") | AC68: =IF($C68="","",IF(COUNTIF('Códigos Santander (ref)'!$A$2:$A$79,$C68)>0,"SANTANDER",IF(COUNTIF('Códigos Itaú (ref)'!$A$2:$A$44,$C68)>0,"ITAU",IF(AND(TRIM(UPPER($I68))="CONTRATUAL",ISNUMBER(SEARCH("INDIVIDUAL",SUBSTITUTE(UPPER($D68)," ","")))),"PREMIUM FREE",""))))
A69: TELA | B69: 52936 | C69: 1RUH3 | D69: BANCO SANTANDER BRASIL SA | E69: 18968051836 | F69: 1RUH3028125029 | G69: 250 | H69: 242.85 | I69: CONTRATUAL | J69: 15739539897 | K69: MARCIA REGINA DE OLIVEIRA FARINA | L69: SÃO PAULO | M69: SP | N69: SERGIANA | O69: JA POSSUI | R69: AUTORIZADO PAGAMENTO | S69: 8202611214 | T69: 5 DIAS ÚTEIS | U69: 46036 | V69: 46037 | W69: 46044 | X69: 46043 | Y69: =IF(AND(X69<>"",W69<>""),IF(X69<=W69,"SIM","NÃO"),"") | AC69: =IF($C69="","",IF(COUNTIF('Códigos Santander (ref)'!$A$2:$A$79,$C69)>0,"SANTANDER",IF(COUNTIF('Códigos Itaú (ref)'!$A$2:$A$44,$C69)>0,"ITAU",IF(AND(TRIM(UPPER($I69))="CONTRATUAL",ISNUMBER(SEARCH("INDIVIDUAL",SUBSTITUTE(UPPER($D69)," ","")))),"PREMIUM FREE",""))))
A70: TELA | B70: 52892 | C70: 0KGE5 | D70: BANCO SANTANDER BRASIL SA | E70: 7898151763 | F70: 0KGE5028783026 | G70: 260 | H70: 212.19 | I70: CONTRATUAL | J70: 229031781 | K70: LEONARDO LIMA BITTENCOURT COSTA | L70: SÃO GONÇALO | M70: RJ | N70: SERGIANA | O70: JA POSSUI | R70: AUTORIZADO PAGAMENTO | S70: 8202611223 | T70: 5 DIAS ÚTEIS | U70: 46036 | V70: 46037 | W70: 46044 | X70: 46043 | Y70: =IF(AND(X70<>"",W70<>""),IF(X70<=W70,"SIM","NÃO"),"") | AC70: =IF($C70="","",IF(COUNTIF('Códigos Santander (ref)'!$A$2:$A$79,$C70)>0,"SANTANDER",IF(COUNTIF('Códigos Itaú (ref)'!$A$2:$A$44,$C70)>0,"ITAU",IF(AND(TRIM(UPPER($I70))="CONTRATUAL",ISNUMBER(SEARCH("INDIVIDUAL",SUBSTITUTE(UPPER($D70)," ","")))),"PREMIUM FREE",""))))
A71: SAC | B71: 52450 | C71: 0P4KE | D71: FUNDO ASSIST SAUDE SERVIDOR | E71: 10543154777 | F71: 0P4KE000324000 | G71: 350 | H71: 350 | I71: COBRANÇA INDEVIDA | J71: 39936876000180 | K71: A2 FACILE CLINICAS ODONTOLOGICAS LTDA | L71: RIO DE JANEIRO | M71: RJ | N71: SERGIANA | O71: 523285 | P71: 46038 | Q71: 46041 | R71: AUTORIZADO PAGAMENTO | S71: 8202611353 | T71: 30 DIAS CORRIDOS | U71: 46036 | V71: 46042 | W71: 46073 | X71: 46048 | Y71: =IF(AND(X71<>"",W71<>""),IF(X71<=W71,"SIM","NÃO"),"") | AC71: =IF($C71="","",IF(COUNTIF('Códigos Santander (ref)'!$A$2:$A$79,$C71)>0,"SANTANDER",IF(COUNTIF('Códigos Itaú (ref)'!$A$2:$A$44,$C71)>0,"ITAU",IF(AND(TRIM(UPPER($I71))="CONTRATUAL",ISNUMBER(SEARCH("INDIVIDUAL",SUBSTITUTE(UPPER($D71)," ","")))),"PREMIUM FREE",""))))
A72: TELA | B72: 51033 | C72: 1RSLN | D72: ITAU UNIBANCO SA | E72: 23087866806 | F72: 1RSLN016000013 | G72: 2950 | H72: 2102.4 | I72: CONTRATUAL | J72: 33642600875 | K72: LUANA RODRIGUES DE SA DA SILVEIRA | L72: SÃO JOSE DO RIO PRETO | M72: SP | N72: SERGIANA | O72: JA POSSUI | R72: AUTORIZADO PAGAMENTO | S72: 8202611224 | T72: 5 DIAS ÚTEIS | U72: 46036 | V72: 46037 | W72: 46044 | X72: 46043 | Y72: =IF(AND(X72<>"",W72<>""),IF(X72<=W72,"SIM","NÃO"),"") | AC72: =IF($C72="","",IF(COUNTIF('Códigos Santander (ref)'!$A$2:$A$79,$C72)>0,"SANTANDER",IF(COUNTIF('Códigos Itaú (ref)'!$A$2:$A$44,$C72)>0,"ITAU",IF(AND(TRIM(UPPER($I72))="CONTRATUAL",ISNUMBER(SEARCH("INDIVIDUAL",SUBSTITUTE(UPPER($D72)," ","")))),"PREMIUM FREE",""))))
A73: SAC | B73: 52471 | C73: 0700C | D73: INDIVIDUAL | E73: 43123180425 | F73: 0700C221210000 | G73: 950 | H73: 950 | I73: COBRANÇA INDEVIDA | J73: 11080860711 | K73: LILIANE NUNES DINIZ | L73: RIO DE JANEIRO | M73: RJ | N73: SERGIANA | O73: 522769 | P73: 46037 | Q73: 46037 | R73: AUTORIZADO PAGAMENTO | S73: 8202611225 | T73: 30 DIAS CORRIDOS | U73: 46036 | V73: 46037 | W73: 46068 | X73: 46043 | Y73: =IF(AND(X73<>"",W73<>""),IF(X73<=W73,"SIM","NÃO"),"") | AC73: =IF($C73="","",IF(COUNTIF('Códigos Santander (ref)'!$A$2:$A$79,$C73)>0,"SANTANDER",IF(COUNTIF('Códigos Itaú (ref)'!$A$2:$A$44,$C73)>0,"ITAU",IF(AND(TRIM(UPPER($I73))="CONTRATUAL",ISNUMBER(SEARCH("INDIVIDUAL",SUBSTITUTE(UPPER($D73)," ","")))),"PREMIUM FREE",""))))
A74: TELA | B74: 52942 | C74: 1RUH3 | D74: BANCO SANTANDER BRASIL SA | E74: 5748915529 | F74: 1RUH3014267012 | G74: 30 | H74: 17.34 | I74: CONTRATUAL | J74: 9028521000121 | K74: RADIUM UNIDADE DE SERVICOS DE IMAGENS DA FACE LTDA | L74: JUAZEIRO | M74: BA | N74: SERGIANA | O74: JA POSSUI | R74: AUTORIZADO PAGAMENTO | S74: 8202611226 | T74: 5 DIAS ÚTEIS | U74: 46037 | V74: 46037 | W74: 46044 | X74: 46043 | Y74: =IF(AND(X74<>"",W74<>""),IF(X74<=W74,"SIM","NÃO"),"") | AC74: =IF($C74="","",IF(COUNTIF('Códigos Santander (ref)'!$A$2:$A$79,$C74)>0,"SANTANDER",IF(COUNTIF('Códigos Itaú (ref)'!$A$2:$A$44,$C74)>0,"ITAU",IF(AND(TRIM(UPPER($I74))="CONTRATUAL",ISNUMBER(SEARCH("INDIVIDUAL",SUBSTITUTE(UPPER($D74)," ","")))),"PREMIUM FREE",""))))
A75: TELA | B75: 52934 | C75: 1RUGZ | D75: SX TOOLS SOLUC SERV COMPARTILHADOS LTDA | E75: 28776802825 | F75: 1RUGZ002658020 | G75: 250 | H75: 212.19 | I75: CONTRATUAL | J75: 12974178871 | K75: MARCIA FERNANDES SARDINHA | L75: SÃO PAULO | M75: SP | N75: SERGIANA | O75: JA POSSUI | R75: AUTORIZADO PAGAMENTO | S75: 8202611228 | T75: 5 DIAS ÚTEIS | U75: 46037 | V75: 46037 | W75: 46044 | X75: 46043 | Y75: =IF(AND(X75<>"",W75<>""),IF(X75<=W75,"SIM","NÃO"),"") | AC75: =IF($C75="","",IF(COUNTIF('Códigos Santander (ref)'!$A$2:$A$79,$C75)>0,"SANTANDER",IF(COUNTIF('Códigos Itaú (ref)'!$A$2:$A$44,$C75)>0,"ITAU",IF(AND(TRIM(UPPER($I75))="CONTRATUAL",ISNUMBER(SEARCH("INDIVIDUAL",SUBSTITUTE(UPPER($D75)," ","")))),"PREMIUM FREE",""))))
A76: TELA | B76: 52940 | C76: 1RUH3 | D76: BANCO SANTANDER BRASIL SA | E76: 22024640850 | F76: 1RUH3033793034 | G76: 1399.39 | H76: 1399.39 | I76: CONTRATUAL | J76: 38260191000101 | K76: FREDERICO VICENTE CLINICA ODONTOLOGICA UNIPESSOAL LTDA | L76: SÃO PAULO | M76: SP | N76: SERGIANA | O76: JA POSSUI | R76: AUTORIZADO PAGAMENTO | S76: 8202611229 | T76: 5 DIAS ÚTEIS | U76: 46037 | V76: 46037 | W76: 46044 | X76: 46043 | Y76: =IF(AND(X76<>"",W76<>""),IF(X76<=W76,"SIM","NÃO"),"") | AC76: =IF($C76="","",IF(COUNTIF('Códigos Santander (ref)'!$A$2:$A$79,$C76)>0,"SANTANDER",IF(COUNTIF('Códigos Itaú (ref)'!$A$2:$A$44,$C76)>0,"ITAU",IF(AND(TRIM(UPPER($I76))="CONTRATUAL",ISNUMBER(SEARCH("INDIVIDUAL",SUBSTITUTE(UPPER($D76)," ","")))),"PREMIUM FREE",""))))
A77: TELA | B77: 52527 | C77: 1RUH3 | D77: BANCO SANTANDER BRASIL SA | E77: 33468161840 | F77: 1RUH3031823009 | G77: 385 | H77: 113.4 | I77: CONTRATUAL | J77: 21476763810 | K77: OSIAS FERREIRA DA SILVA JUNIOR | L77: SÃO PAULO | M77: SP | N77: SERGIANA | O77: 523103 | P77: 46037 | Q77: 46042 | R77: AUTORIZADO PAGAMENTO | S77: 8202611355 | T77: 5 DIAS ÚTEIS | U77: 46037 | V77: 46042 | W77: 46049 | X77: 46048 | Y77: =IF(AND(X77<>"",W77<>""),IF(X77<=W77,"SIM","NÃO"),"") | Z77: Consta no astrein liberação 16/01/2026, erro do SAP | AC77: =IF($C77="","",IF(COUNTIF('Códigos Santander (ref)'!$A$2:$A$79,$C77)>0,"SANTANDER",IF(COUNTIF('Códigos Itaú (ref)'!$A$2:$A$44,$C77)>0,"ITAU",IF(AND(TRIM(UPPER($I77))="CONTRATUAL",ISNUMBER(SEARCH("INDIVIDUAL",SUBSTITUTE(UPPER($D77)," ","")))),"PREMIUM FREE",""))))
A78: TELA | B78: 52585 | C78: 1RUH3 | D78: BANCO SANTANDER BRASIL SA | E78: 33468161840 | F78: 1RUH3031823017 | G78: 385 | H78: 113.4 | I78: CONTRATUAL | J78: 21476763810 | K78: OSIAS FERREIRA DA SILVA JUNIOR | L78: SÃO PAULO | M78: SP | N78: SERGIANA | O78: 523103 | P78: 46037 | Q78: 46042 | R78: AUTORIZADO PAGAMENTO | S78: 8202611356 | T78: 5 DIAS ÚTEIS | U78: 46037 | V78: 46042 | W78: 46049 | X78: 46048 | Y78: =IF(AND(X78<>"",W78<>""),IF(X78<=W78,"SIM","NÃO"),"") | Z78: Consta no astrein liberação 16/01/2026, erro do SAP | AC78: =IF($C78="","",IF(COUNTIF('Códigos Santander (ref)'!$A$2:$A$79,$C78)>0,"SANTANDER",IF(COUNTIF('Códigos Itaú (ref)'!$A$2:$A$44,$C78)>0,"ITAU",IF(AND(TRIM(UPPER($I78))="CONTRATUAL",ISNUMBER(SEARCH("INDIVIDUAL",SUBSTITUTE(UPPER($D78)," ","")))),"PREMIUM FREE",""))))
A79: EMAIL | B79: 42883 | C79: 1RU08 | D79: ITAU UNIBANCO SA | E79: 75843307700 | F79: 1RU08000843008 | G79: 16340 | H79: 3021.88 | I79: CONTRATUAL | J79: 17750168000117 | K79: ORAL DESIGN ODONTOLOGIA LTDA | L79: RIO DE JANEIRO | M79: RJ | N79: CIBELY | O79: 523121 | P79: 46037 | Q79: 46042 | R79: AUTORIZADO PAGAMENTO | S79: 8202611357 | T79: 5 DIAS ÚTEIS | U79: 46037 | V79: 46042 | W79: 46049 | X79: 46048 | Y79: =IF(AND(X79<>"",W79<>""),IF(X79<=W79,"SIM","NÃO"),"") | Z79: Consta no astrein liberação 16/01/2026, erro do SAP | AC79: =IF($C79="","",IF(COUNTIF('Códigos Santander (ref)'!$A$2:$A$79,$C79)>0,"SANTANDER",IF(COUNTIF('Códigos Itaú (ref)'!$A$2:$A$44,$C79)>0,"ITAU",IF(AND(TRIM(UPPER($I79))="CONTRATUAL",ISNUMBER(SEARCH("INDIVIDUAL",SUBSTITUTE(UPPER($D79)," ","")))),"PREMIUM FREE",""))))
A80: TELA | B80: 52914 | C80: 1RUH3 | D80: BANCO SANTANDER BRASIL SA | E80: 23788731826 | F80: 1RUH3017169003 | G80: 600 | H80: 456.07 | I80: CONTRATUAL | J80: 24870458000160 | K80: EDWAL LOBOSCHI | L80: SÃO PAULO | M80: SP | N80: SERGIANA | O80: JA POSSUI | R80: AUTORIZADO PAGAMENTO | S80: 8202611230 | T80: 5 DIAS ÚTEIS | U80: 46037 | V80: 46037 | W80: 46044 | X80: 46043 | Y80: =IF(AND(X80<>"",W80<>""),IF(X80<=W80,"SIM","NÃO"),"") | AC80: =IF($C80="","",IF(COUNTIF('Códigos Santander (ref)'!$A$2:$A$79,$C80)>0,"SANTANDER",IF(COUNTIF('Códigos Itaú (ref)'!$A$2:$A$44,$C80)>0,"ITAU",IF(AND(TRIM(UPPER($I80))="CONTRATUAL",ISNUMBER(SEARCH("INDIVIDUAL",SUBSTITUTE(UPPER($D80)," ","")))),"PREMIUM FREE",""))))
A81: TELA | B81: 53048 | C81: 1RUH3 | D81: BANCO SANTANDER BRASIL SA | E81: 8484858740 | F81: 1RUH3029712009 | G81: 800 | H81: 385 | I81: CONTRATUAL | J81: 229031781 | K81: LEONARDO LIMA BITTENCOURT COSTA | L81: SÃO GONÇALO | M81: RJ | N81: SERGIANA | O81: JA POSSUI | R81: AUTORIZADO PAGAMENTO | S81: 8202611231 | T81: 5 DIAS ÚTEIS | U81: 46037 | V81: 46037 | W81: 46044 | X81: 46043 | Y81: =IF(AND(X81<>"",W81<>""),IF(X81<=W81,"SIM","NÃO"),"") | AC81: =IF($C81="","",IF(COUNTIF('Códigos Santander (ref)'!$A$2:$A$79,$C81)>0,"SANTANDER",IF(COUNTIF('Códigos Itaú (ref)'!$A$2:$A$44,$C81)>0,"ITAU",IF(AND(TRIM(UPPER($I81))="CONTRATUAL",ISNUMBER(SEARCH("INDIVIDUAL",SUBSTITUTE(UPPER($D81)," ","")))),"PREMIUM FREE",""))))
A82: TELA | B82: 52998 | C82: 1RU51 | D82: BANCO SANTANDER BRASIL SA | E82: 10326932828 | F82: 1RU51000260010 | G82: 318.67 | H82: 318.67 | I82: CONTRATUAL | J82: 38260191000101 | K82: FREDERICO VICENTE CLINICA ODONTOLOGICA UNIPESSOAL LTDA | L82: SÃO PAULO | M82: SP | N82: SERGIANA | O82: JA POSSUI | R82: AUTORIZADO PAGAMENTO | S82: 8202611232 | T82: 5 DIAS ÚTEIS | U82: 46037 | V82: 46037 | W82: 46044 | X82: 46043 | Y82: =IF(AND(X82<>"",W82<>""),IF(X82<=W82,"SIM","NÃO"),"") | AC82: =IF($C82="","",IF(COUNTIF('Códigos Santander (ref)'!$A$2:$A$79,$C82)>0,"SANTANDER",IF(COUNTIF('Códigos Itaú (ref)'!$A$2:$A$44,$C82)>0,"ITAU",IF(AND(TRIM(UPPER($I82))="CONTRATUAL",ISNUMBER(SEARCH("INDIVIDUAL",SUBSTITUTE(UPPER($D82)," ","")))),"PREMIUM FREE",""))))
A83: NIP | B83: 51887 | C83: 50700 | D83: INDIVIDUAL MAISODONTO | E83: 6778323469 | F83: 50700152160003 | G83: 800 | H83: 600 | I83: COBRANÇA INDEVIDA | J83: 40446840000105 | K83: SORRIA CLINICAS ODONTOLOGICAS CARUARU LTDA | L83: CARUARU | M83: PE | N83: CIBELY | O83: 523245 | P83: 46037 | Q83: 46041 | R83: AUTORIZADO PAGAMENTO | S83: 8202611358 | T83: 30 DIAS CORRIDOS | U83: 46037 | V83: 46042 | W83: 46073 | X83: 46048 | Y83: =IF(AND(X83<>"",W83<>""),IF(X83<=W83,"SIM","NÃO"),"") | AC83: =IF($C83="","",IF(COUNTIF('Códigos Santander (ref)'!$A$2:$A$79,$C83)>0,"SANTANDER",IF(COUNTIF('Códigos Itaú (ref)'!$A$2:$A$44,$C83)>0,"ITAU",IF(AND(TRIM(UPPER($I83))="CONTRATUAL",ISNUMBER(SEARCH("INDIVIDUAL",SUBSTITUTE(UPPER($D83)," ","")))),"PREMIUM FREE",""))))
A84: TELA | B84: 53067 | C84: 1RUH3 | D84: BANCO SANTANDER BRASIL SA | E84: 33118843888 | F84: 1RUH3032082037 | G84: 560 | H84: 424.38 | I84: CONTRATUAL | J84: 24870458000160 | K84: EDWAL LOBOSCHI | L84: SÃO PAULO | M84: SP | N84: SERGIANA | O84: JA POSSUI | R84: AUTORIZADO PAGAMENTO | S84: 8202611253 | T84: 5 DIAS ÚTEIS | U84: 46037 | V84: 46038 | W84: 46045 | X84: 46045 | Y84: =IF(AND(X84<>"",W84<>""),IF(X84<=W84,"SIM","NÃO"),"") | AC84: =IF($C84="","",IF(COUNTIF('Códigos Santander (ref)'!$A$2:$A$79,$C84)>0,"SANTANDER",IF(COUNTIF('Códigos Itaú (ref)'!$A$2:$A$44,$C84)>0,"ITAU",IF(AND(TRIM(UPPER($I84))="CONTRATUAL",ISNUMBER(SEARCH("INDIVIDUAL",SUBSTITUTE(UPPER($D84)," ","")))),"PREMIUM FREE",""))))
A85: TELA | B85: 52941 | C85: 1RSLN | D85: ITAU UNIBANCO SA | E85: 240505123 | F85: 1RSLN009713000 | G85: 180 | H85: 174.6 | I85: CONTRATUAL | J85: 12717171000115 | K85: EXAME DIGITAL LTDA | L85: TAQUARA | M85: RS | N85: SERGIANA | O85: JA POSSUI | R85: AUTORIZADO PAGAMENTO | S85: 8202611254 | T85: 5 DIAS ÚTEIS | U85: 46037 | V85: 46038 | W85: 46045 | X85: 46045 | Y85: =IF(AND(X85<>"",W85<>""),IF(X85<=W85,"SIM","NÃO"),"") | AC85: =IF($C85="","",IF(COUNTIF('Códigos Santander (ref)'!$A$2:$A$79,$C85)>0,"SANTANDER",IF(COUNTIF('Códigos Itaú (ref)'!$A$2:$A$44,$C85)>0,"ITAU",IF(AND(TRIM(UPPER($I85))="CONTRATUAL",ISNUMBER(SEARCH("INDIVIDUAL",SUBSTITUTE(UPPER($D85)," ","")))),"PREMIUM FREE",""))))
A86: TELA | B86: 52912 | C86: 1RSLN | D86: ITAU UNIBANCO SA | E86: 240505123 | F86: 1RSLN009713000 | G86: 250 | H86: 61.2 | I86: CONTRATUAL | J86: 2351898044 | K86: SCHAIANE L. TEIXEIRA BARRETO | L86: TAQUARA | M86: RS | N86: SERGIANA | O86: JA POSSUI | R86: AUTORIZADO PAGAMENTO | S86: 8202611256 | T86: 5 DIAS ÚTEIS | U86: 46037 | V86: 46038 | W86: 46045 | X86: 46045 | Y86: =IF(AND(X86<>"",W86<>""),IF(X86<=W86,"SIM","NÃO"),"") | AC86: =IF($C86="","",IF(COUNTIF('Códigos Santander (ref)'!$A$2:$A$79,$C86)>0,"SANTANDER",IF(COUNTIF('Códigos Itaú (ref)'!$A$2:$A$44,$C86)>0,"ITAU",IF(AND(TRIM(UPPER($I86))="CONTRATUAL",ISNUMBER(SEARCH("INDIVIDUAL",SUBSTITUTE(UPPER($D86)," ","")))),"PREMIUM FREE",""))))
A87: TELA | B87: 53069 | C87: 1RUH3 | D87: BANCO SANTANDER BRASIL SA | E87: 22001287895 | F87: 1RUH3031150004 | G87: 350 | H87: 243.88 | I87: CONTRATUAL | J87: 24870458000160 | K87: EDWAL LOBOSCHI | L87: SÃO PAULO | M87: SP | N87: SERGIANA | O87: 523377 | P87: 46038 | Q87: 46041 | R87: AUTORIZADO PAGAMENTO | S87: 8202611359 | T87: 5 DIAS ÚTEIS | U87: 46038 | V87: 46042 | W87: 46049 | X87: 46048 | Y87: =IF(AND(X87<>"",W87<>""),IF(X87<=W87,"SIM","NÃO"),"") | AC87: =IF($C87="","",IF(COUNTIF('Códigos Santander (ref)'!$A$2:$A$79,$C87)>0,"SANTANDER",IF(COUNTIF('Códigos Itaú (ref)'!$A$2:$A$44,$C87)>0,"ITAU",IF(AND(TRIM(UPPER($I87))="CONTRATUAL",ISNUMBER(SEARCH("INDIVIDUAL",SUBSTITUTE(UPPER($D87)," ","")))),"PREMIUM FREE",""))))
A88: TELA | B88: 52807 | C88: 1RUH3 | D88: BANCO SANTANDER BRASIL SA | E88: 17214156709 | F88: 1RUH3012406007 | G88: 350 | H88: 14.58 | I88: CONTRATUAL | J88: 22822219000109 | K88: F RACHID DAU PACHECO ODONTOLOGIA ME | L88: NOVA IGUAÇU | M88: RJ | N88: SERGIANA | O88: 523415 | P88: 46038 | Q88: 46041 | R88: AUTORIZADO PAGAMENTO | S88: 8202611360 | T88: 5 DIAS ÚTEIS | U88: 46038 | V88: 46042 | W88: 46049 | X88: 46048 | Y88: =IF(AND(X88<>"",W88<>""),IF(X88<=W88,"SIM","NÃO"),"") | AC88: =IF($C88="","",IF(COUNTIF('Códigos Santander (ref)'!$A$2:$A$79,$C88)>0,"SANTANDER",IF(COUNTIF('Códigos Itaú (ref)'!$A$2:$A$44,$C88)>0,"ITAU",IF(AND(TRIM(UPPER($I88))="CONTRATUAL",ISNUMBER(SEARCH("INDIVIDUAL",SUBSTITUTE(UPPER($D88)," ","")))),"PREMIUM FREE",""))))
A89: TELA | B89: 52918 | C89: 1RSLN | D89: ITAU UNIBANCO SA | E89: 11435080769 | F89: 1RSLN016080009 | G89: 450 | H89: 450 | I89: CONTRATUAL | J89: 229031781 | K89: LEONARDO LIMA BITTENCOURT COSTA | L89: SÃO GONÇALO | M89: RJ | N89: SERGIANA | O89: JA POSSUI | R89: AUTORIZADO PAGAMENTO | S89: 8202611257 | T89: 5 DIAS ÚTEIS | U89: 46038 | V89: 46038 | W89: 46045 | X89: 46045 | Y89: =IF(AND(X89<>"",W89<>""),IF(X89<=W89,"SIM","NÃO"),"") | AC89: =IF($C89="","",IF(COUNTIF('Códigos Santander (ref)'!$A$2:$A$79,$C89)>0,"SANTANDER",IF(COUNTIF('Códigos Itaú (ref)'!$A$2:$A$44,$C89)>0,"ITAU",IF(AND(TRIM(UPPER($I89))="CONTRATUAL",ISNUMBER(SEARCH("INDIVIDUAL",SUBSTITUTE(UPPER($D89)," ","")))),"PREMIUM FREE",""))))
A90: TELA | B90: 53050 | C90: 1RSLN | D90: ITAU UNIBANCO SA | E90: 93401736 | F90: 1RSLN011817003 | G90: 450 | H90: 450 | I90: CONTRATUAL | J90: 5950466730 | K90: ZULMA FLORES BLANCO QUEIROZ | L90: SÃO GONÇALO | M90: RJ | N90: SERGIANA | O90: JA POSSUI | R90: AUTORIZADO PAGAMENTO | S90: 8202611258 | T90: 5 DIAS ÚTEIS | U90: 46038 | V90: 46038 | W90: 46045 | X90: 46045 | Y90: =IF(AND(X90<>"",W90<>""),IF(X90<=W90,"SIM","NÃO"),"") | AC90: =IF($C90="","",IF(COUNTIF('Códigos Santander (ref)'!$A$2:$A$79,$C90)>0,"SANTANDER",IF(COUNTIF('Códigos Itaú (ref)'!$A$2:$A$44,$C90)>0,"ITAU",IF(AND(TRIM(UPPER($I90))="CONTRATUAL",ISNUMBER(SEARCH("INDIVIDUAL",SUBSTITUTE(UPPER($D90)," ","")))),"PREMIUM FREE",""))))
A91: TELA | B91: 53051 | C91: 1RSLN | D91: ITAU UNIBANCO SA | E91: 30097221848 | F91: 1RSLN013923021 | G91: 500 | H91: 500 | I91: CONTRATUAL | J91: 85769908815 | K91: SONIA PINEDA VICENTE | L91: SÃO PAULO | M91: SP | N91: SERGIANA | O91: JA POSSUI | R91: AUTORIZADO PAGAMENTO | S91: 8202611259 | T91: 5 DIAS ÚTEIS | U91: 46038 | V91: 46038 | W91: 46045 | X91: 46045 | Y91: =IF(AND(X91<>"",W91<>""),IF(X91<=W91,"SIM","NÃO"),"") | AC91: =IF($C91="","",IF(COUNTIF('Códigos Santander (ref)'!$A$2:$A$79,$C91)>0,"SANTANDER",IF(COUNTIF('Códigos Itaú (ref)'!$A$2:$A$44,$C91)>0,"ITAU",IF(AND(TRIM(UPPER($I91))="CONTRATUAL",ISNUMBER(SEARCH("INDIVIDUAL",SUBSTITUTE(UPPER($D91)," ","")))),"PREMIUM FREE",""))))
A92: TELA | B92: 52917 | C92: 1RUH3 | D92: BANCO SANTANDER BRASIL SA | E92: 8608758733 | F92: 1RUH3031469019 | G92: 260 | H92: 212.19 | I92: CONTRATUAL | J92: 5950466730 | K92: ZULMA FLORES BLANCO QUEIROZ | L92: SÃO GONÇALO | M92: RJ | N92: SERGIANA | O92: JA POSSUI | R92: AUTORIZADO PAGAMENTO | S92: 8202611260 | T92: 5 DIAS ÚTEIS | U92: 46038 | V92: 46038 | W92: 46045 | X92: 46045 | Y92: =IF(AND(X92<>"",W92<>""),IF(X92<=W92,"SIM","NÃO"),"") | AC92: =IF($C92="","",IF(COUNTIF('Códigos Santander (ref)'!$A$2:$A$79,$C92)>0,"SANTANDER",IF(COUNTIF('Códigos Itaú (ref)'!$A$2:$A$44,$C92)>0,"ITAU",IF(AND(TRIM(UPPER($I92))="CONTRATUAL",ISNUMBER(SEARCH("INDIVIDUAL",SUBSTITUTE(UPPER($D92)," ","")))),"PREMIUM FREE",""))))
A93: TELA | B93: 52999 | C93: 1RUH3 | D93: BANCO SANTANDER BRASIL SA | E93: 2635116776 | F93: 1RUH3032448007 | G93: 260 | H93: 212.19 | I93: CONTRATUAL | J93: 5950466730 | K93: ZULMA FLORES BLANCO QUEIROZ | L93: SÃO GONÇALO | M93: RJ | N93: SERGIANA | O93: JA POSSUI | R93: AUTORIZADO PAGAMENTO | S93: 8202611261 | T93: 5 DIAS ÚTEIS | U93: 46038 | V93: 46038 | W93: 46045 | X93: 46045 | Y93: =IF(AND(X93<>"",W93<>""),IF(X93<=W93,"SIM","NÃO"),"") | AC93: =IF($C93="","",IF(COUNTIF('Códigos Santander (ref)'!$A$2:$A$79,$C93)>0,"SANTANDER",IF(COUNTIF('Códigos Itaú (ref)'!$A$2:$A$44,$C93)>0,"ITAU",IF(AND(TRIM(UPPER($I93))="CONTRATUAL",ISNUMBER(SEARCH("INDIVIDUAL",SUBSTITUTE(UPPER($D93)," ","")))),"PREMIUM FREE",""))))
A94: TELA | B94: 52978 | C94: 1RUB1 | D94: F1RST TECNOLOGIA E INOVACAO LTDA | E94: 35353181816 | F94: 1RUB1001483030 | G94: 230 | H94: 122.48 | I94: CONTRATUAL | J94: 22733506862 | K94: THAIS SIMONE ELIAS | L94: SÃO BERNARDO DO CAMPO | M94: SP | N94: SERGIANA | O94: JA POSSUI | R94: AUTORIZADO PAGAMENTO | S94: 8202611262 | T94: 5 DIAS ÚTEIS | U94: 46038 | V94: 46038 | W94: 46045 | X94: 46045 | Y94: =IF(AND(X94<>"",W94<>""),IF(X94<=W94,"SIM","NÃO"),"") | AC94: =IF($C94="","",IF(COUNTIF('Códigos Santander (ref)'!$A$2:$A$79,$C94)>0,"SANTANDER",IF(COUNTIF('Códigos Itaú (ref)'!$A$2:$A$44,$C94)>0,"ITAU",IF(AND(TRIM(UPPER($I94))="CONTRATUAL",ISNUMBER(SEARCH("INDIVIDUAL",SUBSTITUTE(UPPER($D94)," ","")))),"PREMIUM FREE",""))))
A95: TELA | B95: 52943 | C95: 1RUB1 | D95: F1RST TECNOLOGIA E INOVACAO LTDA | E95: 35353181816 | F95: 1RUB1001483021 | G95: 230 | H95: 122.48 | I95: CONTRATUAL | J95: 22733506862 | K95: THAIS SIMONE ELIAS | L95: SÃO BERNARDO DO CAMPO | M95: SP | N95: SERGIANA | O95: JA POSSUI | R95: AUTORIZADO PAGAMENTO | S95: 8202611263 | T95: 5 DIAS ÚTEIS | U95: 46038 | V95: 46038 | W95: 46045 | X95: 46045 | Y95: =IF(AND(X95<>"",W95<>""),IF(X95<=W95,"SIM","NÃO"),"") | AC95: =IF($C95="","",IF(COUNTIF('Códigos Santander (ref)'!$A$2:$A$79,$C95)>0,"SANTANDER",IF(COUNTIF('Códigos Itaú (ref)'!$A$2:$A$44,$C95)>0,"ITAU",IF(AND(TRIM(UPPER($I95))="CONTRATUAL",ISNUMBER(SEARCH("INDIVIDUAL",SUBSTITUTE(UPPER($D95)," ","")))),"PREMIUM FREE",""))))
A96: TELA | B96: 52910 | C96: 1RUH3 | D96: BANCO SANTANDER BRASIL SA | E96: 10267586701 | F96: 1RUH3014938006 | G96: 400 | H96: 192.85 | I96: COBRANÇA INDEVIDA | J96: 22984621867 | K96: ISABELLA ZATZ PANCIOLI | L96: SÃO PAULO | M96: SP | N96: SERGIANA | O96: 523516 | P96: 46041 | Q96: 46042 | R96: AUTORIZADO PAGAMENTO | S96: 8202611361 | T96: 5 DIAS ÚTEIS | U96: 46038 | V96: 46042 | W96: 46049 | X96: 46048 | Y96: =IF(AND(X96<>"",W96<>""),IF(X96<=W96,"SIM","NÃO"),"") | AC96: =IF($C96="","",IF(COUNTIF('Códigos Santander (ref)'!$A$2:$A$79,$C96)>0,"SANTANDER",IF(COUNTIF('Códigos Itaú (ref)'!$A$2:$A$44,$C96)>0,"ITAU",IF(AND(TRIM(UPPER($I96))="CONTRATUAL",ISNUMBER(SEARCH("INDIVIDUAL",SUBSTITUTE(UPPER($D96)," ","")))),"PREMIUM FREE",""))))
A97: TELA | B97: 52971 | C97: 1RUH3 | D97: BANCO SANTANDER BRASIL SA | E97: 2786641640 | F97: 1RUH3037003003 | G97: 572 | H97: 323.65 | I97: CONTRATUAL | J97: 2888202000147 | K97: DIAGNOSTICOS RADIOLOGIA ORAL LTDA | L97: CAMPINAS | M97: SP | N97: SERGIANA | O97: 523539 | P97: 46041 | Q97: 46042 | R97: AUTORIZADO PAGAMENTO | S97: 8202611363 | T97: 5 DIAS ÚTEIS | U97: 46038 | V97: 46042 | W97: 46049 | X97: 46048 | Y97: =IF(AND(X97<>"",W97<>""),IF(X97<=W97,"SIM","NÃO"),"") | AC97: =IF($C97="","",IF(COUNTIF('Códigos Santander (ref)'!$A$2:$A$79,$C97)>0,"SANTANDER",IF(COUNTIF('Códigos Itaú (ref)'!$A$2:$A$44,$C97)>0,"ITAU",IF(AND(TRIM(UPPER($I97))="CONTRATUAL",ISNUMBER(SEARCH("INDIVIDUAL",SUBSTITUTE(UPPER($D97)," ","")))),"PREMIUM FREE",""))))
A98: TELA | B98: 53053 | C98: 1RUH3 | D98: BANCO SANTANDER BRASIL SA | E98: 12864768798 | F98: 1RUH3025688022 | G98: 280 | H98: 212.19 | I98: CONTRATUAL | J98: 229031781 | K98: LEONARDO LIMA BITTENCOURT COSTA | L98: SÃO GONÇALO | M98: RJ | N98: SERGIANA | O98: JA POSSUI | R98: AUTORIZADO PAGAMENTO | S98: 8202611323 | T98: 5 DIAS ÚTEIS | U98: 46041 | V98: 46041 | W98: 46048 | X98: 46045 | Y98: =IF(AND(X98<>"",W98<>""),IF(X98<=W98,"SIM","NÃO"),"") | AC98: =IF($C98="","",IF(COUNTIF('Códigos Santander (ref)'!$A$2:$A$79,$C98)>0,"SANTANDER",IF(COUNTIF('Códigos Itaú (ref)'!$A$2:$A$44,$C98)>0,"ITAU",IF(AND(TRIM(UPPER($I98))="CONTRATUAL",ISNUMBER(SEARCH("INDIVIDUAL",SUBSTITUTE(UPPER($D98)," ","")))),"PREMIUM FREE",""))))
A99: TELA | B99: 52920 | C99: 1RU51 | D99: BANCO SANTANDER BRASIL SA | E99: 10040693830 | F99: 1RU51000205001 | G99: 350 | H99: 163.8 | I99: CONTRATUAL | J99: 24870458000160 | K99: EDWAL LOBOSCHI | L99: SÃO PAULO | M99: SP | N99: SERGIANA | O99: JA POSSUI | R99: AUTORIZADO PAGAMENTO | S99: 8202611324 | T99: 5 DIAS ÚTEIS | U99: 46041 | V99: 46041 | W99: 46048 | X99: 46045 | Y99: =IF(AND(X99<>"",W99<>""),IF(X99<=W99,"SIM","NÃO"),"") | AC99: =IF($C99="","",IF(COUNTIF('Códigos Santander (ref)'!$A$2:$A$79,$C99)>0,"SANTANDER",IF(COUNTIF('Códigos Itaú (ref)'!$A$2:$A$44,$C99)>0,"ITAU",IF(AND(TRIM(UPPER($I99))="CONTRATUAL",ISNUMBER(SEARCH("INDIVIDUAL",SUBSTITUTE(UPPER($D99)," ","")))),"PREMIUM FREE",""))))
A100: TELA | B100: 53052 | C100: 1RUH3 | D100: BANCO SANTANDER BRASIL SA | E100: 27788976822 | F100: 1RUH3034713000 | G100: 370 | H100: 243.88 | I100: CONTRATUAL | J100: 24870458000160 | K100: EDWAL LOBOSCHI | L100: SÃO PAULO | M100: SP | N100: SERGIANA | O100: JA POSSUI | R100: AUTORIZADO PAGAMENTO | S100: 8202611326 | T100: 5 DIAS ÚTEIS | U100: 46041 | V100: 46041 | W100: 46048 | X100: 46045 | Y100: =IF(AND(X100<>"",W100<>""),IF(X100<=W100,"SIM","NÃO"),"") | AC100: =IF($C100="","",IF(COUNTIF('Códigos Santander (ref)'!$A$2:$A$79,$C100)>0,"SANTANDER",IF(COUNTIF('Códigos Itaú (ref)'!$A$2:$A$44,$C100)>0,"ITAU",IF(AND(TRIM(UPPER($I100))="CONTRATUAL",ISNUMBER(SEARCH("INDIVIDUAL",SUBSTITUTE(UPPER($D100)," ","")))),"PREMIUM FREE",""))))
...

Sheet Fevereiro 2026
A1: CANAL | B1: N° SOLICITAÇÃO | C1: CÓD. EMPRESA | D1: EMPRESA | E1: CPF TITULAR | F1: COD. DO BENEFICIÁRIO | G1: VALOR SOLICITADO | H1: VALOR PAGO | I1: MOTIVO | J1: CPF/CNPJ DENTISTA | K1: NOME PRESTADOR DE SERVIÇO | L1: CIDADE PRESTADOR | M1: UF PRESTADOR | N1: AUDITOR | O1: ASTREIN | P1: DT SOLICITAÇÃO ASTREIN | Q1: DT LIBERAÇÃO ASTREIN | R1: STATUS DA SOLICITAÇÃO | S1: PROCESSO | T1: PRAZO CONTRATUAL | U1: DT AUDITORIA | V1: DT APROVAÇÃO | W1: DT PRAZO CONTRATUAL | X1: DATA DE PAGAMENTO SAP | Y1: PRAZO ATENDIDO | Z1: OBS | AC1: SEGMENTO (auxiliar automático)
A2: TELA | B2: 53289 | C2: 1RUH3 | D2: BANCO SANTANDER BRASIL SA | E2: 27277126858 | F2: 1RUH3014749009 | G2: 350 | H2: 243.88 | I2: CONTRATUAL | J2: 24870458000160 | K2: EDWAL LOBOSCHI | L2: SÃO PAULO | M2: SP | N2: SERGIANA | O2: JA POSSUI | R2: AUTORIZADO PAGAMENTO | S2: 8202617774 | T2: 5 DIAS ÚTEIS | U2: 46052 | V2: 46055 | W2: 46062 | X2: 46059 | Y2: =IF(AND(X2<>"",W2<>""),IF(X2<=W2,"SIM","NÃO"),"") | AC2: =IF($C2="","",IF(COUNTIF('Códigos Santander (ref)'!$A$2:$A$79,$C2)>0,"SANTANDER",IF(COUNTIF('Códigos Itaú (ref)'!$A$2:$A$44,$C2)>0,"ITAU",IF(AND(TRIM(UPPER($I2))="CONTRATUAL",ISNUMBER(SEARCH("INDIVIDUAL",SUBSTITUTE(UPPER($D2)," ","")))),"PREMIUM FREE",""))))
A3: TELA | B3: 53186 | C3: 1RU51 | D3: BANCO SANTANDER BRASIL SA | E3: 764153846 | F3: 1RU51000760005 | G3: 140 | H3: 140 | I3: CONTRATUAL | J3: 2190751000143 | K3: UNIRAD SERVICOS ODONTOLOGICOS LTDA | L3: SÃO PAULO | M3: SP | N3: SERGIANA | O3: JA POSSUI | R3: AUTORIZADO PAGAMENTO | S3: 8202617776 | T3: 5 DIAS ÚTEIS | U3: 46052 | V3: 46055 | W3: 46062 | X3: 46059 | Y3: =IF(AND(X3<>"",W3<>""),IF(X3<=W3,"SIM","NÃO"),"") | AC3: =IF($C3="","",IF(COUNTIF('Códigos Santander (ref)'!$A$2:$A$79,$C3)>0,"SANTANDER",IF(COUNTIF('Códigos Itaú (ref)'!$A$2:$A$44,$C3)>0,"ITAU",IF(AND(TRIM(UPPER($I3))="CONTRATUAL",ISNUMBER(SEARCH("INDIVIDUAL",SUBSTITUTE(UPPER($D3)," ","")))),"PREMIUM FREE",""))))
A4: TELA | B4: 51889 | C4: 1RUH3 | D4: BANCO SANTANDER BRASIL SA | E4: 26501291828 | F4: 1RUH3030923000 | G4: 360 | H4: 243.88 | I4: CONTRATUAL | J4: 15739539897 | K4: MARCIA REGINA DE OLIVEIRA FARINA | L4: SÃO PAULO | M4: SP | N4: SERGIANA | O4: 526826 | P4: 46052 | Q4: 46055 | R4: AUTORIZADO PAGAMENTO | S4: 8202617873 | T4: 5 DIAS ÚTEIS | U4: 46051 | V4: 46056 | W4: 46063 | X4: 46062 | Y4: =IF(AND(X4<>"",W4<>""),IF(X4<=W4,"SIM","NÃO"),"") | AC4: =IF($C4="","",IF(COUNTIF('Códigos Santander (ref)'!$A$2:$A$79,$C4)>0,"SANTANDER",IF(COUNTIF('Códigos Itaú (ref)'!$A$2:$A$44,$C4)>0,"ITAU",IF(AND(TRIM(UPPER($I4))="CONTRATUAL",ISNUMBER(SEARCH("INDIVIDUAL",SUBSTITUTE(UPPER($D4)," ","")))),"PREMIUM FREE",""))))
A5: TELA | B5: 51965 | C5: 1RUH3 | D5: BANCO SANTANDER BRASIL SA | E5: 26501291828 | F5: 1RUH3030923018 | G5: 360 | H5: 243.88 | I5: CONTRATUAL | J5: 15739539897 | K5: MARCIA REGINA DE OLIVEIRA FARINA | L5: SÃO PAULO | M5: SP | N5: SERGIANA | O5: 526826 | P5: 46052 | Q5: 46055 | R5: AUTORIZADO PAGAMENTO | S5: 8202617874 | T5: 5 DIAS ÚTEIS | U5: 46051 | V5: 46056 | W5: 46063 | X5: 46057 | Y5: =IF(AND(X5<>"",W5<>""),IF(X5<=W5,"SIM","NÃO"),"") | AC5: =IF($C5="","",IF(COUNTIF('Códigos Santander (ref)'!$A$2:$A$79,$C5)>0,"SANTANDER",IF(COUNTIF('Códigos Itaú (ref)'!$A$2:$A$44,$C5)>0,"ITAU",IF(AND(TRIM(UPPER($I5))="CONTRATUAL",ISNUMBER(SEARCH("INDIVIDUAL",SUBSTITUTE(UPPER($D5)," ","")))),"PREMIUM FREE",""))))
A6: TELA | B6: 51780 | C6: 1RUH3 | D6: BANCO SANTANDER BRASIL SA | E6: 26501291828 | F6: 1RUH3030923026 | G6: 360 | H6: 173.51 | I6: CONTRATUAL | J6: 15739539897 | K6: MARCIA REGINA DE OLIVEIRA FARINA | L6: SÃO PAULO | M6: SP | N6: SERGIANA | O6: 526826 | P6: 46052 | Q6: 46055 | R6: AUTORIZADO PAGAMENTO | S6: 8202617875 | T6: 5 DIAS ÚTEIS | U6: 46051 | V6: 46056 | W6: 46063 | X6: 46057 | Y6: =IF(AND(X6<>"",W6<>""),IF(X6<=W6,"SIM","NÃO"),"") | AC6: =IF($C6="","",IF(COUNTIF('Códigos Santander (ref)'!$A$2:$A$79,$C6)>0,"SANTANDER",IF(COUNTIF('Códigos Itaú (ref)'!$A$2:$A$44,$C6)>0,"ITAU",IF(AND(TRIM(UPPER($I6))="CONTRATUAL",ISNUMBER(SEARCH("INDIVIDUAL",SUBSTITUTE(UPPER($D6)," ","")))),"PREMIUM FREE",""))))
A7: SAC | B7: 53143 | C7: 0JMJX | D7: MARIA JEUSA DO NASCIMENTO ALMEIDA | E7: 15183274860 | F7: 0JMJX472647011 | G7: 300 | H7: 300 | I7: INSUFICIÊNCIA DE REDE | J7: 59527440000144 | K7: UNIODONTO DE JUNDIAI-COOPERATIVA ODONTOLOGICA | L7: JUNDIAÍ | M7: SP | N7: SERGIANA | O7: 526730 | P7: 46052 | Q7: 46055 | R7: AUTORIZADO PAGAMENTO | S7: 8202617772 | T7: 30 DIAS CORRIDOS | U7: 46051 | V7: 46055 | W7: 46083 | X7: 46057 | Y7: =IF(AND(X7<>"",W7<>""),IF(X7<=W7,"SIM","NÃO"),"") | AC7: =IF($C7="","",IF(COUNTIF('Códigos Santander (ref)'!$A$2:$A$79,$C7)>0,"SANTANDER",IF(COUNTIF('Códigos Itaú (ref)'!$A$2:$A$44,$C7)>0,"ITAU",IF(AND(TRIM(UPPER($I7))="CONTRATUAL",ISNUMBER(SEARCH("INDIVIDUAL",SUBSTITUTE(UPPER($D7)," ","")))),"PREMIUM FREE",""))))
A8: TELA | B8: 53289 | C8: 1RUH3 | D8: BANCO SANTANDER BRASIL SA | E8: 27277126858 | F8: 1RUH3014749009 | G8: 350 | H8: 243.88 | I8: CONTRATUAL | J8: 24870458000160 | K8: EDWAL LOBOSCHI | L8: SÃO PAULO | M8: SP | N8: SERGIANA | O8: JA POSSUI | R8: AUTORIZADO PAGAMENTO | S8: 8202617774 | T8: 5 DIAS ÚTEIS | U8: 46052 | V8: 46055 | W8: 46062 | X8: 46059 | Y8: =IF(AND(X8<>"",W8<>""),IF(X8<=W8,"SIM","NÃO"),"") | AC8: =IF($C8="","",IF(COUNTIF('Códigos Santander (ref)'!$A$2:$A$79,$C8)>0,"SANTANDER",IF(COUNTIF('Códigos Itaú (ref)'!$A$2:$A$44,$C8)>0,"ITAU",IF(AND(TRIM(UPPER($I8))="CONTRATUAL",ISNUMBER(SEARCH("INDIVIDUAL",SUBSTITUTE(UPPER($D8)," ","")))),"PREMIUM FREE",""))))
A9: TELA | B9: 53186 | C9: 1RU51 | D9: BANCO SANTANDER BRASIL SA | E9: 764153846 | F9: 1RU51000760005 | G9: 140 | H9: 140 | I9: CONTRATUAL | J9: 2190751000143 | K9: UNIRAD SERVICOS ODONTOLOGICOS LTDA | L9: SÃO PAULO | M9: SP | N9: SERGIANA | O9: JA POSSUI | R9: AUTORIZADO PAGAMENTO | S9: 8202617776 | T9: 5 DIAS ÚTEIS | U9: 46052 | V9: 46055 | W9: 46062 | X9: 46059 | Y9: =IF(AND(X9<>"",W9<>""),IF(X9<=W9,"SIM","NÃO"),"") | AC9: =IF($C9="","",IF(COUNTIF('Códigos Santander (ref)'!$A$2:$A$79,$C9)>0,"SANTANDER",IF(COUNTIF('Códigos Itaú (ref)'!$A$2:$A$44,$C9)>0,"ITAU",IF(AND(TRIM(UPPER($I9))="CONTRATUAL",ISNUMBER(SEARCH("INDIVIDUAL",SUBSTITUTE(UPPER($D9)," ","")))),"PREMIUM FREE",""))))
A10: TELA | B10: 53280 | C10: 1RUB1 | D10: F1RST TECNOLOGIA E INOVACAO LTDA | E10: 16240400807 | F10: 1RUB1000530000 | G10: 908 | H10: 243.88 | I10: CONTRATUAL | J10: 2627303163 | K10: LAURA GUIMARAES MELO COSTA | L10: SANTOS | M10: SP | N10: SERGIANA | O10: 527566 | P10: 46056 | Q10: 46057 | R10: AUTORIZADO PAGAMENTO | S10: 8202617965 | T10: 5 DIAS ÚTEIS | U10: 46056 | V10: 46058 | W10: 46065 | X10: 46064 | Y10: SIM | AC10: =IF($C10="","",IF(COUNTIF('Códigos Santander (ref)'!$A$2:$A$79,$C10)>0,"SANTANDER",IF(COUNTIF('Códigos Itaú (ref)'!$A$2:$A$44,$C10)>0,"ITAU",IF(AND(TRIM(UPPER($I10))="CONTRATUAL",ISNUMBER(SEARCH("INDIVIDUAL",SUBSTITUTE(UPPER($D10)," ","")))),"PREMIUM FREE",""))))
A11: TELA | B11: 53293 | C11: 1RUD5 | D11: SANTANDER HOLDING IMOBILIARIA SA | E11: 26534957833 | F11: 1RUD5000037010 | G11: 300 | H11: 212.19 | I11: CONTRATUAL | J11: 21315482819 | K11: CRISTINA YUKA HASSUNUMA | L11: SÃO PAULO | M11: SP | N11: SERGIANA | O11: JA POSSUI | R11: AUTORIZADO PAGAMENTO | S11: 8202617888 | T11: 5 DIAS ÚTEIS | U11: 46056 | V11: 46056 | W11: 46063 | X11: 46062 | Y11: SIM | AC11: =IF($C11="","",IF(COUNTIF('Códigos Santander (ref)'!$A$2:$A$79,$C11)>0,"SANTANDER",IF(COUNTIF('Códigos Itaú (ref)'!$A$2:$A$44,$C11)>0,"ITAU",IF(AND(TRIM(UPPER($I11))="CONTRATUAL",ISNUMBER(SEARCH("INDIVIDUAL",SUBSTITUTE(UPPER($D11)," ","")))),"PREMIUM FREE",""))))
A12: TELA | B12: 53331 | C12: 1RUH3 | D12: BANCO SANTANDER BRASIL SA | E12: 46992730843 | F12: 1RUH3006876021 | G12: 150 | H12: 150 | I12: CONTRATUAL | J12: 37710114857 | K12: LARISSA SANDY DA SILVA LEITE | L12: CRUZEIRO | M12: SP | N12: SERGIANA | O12: JA POSSUI | R12: AUTORIZADO PAGAMENTO | S12: 8202617889 | T12: 5 DIAS ÚTEIS | U12: 46056 | V12: 46056 | W12: 46063 | X12: 46062 | Y12: SIM | AC12: =IF($C12="","",IF(COUNTIF('Códigos Santander (ref)'!$A$2:$A$79,$C12)>0,"SANTANDER",IF(COUNTIF('Códigos Itaú (ref)'!$A$2:$A$44,$C12)>0,"ITAU",IF(AND(TRIM(UPPER($I12))="CONTRATUAL",ISNUMBER(SEARCH("INDIVIDUAL",SUBSTITUTE(UPPER($D12)," ","")))),"PREMIUM FREE",""))))
A13: TELA | B13: 48305 | C13: 1RSX8 | D13: ITAU UNIBANCO SA | E13: 73126810772 | F13: 1RSX8000317012 | G13: 4490 | H13: 931 | I13: CONTRATUAL | J13: 7959716722 | K13: JULIANA VIEGAS SONEGHETI | L13: NITERÓI | M13: RJ | N13: SERGIANA | O13: JA POSSUI | R13: AUTORIZADO PAGAMENTO | S13: 8202617890 | T13: 5 DIAS ÚTEIS | U13: 46056 | V13: 46056 | W13: 46063 | X13: 46062 | Y13: SIM | AC13: =IF($C13="","",IF(COUNTIF('Códigos Santander (ref)'!$A$2:$A$79,$C13)>0,"SANTANDER",IF(COUNTIF('Códigos Itaú (ref)'!$A$2:$A$44,$C13)>0,"ITAU",IF(AND(TRIM(UPPER($I13))="CONTRATUAL",ISNUMBER(SEARCH("INDIVIDUAL",SUBSTITUTE(UPPER($D13)," ","")))),"PREMIUM FREE",""))))
A14: TELA | B14: 46747 | C14: 1RUH3 | D14: BANCO SANTANDER BRASIL SA | E14: 40072933844 | F14: 1RUH3038441004 | G14: 3200 | H14: 470.25 | I14: CONTRATUAL | J14: 30589069861 | K14: SILVIO A. T. MACHADO FILHO | L14: SÃO PAULO | M14: SP | N14: SERGIANA | O14: 527568 | P14: 46056 | Q14: 46062 | R14: AUTORIZADO PAGAMENTO | S14: 8202618173 | T14: 5 DIAS ÚTEIS | U14: 46056 | V14: 46062 | W14: 46069 | X14: 46071 | Y14: NÃO | AC14: =IF($C14="","",IF(COUNTIF('Códigos Santander (ref)'!$A$2:$A$79,$C14)>0,"SANTANDER",IF(COUNTIF('Códigos Itaú (ref)'!$A$2:$A$44,$C14)>0,"ITAU",IF(AND(TRIM(UPPER($I14))="CONTRATUAL",ISNUMBER(SEARCH("INDIVIDUAL",SUBSTITUTE(UPPER($D14)," ","")))),"PREMIUM FREE",""))))
A15: TELA | B15: 53290 | C15: 1RUH3 | D15: BANCO SANTANDER BRASIL SA | E15: 22024640850 | F15: 1RUH3033793018 | G15: 352.06 | H15: 352.06 | I15: CONTRATUAL | J15: 5671101000108 | K15: FORMMA ODONTO LTDA | L15: SÃO PAULO | M15: SP | N15: SERGIANA | O15: JA POSSUI | R15: AUTORIZADO PAGAMENTO | S15: 8202617891 | T15: 5 DIAS ÚTEIS | U15: 46056 | V15: 46056 | W15: 46063 | X15: 46062 | Y15: SIM | AC15: =IF($C15="","",IF(COUNTIF('Códigos Santander (ref)'!$A$2:$A$79,$C15)>0,"SANTANDER",IF(COUNTIF('Códigos Itaú (ref)'!$A$2:$A$44,$C15)>0,"ITAU",IF(AND(TRIM(UPPER($I15))="CONTRATUAL",ISNUMBER(SEARCH("INDIVIDUAL",SUBSTITUTE(UPPER($D15)," ","")))),"PREMIUM FREE",""))))
A16: TELA | B16: 53225 | C16: 1RU51 | D16: BANCO SANTANDER BRASIL SA | E16: 21957476842 | F16: 1RU51000355011 | G16: 210 | H16: 90.94 | I16: CONTRATUAL | J16: 8229165000141 | K16: CLINICA NEW LIFE PRIME ODONTOLOGIA LTDA | L16: SÃO PAULO | M16: SP | N16: SERGIANA | O16: JA POSSUI | R16: AUTORIZADO PAGAMENTO | S16: 8202617892 | T16: 5 DIAS ÚTEIS | U16: 46056 | V16: 46056 | W16: 46063 | X16: 46062 | Y16: SIM | AC16: =IF($C16="","",IF(COUNTIF('Códigos Santander (ref)'!$A$2:$A$79,$C16)>0,"SANTANDER",IF(COUNTIF('Códigos Itaú (ref)'!$A$2:$A$44,$C16)>0,"ITAU",IF(AND(TRIM(UPPER($I16))="CONTRATUAL",ISNUMBER(SEARCH("INDIVIDUAL",SUBSTITUTE(UPPER($D16)," ","")))),"PREMIUM FREE",""))))
A17: TELA | B17: 53189 | C17: 1RBB2 | D17: PROTEGE SA PROTECAO E TRANSPORTE DE VALORES | E17: 7054095626 | F17: 1RBB2000304000 | G17: 55 | H17: 55 | I17: COBRANÇA INDEVIDA | J17: 29727662000140 | K17: ODONTOMED CONSULTORIO E SERVICOS LTDA | L17: MURIAÉ | M17: MG | N17: SERGIANA | O17: 527569 | P17: 46056 | Q17: 46063 | R17: AUTORIZADO PAGAMENTO | S17: 8202618221 | T17: 30 DIAS CORRIDOS | U17: 46056 | V17: 46063 | W17: 46091 | X17: 46071 | Y17: SIM | AC17: =IF($C17="","",IF(COUNTIF('Códigos Santander (ref)'!$A$2:$A$79,$C17)>0,"SANTANDER",IF(COUNTIF('Códigos Itaú (ref)'!$A$2:$A$44,$C17)>0,"ITAU",IF(AND(TRIM(UPPER($I17))="CONTRATUAL",ISNUMBER(SEARCH("INDIVIDUAL",SUBSTITUTE(UPPER($D17)," ","")))),"PREMIUM FREE",""))))
A18: TELA | B18: 53247 | C18: 1RBB2 | D18: PROTEGE SA PROTECAO E TRANSPORTE DE VALORES | E18: 7054095626 | F18: 1RBB2000304000 | G18: 50 | H18: 20 | I18: INSUFICIÊNCIA DE REDE | J18: 58148715000176 | K18: RXT RADIOLOGIA ODONTOLOGICA LTDA | L18: MURIAÉ | M18: MG | N18: SERGIANA | O18: 527569 | P18: 46056 | Q18: 46063 | R18: AUTORIZADO PAGAMENTO | S18: 8202618222 | T18: 30 DIAS CORRIDOS | U18: 46056 | V18: 46063 | W18: 46091 | X18: 46071 | Y18: SIM | AC18: =IF($C18="","",IF(COUNTIF('Códigos Santander (ref)'!$A$2:$A$79,$C18)>0,"SANTANDER",IF(COUNTIF('Códigos Itaú (ref)'!$A$2:$A$44,$C18)>0,"ITAU",IF(AND(TRIM(UPPER($I18))="CONTRATUAL",ISNUMBER(SEARCH("INDIVIDUAL",SUBSTITUTE(UPPER($D18)," ","")))),"PREMIUM FREE",""))))
A19: TELA | B19: 53248 | C19: 1RBB2 | D19: PROTEGE SA PROTECAO E TRANSPORTE DE VALORES | E19: 7054095626 | F19: 1RBB2000304000 | G19: 50 | H19: 50 | I19: INSUFICIÊNCIA DE REDE | J19: 12257539000100 | K19: RADIOLOGIA ODONTOLOGICA DIGITAL DE MURIAÃ LTDA | L19: MURIAÉ | M19: MG | N19: SERGIANA | O19: 527569 | P19: 46056 | Q19: 46063 | R19: AUTORIZADO PAGAMENTO | S19: 8202618223 | T19: 30 DIAS CORRIDOS | U19: 46056 | V19: 46063 | W19: 46091 | X19: 46071 | Y19: SIM | AC19: =IF($C19="","",IF(COUNTIF('Códigos Santander (ref)'!$A$2:$A$79,$C19)>0,"SANTANDER",IF(COUNTIF('Códigos Itaú (ref)'!$A$2:$A$44,$C19)>0,"ITAU",IF(AND(TRIM(UPPER($I19))="CONTRATUAL",ISNUMBER(SEARCH("INDIVIDUAL",SUBSTITUTE(UPPER($D19)," ","")))),"PREMIUM FREE",""))))
A20: EMAIL | B20: 53307 | C20: 0JMK0 | D20: KISTON RESTAURANTES LTDA | E20: 9944560693 | F20: 0JMK0127277001 | G20: 180 | H20: 180 | I20: COBRANÇA INDEVIDA | J20: 36420865000154 | K20: DESIGNO DO SORRISO LTDA | L20: SÃO PAULO | M20: SP | N20: CIBELY | O20: 527574 | P20: 46056 | Q20: 46057 | R20: AUTORIZADO PAGAMENTO | S20: 8202617966 | T20: 30 DIAS CORRIDOS | U20: 46056 | V20: 46058 | W20: 46086 | X20: 46064 | Y20: SIM | AC20: =IF($C20="","",IF(COUNTIF('Códigos Santander (ref)'!$A$2:$A$79,$C20)>0,"SANTANDER",IF(COUNTIF('Códigos Itaú (ref)'!$A$2:$A$44,$C20)>0,"ITAU",IF(AND(TRIM(UPPER($I20))="CONTRATUAL",ISNUMBER(SEARCH("INDIVIDUAL",SUBSTITUTE(UPPER($D20)," ","")))),"PREMIUM FREE",""))))
A21: TELA | B21: 52913 | C21: 50700 | D21: INDIVIDUAL MAISODONTO | E21: 235112577 | F21: 50700435930007 | G21: 350 | H21: 52.2 | I21: CONTRATUAL | J21: 96038624520 | K21: ODONTO FACE CENTER | L21: EUNAPOLIS | M21: BA | N21: SERGIANA | O21: 527585 | P21: 46056 | Q21: 46057 | R21: AUTORIZADO PAGAMENTO | S21: 8202618048 | T21: 30 DIAS CORRIDOS | U21: 46056 | V21: 46058 | W21: 46086 | X21: 46064 | Y21: SIM | AC21: =IF($C21="","",IF(COUNTIF('Códigos Santander (ref)'!$A$2:$A$79,$C21)>0,"SANTANDER",IF(COUNTIF('Códigos Itaú (ref)'!$A$2:$A$44,$C21)>0,"ITAU",IF(AND(TRIM(UPPER($I21))="CONTRATUAL",ISNUMBER(SEARCH("INDIVIDUAL",SUBSTITUTE(UPPER($D21)," ","")))),"PREMIUM FREE",""))))
A22: NIP | B22: 51531 | C22: 0700G | D22: INDIVIDUAL | E22: 9197014699 | F22: 0700G400908005 | G22: 1000 | H22: 126 | I22: CONTRATUAL | J22: 5744533000100 | K22: NUCLEO ODONTOLOGICO LOURDES LTDA | L22: BELO HORIZONTE | M22: MG | N22: SERGIANA | O22: 527980 | P22: 46059 | Q22: 46062 | R22: AUTORIZADO PAGAMENTO | S22: 8202618174 | T22: 30 DIAS CORRIDOS | U22: 46057 | V22: 46062 | W22: 46090 | X22: 46071 | Y22: SIM | AC22: =IF($C22="","",IF(COUNTIF('Códigos Santander (ref)'!$A$2:$A$79,$C22)>0,"SANTANDER",IF(COUNTIF('Códigos Itaú (ref)'!$A$2:$A$44,$C22)>0,"ITAU",IF(AND(TRIM(UPPER($I22))="CONTRATUAL",ISNUMBER(SEARCH("INDIVIDUAL",SUBSTITUTE(UPPER($D22)," ","")))),"PREMIUM FREE",""))))
A23: TELA | B23: 52946 | C23: 1RUH3 | D23: BANCO SANTANDER BRASIL SA | E23: 33006382838 | F23: 1RUH3024620009 | G23: 2900 | H23: 977.33 | I23: CONTRATUAL | J23: 45641559000139 | K23: MM CLINICA ODONTOLOGICA S/S LTDA | L23: SÃO PAULO | M23: SP | N23: SERGIANA | O23: 528488 | P23: 46059 | Q23: 46063 | R23: AUTORIZADO PAGAMENTO | S23: 8202618219 | T23: 5 DIAS ÚTEIS | U23: 46057 | V23: 46063 | W23: 46070 | X23: 46071 | Y23: NÃO | AC23: =IF($C23="","",IF(COUNTIF('Códigos Santander (ref)'!$A$2:$A$79,$C23)>0,"SANTANDER",IF(COUNTIF('Códigos Itaú (ref)'!$A$2:$A$44,$C23)>0,"ITAU",IF(AND(TRIM(UPPER($I23))="CONTRATUAL",ISNUMBER(SEARCH("INDIVIDUAL",SUBSTITUTE(UPPER($D23)," ","")))),"PREMIUM FREE",""))))
A24: TELA | B24: 53055 | C24: 0M1CA | D24: CARREFOUR COMERCIO E INDUSTRIA LTDA | E24: 34485510824 | F24: 0M1CA011476036 | G24: 91.2 | H24: 91.2 | I24: CONTRATUAL | J24: 29870689809 | K24: CENTRO ODONTOLOGICO PARQUE DAS NACOES LTDA | L24: SANTO ANDRÉ | M24: SP | N24: SERGIANA | O24: JA POSSUI | R24: AUTORIZADO PAGAMENTO | S24: 8202617967 | T24: 5 DIAS ÚTEIS | U24: 46057 | V24: 46058 | W24: 46065 | X24: 46064 | Y24: SIM | AC24: =IF($C24="","",IF(COUNTIF('Códigos Santander (ref)'!$A$2:$A$79,$C24)>0,"SANTANDER",IF(COUNTIF('Códigos Itaú (ref)'!$A$2:$A$44,$C24)>0,"ITAU",IF(AND(TRIM(UPPER($I24))="CONTRATUAL",ISNUMBER(SEARCH("INDIVIDUAL",SUBSTITUTE(UPPER($D24)," ","")))),"PREMIUM FREE",""))))
A25: TELA | B25: 53251 | C25: 1RU72 | D25: SANTANDER BRASIL TECNOLOGIA SA | E25: 4530351831 | F25: 1RU72000009016 | G25: 340 | H25: 192.85 | I25: CONTRATUAL | J25: 10767888000146 | K25: SR ODONTOLOGIA INTEGRADA LTDA | L25: SÃO PAULO | M25: SP | N25: SERGIANA | O25: JA POSSUI | R25: AUTORIZADO PAGAMENTO | S25: 8202618047 | T25: 5 DIAS ÚTEIS | U25: 46057 | V25: 46058 | W25: 46065 | X25: 46064 | Y25: SIM | AC25: =IF($C25="","",IF(COUNTIF('Códigos Santander (ref)'!$A$2:$A$79,$C25)>0,"SANTANDER",IF(COUNTIF('Códigos Itaú (ref)'!$A$2:$A$44,$C25)>0,"ITAU",IF(AND(TRIM(UPPER($I25))="CONTRATUAL",ISNUMBER(SEARCH("INDIVIDUAL",SUBSTITUTE(UPPER($D25)," ","")))),"PREMIUM FREE",""))))
A26: TELA | B26: 52847 | C26: 60300 | D26: INDIVIDUAL | E26: 7654056109 | F26: 60300860832016 | G26: 2250 | H26: 130.8 | I26: CONTRATUAL | J26: 52147029000102 | K26: N P CONSULTORIO ODONTOLOGICO | L26: GOIANIA | M26: GO | N26: SERGIANA | O26: 528500 | P26: 46059 | Q26: 46062 | R26: AUTORIZADO PAGAMENTO | S26: 8202618214 | T26: 30 DIAS CORRIDOS | U26: 46057 | V26: 46063 | W26: 46091 | X26: 46071 | Y26: SIM | AC26: =IF($C26="","",IF(COUNTIF('Códigos Santander (ref)'!$A$2:$A$79,$C26)>0,"SANTANDER",IF(COUNTIF('Códigos Itaú (ref)'!$A$2:$A$44,$C26)>0,"ITAU",IF(AND(TRIM(UPPER($I26))="CONTRATUAL",ISNUMBER(SEARCH("INDIVIDUAL",SUBSTITUTE(UPPER($D26)," ","")))),"PREMIUM FREE",""))))
A27: TELA | B27: 51786 | C27: 1RU51 | D27: BANCO SANTANDER BRASIL SA | E27: 9033885883 | F27: 1RU51000622001 | G27: 500 | H27: 159.3 | I27: CONTRATUAL | J27: 7746721885 | K27: PAULO EDUARDO DAMIANI | L27: SÃO PAULO | M27: SP | N27: SERGIANA | O27: JA POSSUI | R27: AUTORIZADO PAGAMENTO | S27: 8202617968 | T27: 5 DIAS ÚTEIS | U27: 46057 | V27: 46058 | W27: 46065 | X27: 46064 | Y27: SIM | AC27: =IF($C27="","",IF(COUNTIF('Códigos Santander (ref)'!$A$2:$A$79,$C27)>0,"SANTANDER",IF(COUNTIF('Códigos Itaú (ref)'!$A$2:$A$44,$C27)>0,"ITAU",IF(AND(TRIM(UPPER($I27))="CONTRATUAL",ISNUMBER(SEARCH("INDIVIDUAL",SUBSTITUTE(UPPER($D27)," ","")))),"PREMIUM FREE",""))))
A28: TELA | B28: 52336 | C28: 1RU51 | D28: BANCO SANTANDER BRASIL SA | E28: 9033885883 | F28: 1RU51000622001 | G28: 3600 | H28: 326.64 | I28: CONTRATUAL | J28: 7746721885 | K28: PAULO EDUARDO DAMIANI | L28: SÃO PAULO | M28: SP | N28: SERGIANA | O28: JA POSSUI | R28: AUTORIZADO PAGAMENTO | S28: 8202617969 | T28: 5 DIAS ÚTEIS | U28: 46057 | V28: 46058 | W28: 46065 | X28: 46064 | Y28: SIM | AC28: =IF($C28="","",IF(COUNTIF('Códigos Santander (ref)'!$A$2:$A$79,$C28)>0,"SANTANDER",IF(COUNTIF('Códigos Itaú (ref)'!$A$2:$A$44,$C28)>0,"ITAU",IF(AND(TRIM(UPPER($I28))="CONTRATUAL",ISNUMBER(SEARCH("INDIVIDUAL",SUBSTITUTE(UPPER($D28)," ","")))),"PREMIUM FREE",""))))
A29: SAC | B29: 53088 | C29: 0JFQ2 | D29: SAO LUCAS SAUDE SA | E29: 22251894802 | F29: 0JFQ2000922005 | G29: 1450 | H29: 1450 | I29: COBRANÇA INDEVIDA | J29: 34219934839 | K29: CARLOS HENRIQUE MELONI | L29: AMERICANA | M29: SP | N29: CIBELY | O29: 528509 | P29: 46059 | Q29: 46063 | R29: AUTORIZADO PAGAMENTO | S29: 8202618220 | T29: 30 DIAS CORRIDOS | U29: 46057 | V29: 46063 | W29: 46091 | X29: 46071 | Y29: SIM | AC29: =IF($C29="","",IF(COUNTIF('Códigos Santander (ref)'!$A$2:$A$79,$C29)>0,"SANTANDER",IF(COUNTIF('Códigos Itaú (ref)'!$A$2:$A$44,$C29)>0,"ITAU",IF(AND(TRIM(UPPER($I29))="CONTRATUAL",ISNUMBER(SEARCH("INDIVIDUAL",SUBSTITUTE(UPPER($D29)," ","")))),"PREMIUM FREE",""))))
A30: TELA | B30: 52930 | C30: 1RSLN | D30: ITAU UNIBANCO SA | E30: 23087866806 | F30: 1RSLN016000013 | G30: 950 | H30: 288 | I30: CONTRATUAL | J30: 33642600875 | K30: LUANA RODRIGUES DE SA DA SILVEIRA | L30: SAO JOSE DO RIO PRETO | N30: SERGIANA | O30: JA POSSUI | R30: AUTORIZADO PAGAMENTO | S30: 8202617970 | T30: 5 DIAS ÚTEIS | U30: 46057 | V30: 46058 | W30: 46065 | X30: 46064 | Y30: SIM | AC30: =IF($C30="","",IF(COUNTIF('Códigos Santander (ref)'!$A$2:$A$79,$C30)>0,"SANTANDER",IF(COUNTIF('Códigos Itaú (ref)'!$A$2:$A$44,$C30)>0,"ITAU",IF(AND(TRIM(UPPER($I30))="CONTRATUAL",ISNUMBER(SEARCH("INDIVIDUAL",SUBSTITUTE(UPPER($D30)," ","")))),"PREMIUM FREE",""))))
A31: TELA | B31: 42603 | C31: 1RSX8 | D31: ITAU UNIBANCO SA | E31: 73126810772 | F31: 1RSX8000317012 | G31: 16000 | H31: 7999.99 | I31: CONTRATUAL | J31: 7959716722 | K31: JULIANA VIEGAS SONEGHETI | L31: NITERÓI | M31: RJ | N31: SERGIANA | O31: JA POSSUI | R31: AUTORIZADO PAGAMENTO | S31: 8202617971 | T31: 5 DIAS ÚTEIS | U31: 46057 | V31: 46058 | W31: 46065 | X31: 46064 | Y31: SIM | AC31: =IF($C31="","",IF(COUNTIF('Códigos Santander (ref)'!$A$2:$A$79,$C31)>0,"SANTANDER",IF(COUNTIF('Códigos Itaú (ref)'!$A$2:$A$44,$C31)>0,"ITAU",IF(AND(TRIM(UPPER($I31))="CONTRATUAL",ISNUMBER(SEARCH("INDIVIDUAL",SUBSTITUTE(UPPER($D31)," ","")))),"PREMIUM FREE",""))))
A32: TELA | B32: 53301 | C32: 1RUH3 | D32: BANCO SANTANDER BRASIL SA | E32: 26447218811 | F32: 1RUH3032093004 | G32: 200 | H32: 200 | I32: CONTRATUAL | J32: 5389120000146 | K32: K N SERVICOS MEDICOS E ODONTOLOGICOS S/S LTDA | L32: JACAREÍ | M32: SP | N32: SERGIANA | O32: JA POSSUI | R32: AUTORIZADO PAGAMENTO | S32: 8202617972 | T32: 5 DIAS ÚTEIS | U32: 46057 | V32: 46058 | W32: 46065 | X32: 46064 | Y32: SIM | AC32: =IF($C32="","",IF(COUNTIF('Códigos Santander (ref)'!$A$2:$A$79,$C32)>0,"SANTANDER",IF(COUNTIF('Códigos Itaú (ref)'!$A$2:$A$44,$C32)>0,"ITAU",IF(AND(TRIM(UPPER($I32))="CONTRATUAL",ISNUMBER(SEARCH("INDIVIDUAL",SUBSTITUTE(UPPER($D32)," ","")))),"PREMIUM FREE",""))))
A33: TELA | B33: 53001 | C33: 50700 | D33: INDIVIDUAL MAISODONTO | E33: 13277469646 | F33: 50700440549006 | G33: 200 | H33: 200 | I33: COBRANÇA INDEVIDA | J33: 12888840000111 | K33: CLINICA DENTARIA TIRADENTES LTDA | L33: CONTAGEM | M33: MG | N33: SERGIANA | O33: 528514 | P33: 46059 | Q33: 46062 | R33: AUTORIZADO PAGAMENTO | S33: 8202618215 | T33: 30 DIAS CORRIDOS | U33: 46058 | V33: 46063 | W33: 46091 | X33: 46071 | Y33: SIM | AC33: =IF($C33="","",IF(COUNTIF('Códigos Santander (ref)'!$A$2:$A$79,$C33)>0,"SANTANDER",IF(COUNTIF('Códigos Itaú (ref)'!$A$2:$A$44,$C33)>0,"ITAU",IF(AND(TRIM(UPPER($I33))="CONTRATUAL",ISNUMBER(SEARCH("INDIVIDUAL",SUBSTITUTE(UPPER($D33)," ","")))),"PREMIUM FREE",""))))
A34: TELA | B34: 52996 | C34: 0GF7X | D34: JSL S.A. | E34: 46989579153 | F34: 0GF7X002567008 | G34: 350 | H34: 350 | I34: COBRANÇA INDEVIDA | J34: 43607045000131 | K34: CENTRO ODONTOLOGICO DRA RENATA TABORDA | L34: GOIANIA | M34: GO | N34: SERGIANA | O34: 528518 | P34: 46059 | Q34: 46063 | R34: AUTORIZADO PAGAMENTO | S34: 8202618224 | T34: 30 DIAS CORRIDOS | U34: 46058 | V34: 46063 | W34: 46091 | X34: 46071 | Y34: SIM | AC34: =IF($C34="","",IF(COUNTIF('Códigos Santander (ref)'!$A$2:$A$79,$C34)>0,"SANTANDER",IF(COUNTIF('Códigos Itaú (ref)'!$A$2:$A$44,$C34)>0,"ITAU",IF(AND(TRIM(UPPER($I34))="CONTRATUAL",ISNUMBER(SEARCH("INDIVIDUAL",SUBSTITUTE(UPPER($D34)," ","")))),"PREMIUM FREE",""))))
A35: TELA | B35: 53226 | C35: 1RSX8 | D35: ITAU UNIBANCO SA | E35: 8335805822 | F35: 1RSX8000127019 | G35: 3810 | H35: 1630.8 | I35: CONTRATUAL | J35: 56171371000190 | K35: BRUNA THAYLA OLIVEIRA DE SOUZA | L35: SÃO PAULO | M35: SP | N35: SERGIANA | O35: JA POSSUI | R35: AUTORIZADO PAGAMENTO | S35: 8202618050 | T35: 5 DIAS ÚTEIS | U35: 46058 | V35: 46059 | W35: 46066 | X35: 46064 | Y35: SIM | AC35: =IF($C35="","",IF(COUNTIF('Códigos Santander (ref)'!$A$2:$A$79,$C35)>0,"SANTANDER",IF(COUNTIF('Códigos Itaú (ref)'!$A$2:$A$44,$C35)>0,"ITAU",IF(AND(TRIM(UPPER($I35))="CONTRATUAL",ISNUMBER(SEARCH("INDIVIDUAL",SUBSTITUTE(UPPER($D35)," ","")))),"PREMIUM FREE",""))))
A36: TELA | B36: 53136 | C36: 1RUH3 | D36: BANCO SANTANDER BRASIL SA | E36: 35294731894 | F36: 1RUH3003838030 | G36: 250 | H36: 212.19 | I36: CONTRATUAL | J36: 61473217000103 | K36: LUMINA ODONTOLOGIA ESPECIALIZADA LTDA | L36: SÃO PAULO | M36: SP | N36: SERGIANA | O36: 528596 | P36: 46059 | Q36: 46063 | R36: AUTORIZADO PAGAMENTO | S36: 8202618225 | T36: 5 DIAS ÚTEIS | U36: 46058 | V36: 46063 | W36: 46070 | X36: 46071 | Y36: NÃO | Z36: Solicitado alteração de PD | AC36: =IF($C36="","",IF(COUNTIF('Códigos Santander (ref)'!$A$2:$A$79,$C36)>0,"SANTANDER",IF(COUNTIF('Códigos Itaú (ref)'!$A$2:$A$44,$C36)>0,"ITAU",IF(AND(TRIM(UPPER($I36))="CONTRATUAL",ISNUMBER(SEARCH("INDIVIDUAL",SUBSTITUTE(UPPER($D36)," ","")))),"PREMIUM FREE",""))))
A37: TELA | B37: 53283 | C37: 0M1CA | D37: CARREFOUR COMERCIO E INDUSTRIA LTDA | E37: 34485510824 | F37: 0M1CA011476036 | G37: 91.2 | H37: 91.2 | I37: CONTRATUAL | J37: 23698394000107 | K37: CENTRO ODONTOLOGICO PARQUE DAS NACOES LTDA | L37: SANTO ANDRÉ | M37: SP | N37: SERGIANA | O37: JA POSSUI | R37: AUTORIZADO PAGAMENTO | S37: 8202618110 | T37: 8 DIAS ÚTEIS | U37: 46058 | V37: 46059 | W37: 46066 | X37: 46064 | Y37: SIM | AC37: =IF($C37="","",IF(COUNTIF('Códigos Santander (ref)'!$A$2:$A$79,$C37)>0,"SANTANDER",IF(COUNTIF('Códigos Itaú (ref)'!$A$2:$A$44,$C37)>0,"ITAU",IF(AND(TRIM(UPPER($I37))="CONTRATUAL",ISNUMBER(SEARCH("INDIVIDUAL",SUBSTITUTE(UPPER($D37)," ","")))),"PREMIUM FREE",""))))
A38: TELA | B38: 53231 | C38: 1RUH3 | D38: BANCO SANTANDER BRASIL SA | E38: 3528899930 | F38: 1RUH3000745022 | G38: 350 | H38: 350 | I38: CONTRATUAL | J38: 5377690000116 | K38: UESU ODONTOLOGIA ESPECIALIZADA LTDA | L38: MARINGÁ | M38: PR | N38: SERGIANA | O38: JA POSSUI | R38: AUTORIZADO PAGAMENTO | S38: 8202618226 | T38: 5 DIAS ÚTEIS | U38: 46058 | V38: 46063 | W38: 46070 | X38: 46071 | Y38: NÃO | AC38: =IF($C38="","",IF(COUNTIF('Códigos Santander (ref)'!$A$2:$A$79,$C38)>0,"SANTANDER",IF(COUNTIF('Códigos Itaú (ref)'!$A$2:$A$44,$C38)>0,"ITAU",IF(AND(TRIM(UPPER($I38))="CONTRATUAL",ISNUMBER(SEARCH("INDIVIDUAL",SUBSTITUTE(UPPER($D38)," ","")))),"PREMIUM FREE",""))))
A39: TELA | B39: 53407 | C39: 1RUGZ | D39: SX TOOLS SOLUC SERV COMPARTILHADOS LTDA | E39: 27057965842 | F39: 1RUGZ003111008 | G39: 400 | H39: 124.6 | I39: CONTRATUAL | J39: 24666522859 | K39: ANGELA DE CASSIA NAZARETH SOUTO | L39: SÃO PAULO | M39: SP | N39: SERGIANA | O39: 528525 | P39: 46059 | Q39: 46063 | R39: AUTORIZADO PAGAMENTO | S39: 8202618227 | T39: 5 DIAS ÚTEIS | U39: 46058 | V39: 46063 | W39: 46070 | X39: 46071 | Y39: NÃO | AC39: =IF($C39="","",IF(COUNTIF('Códigos Santander (ref)'!$A$2:$A$79,$C39)>0,"SANTANDER",IF(COUNTIF('Códigos Itaú (ref)'!$A$2:$A$44,$C39)>0,"ITAU",IF(AND(TRIM(UPPER($I39))="CONTRATUAL",ISNUMBER(SEARCH("INDIVIDUAL",SUBSTITUTE(UPPER($D39)," ","")))),"PREMIUM FREE",""))))
A40: TELA | B40: 51665 | C40: 60300 | D40: INDIVIDUAL | E40: 51656914549 | F40: 60300849475024 | G40: 750 | H40: 111.9 | I40: COBRANÇA INDEVIDA | J40: 99593807500 | K40: THIAGO CAVALCANTE MILET | L40: ARACAJU | M40: SE | N40: SERGIANA | O40: 528527 | P40: 46059 | Q40: 46062 | R40: AUTORIZADO PAGAMENTO | S40: 8202618216 | T40: 30 DIAS CORRIDOS | U40: 46059 | V40: 46063 | W40: 46091 | X40: 46071 | Y40: SIM | AC40: =IF($C40="","",IF(COUNTIF('Códigos Santander (ref)'!$A$2:$A$79,$C40)>0,"SANTANDER",IF(COUNTIF('Códigos Itaú (ref)'!$A$2:$A$44,$C40)>0,"ITAU",IF(AND(TRIM(UPPER($I40))="CONTRATUAL",ISNUMBER(SEARCH("INDIVIDUAL",SUBSTITUTE(UPPER($D40)," ","")))),"PREMIUM FREE",""))))
A41: LECOM | B41: 53447 | C41: 1RTQK | D41: FABRISPUMA COLCHOES E MOVEIS LTDA | E41: 42707354813 | F41: 1RTQK000326003 | G41: 80 | H41: 80 | I41: CONTRATUAL | J41: 619727000151 | K41: ROI - RADIOLOGIA ODONTOLOGICA ITU LTDA | L41: ITU | M41: SP | N41: VITORIA | O41: 528492 | P41: 46059 | Q41: 46062 | R41: AUTORIZADO PAGAMENTO | S41: 8202618217 | T41: 30 DIAS CORRIDOS | U41: 46059 | V41: 46063 | W41: 46091 | X41: 46071 | Y41: SIM | Z41: LECOM | AC41: =IF($C41="","",IF(COUNTIF('Códigos Santander (ref)'!$A$2:$A$79,$C41)>0,"SANTANDER",IF(COUNTIF('Códigos Itaú (ref)'!$A$2:$A$44,$C41)>0,"ITAU",IF(AND(TRIM(UPPER($I41))="CONTRATUAL",ISNUMBER(SEARCH("INDIVIDUAL",SUBSTITUTE(UPPER($D41)," ","")))),"PREMIUM FREE",""))))
A42: TELA | B42: 53302 | C42: 1RUD4 | D42: SANTANDER SEC SERV BR DIST TIT VAL IMOB SA | E42: 27503251883 | F42: 1RUD4000220000 | G42: 220 | H42: 124.6 | I42: CONTRATUAL | J42: 48284105000146 | K42: CLINICA ODONTOLOGICA T.L.L. LTDA | L42: SÃO PAULO | M42: SP | N42: SERGIANA | O42: 528548 | P42: 46059 | Q42: 46063 | R42: AUTORIZADO PAGAMENTO | S42: 8202618218 | T42: 5 DIAS ÚTEIS | U42: 46059 | V42: 46063 | W42: 46070 | X42: 46071 | Y42: NÃO | AC42: =IF($C42="","",IF(COUNTIF('Códigos Santander (ref)'!$A$2:$A$79,$C42)>0,"SANTANDER",IF(COUNTIF('Códigos Itaú (ref)'!$A$2:$A$44,$C42)>0,"ITAU",IF(AND(TRIM(UPPER($I42))="CONTRATUAL",ISNUMBER(SEARCH("INDIVIDUAL",SUBSTITUTE(UPPER($D42)," ","")))),"PREMIUM FREE",""))))
A43: TELA | B43: 53391 | C43: 1RSX8 | D43: ITAU UNIBANCO SA | E43: 86498584734 | F43: 1RSX8000168009 | G43: 330 | H43: 162 | I43: CONTRATUAL | J43: 5187127705 | K43: LUCINDA MERCEDES CORDEIRO DE V OLIVEIRA | L43: SÃO GONÇALO | M43: RJ | N43: SERGIANA | O43: JA POSSUI | R43: AUTORIZADO PAGAMENTO | S43: 8202618109 | T43: 5 DIAS ÚTEIS | U43: 46059 | V43: 46059 | W43: 46066 | X43: 46064 | Y43: SIM | AC43: =IF($C43="","",IF(COUNTIF('Códigos Santander (ref)'!$A$2:$A$79,$C43)>0,"SANTANDER",IF(COUNTIF('Códigos Itaú (ref)'!$A$2:$A$44,$C43)>0,"ITAU",IF(AND(TRIM(UPPER($I43))="CONTRATUAL",ISNUMBER(SEARCH("INDIVIDUAL",SUBSTITUTE(UPPER($D43)," ","")))),"PREMIUM FREE",""))))
A44: TELA | B44: 52446 | C44: 1RSLN | D44: ITAU UNIBANCO SA | E44: 21955135860 | F44: 1RSLN014848007 | G44: 3525 | H44: 1693 | I44: CONTRATUAL | J44: 16897597805 | K44: ELISABETE RAMALHO SOARES | L44: SÃO PAULO | M44: SP | N44: CIBELY | O44: JA POSSUI | R44: AUTORIZADO PAGAMENTO | S44: 8202618108 | T44: 5 DIAS ÚTEIS | U44: 46059 | V44: 46059 | W44: 46066 | X44: 46064 | Y44: SIM | AC44: =IF($C44="","",IF(COUNTIF('Códigos Santander (ref)'!$A$2:$A$79,$C44)>0,"SANTANDER",IF(COUNTIF('Códigos Itaú (ref)'!$A$2:$A$44,$C44)>0,"ITAU",IF(AND(TRIM(UPPER($I44))="CONTRATUAL",ISNUMBER(SEARCH("INDIVIDUAL",SUBSTITUTE(UPPER($D44)," ","")))),"PREMIUM FREE",""))))
A45: TELA | B45: 53357 | C45: 1RU51 | D45: BANCO SANTANDER BRASIL SA | E45: 764153846 | F45: 1RU51000760005 | G45: 800 | H45: 192.85 | I45: CONTRATUAL | J45: 96248351872 | K45: MARCELO RUI OLIVEIRA GONZAGA | L45: SÃO PAULO | M45: SP | N45: SERGIANA | O45: JA POSSUI | R45: AUTORIZADO PAGAMENTO | S45: 8202618176 | T45: 5 DIAS ÚTEIS | U45: 46059 | V45: 46062 | W45: 46069 | X45: 46071 | Y45: NÃO | AC45: =IF($C45="","",IF(COUNTIF('Códigos Santander (ref)'!$A$2:$A$79,$C45)>0,"SANTANDER",IF(COUNTIF('Códigos Itaú (ref)'!$A$2:$A$44,$C45)>0,"ITAU",IF(AND(TRIM(UPPER($I45))="CONTRATUAL",ISNUMBER(SEARCH("INDIVIDUAL",SUBSTITUTE(UPPER($D45)," ","")))),"PREMIUM FREE",""))))
A46: TELA | B46: 53409 | C46: 1RU51 | D46: BANCO SANTANDER BRASIL SA | E46: 764153846 | F46: 1RU51000760013 | G46: 800 | H46: 192.85 | I46: CONTRATUAL | J46: 96248351872 | K46: MARCELO RUI OLIVEIRA GONZAGA | L46: SÃO PAULO | M46: SP | N46: SERGIANA | O46: JA POSSUI | R46: AUTORIZADO PAGAMENTO | S46: 8202618177 | T46: 5 DIAS ÚTEIS | U46: 46059 | V46: 46062 | W46: 46069 | X46: 46071 | Y46: NÃO | AC46: =IF($C46="","",IF(COUNTIF('Códigos Santander (ref)'!$A$2:$A$79,$C46)>0,"SANTANDER",IF(COUNTIF('Códigos Itaú (ref)'!$A$2:$A$44,$C46)>0,"ITAU",IF(AND(TRIM(UPPER($I46))="CONTRATUAL",ISNUMBER(SEARCH("INDIVIDUAL",SUBSTITUTE(UPPER($D46)," ","")))),"PREMIUM FREE",""))))
A47: TELA | B47: 53432 | C47: 1RUH3 | D47: BANCO SANTANDER BRASIL SA | E47: 28436101847 | F47: 1RUH3030807018 | G47: 370 | H47: 173.51 | I47: CONTRATUAL | J47: 24870458000160 | K47: EDWAL LOBOSCHI | L47: SÃO PAULO | M47: SP | N47: SERGIANA | O47: JA POSSUI | R47: AUTORIZADO PAGAMENTO | S47: 8202618178 | T47: 5 DIAS ÚTEIS | U47: 46062 | V47: 46062 | W47: 46069 | X47: 46071 | Y47: NÃO | AC47: =IF($C47="","",IF(COUNTIF('Códigos Santander (ref)'!$A$2:$A$79,$C47)>0,"SANTANDER",IF(COUNTIF('Códigos Itaú (ref)'!$A$2:$A$44,$C47)>0,"ITAU",IF(AND(TRIM(UPPER($I47))="CONTRATUAL",ISNUMBER(SEARCH("INDIVIDUAL",SUBSTITUTE(UPPER($D47)," ","")))),"PREMIUM FREE",""))))
A48: TELA | B48: 53489 | C48: 1RUGZ | D48: SX TOOLS SOLUC SERV COMPARTILHADOS LTDA | E48: 32684403805 | F48: 1RUGZ000755010 | G48: 139.9 | H48: 90.94 | I48: CONTRATUAL | J48: 22339086000114 | K48: CEORT CLINICA ODONTOLOGICA LTDA | L48: SÃO BERNARDO DO CAMPO | M48: SP | N48: SERGIANA | O48: JA POSSUI | R48: AUTORIZADO PAGAMENTO | S48: 8202618179 | T48: 5 DIAS ÚTEIS | U48: 46062 | V48: 46062 | W48: 46069 | X48: 46071 | Y48: NÃO | AC48: =IF($C48="","",IF(COUNTIF('Códigos Santander (ref)'!$A$2:$A$79,$C48)>0,"SANTANDER",IF(COUNTIF('Códigos Itaú (ref)'!$A$2:$A$44,$C48)>0,"ITAU",IF(AND(TRIM(UPPER($I48))="CONTRATUAL",ISNUMBER(SEARCH("INDIVIDUAL",SUBSTITUTE(UPPER($D48)," ","")))),"PREMIUM FREE",""))))
A49: TELA | B49: 53328 | C49: 1RBFP | D49: EM DIA SERVICOS ESPECIALIZADOS EM COBRANCAS L | E49: 22145988807 | F49: 1RBFP000169021 | G49: 100 | H49: 100 | I49: CONTRATUAL | J49: 37541578000165 | K49: AKABANE ODONTOLOGIA LTDA | L49: SÃO PAULO | M49: SP | N49: SERGIANA | O49: JA POSSUI | R49: AUTORIZADO PAGAMENTO | S49: 8202618180 | T49: 5 DIAS ÚTEIS | U49: 46062 | V49: 46062 | W49: 46069 | X49: 46071 | Y49: NÃO | AC49: =IF($C49="","",IF(COUNTIF('Códigos Santander (ref)'!$A$2:$A$79,$C49)>0,"SANTANDER",IF(COUNTIF('Códigos Itaú (ref)'!$A$2:$A$44,$C49)>0,"ITAU",IF(AND(TRIM(UPPER($I49))="CONTRATUAL",ISNUMBER(SEARCH("INDIVIDUAL",SUBSTITUTE(UPPER($D49)," ","")))),"PREMIUM FREE",""))))
A50: TELA | B50: 51467 | C50: 1RUH3 | D50: BANCO SANTANDER BRASIL SA | E50: 33183282860 | F50: 1RUH3033827010 | G50: 160 | H50: 90.94 | I50: CONTRATUAL | J50: 35045007866 | K50: PRISCILA GOMES DA SILVA | L50: MARIPORÃ | M50: SP | N50: SERGIANA | O50: 528766 | P50: 46062 | Q50: 46063 | R50: AUTORIZADO PAGAMENTO | S50: 8202618231 | T50: 5 DIAS ÚTEIS | U50: 46062 | V50: 46063 | W50: 46070 | X50: 46071 | Y50: NÃO | AC50: =IF($C50="","",IF(COUNTIF('Códigos Santander (ref)'!$A$2:$A$79,$C50)>0,"SANTANDER",IF(COUNTIF('Códigos Itaú (ref)'!$A$2:$A$44,$C50)>0,"ITAU",IF(AND(TRIM(UPPER($I50))="CONTRATUAL",ISNUMBER(SEARCH("INDIVIDUAL",SUBSTITUTE(UPPER($D50)," ","")))),"PREMIUM FREE",""))))
A51: TELA | B51: 52175 | C51: 1RUH3 | D51: BANCO SANTANDER BRASIL SA | E51: 33183282860 | F51: 1RUH3033827010 | G51: 160 | H51: 90.94 | I51: CONTRATUAL | J51: 35045007866 | K51: PRISCILA GOMES DA SILVA | L51: MARIPORÃ | M51: SP | N51: SERGIANA | O51: 528766 | P51: 46062 | Q51: 46063 | R51: AUTORIZADO PAGAMENTO | S51: 8202618232 | T51: 5 DIAS ÚTEIS | U51: 46062 | V51: 46063 | W51: 46070 | X51: 46071 | Y51: NÃO | AC51: =IF($C51="","",IF(COUNTIF('Códigos Santander (ref)'!$A$2:$A$79,$C51)>0,"SANTANDER",IF(COUNTIF('Códigos Itaú (ref)'!$A$2:$A$44,$C51)>0,"ITAU",IF(AND(TRIM(UPPER($I51))="CONTRATUAL",ISNUMBER(SEARCH("INDIVIDUAL",SUBSTITUTE(UPPER($D51)," ","")))),"PREMIUM FREE",""))))
A52: TELA | B52: 53360 | C52: 1RUH3 | D52: BANCO SANTANDER BRASIL SA | E52: 34153168823 | F52: 1RUH3029503000 | G52: 350 | H52: 243.88 | I52: CONTRATUAL | J52: 24870458000160 | K52: EDWAL LOBOSCHI | L52: SÃO PAULO | M52: SP | N52: SERGIANA | O52: JA POSSUI | R52: AUTORIZADO PAGAMENTO | S52: 8202618181 | T52: 5 DIAS ÚTEIS | U52: 46062 | V52: 46062 | W52: 46069 | X52: 46071 | Y52: NÃO | AC52: =IF($C52="","",IF(COUNTIF('Códigos Santander (ref)'!$A$2:$A$79,$C52)>0,"SANTANDER",IF(COUNTIF('Códigos Itaú (ref)'!$A$2:$A$44,$C52)>0,"ITAU",IF(AND(TRIM(UPPER($I52))="CONTRATUAL",ISNUMBER(SEARCH("INDIVIDUAL",SUBSTITUTE(UPPER($D52)," ","")))),"PREMIUM FREE",""))))
A53: TELA | B53: 53104 | C53: 1RUH3 | D53: BANCO SANTANDER BRASIL SA | E53: 30895640848 | F53: 1RUH3035661020 | G53: 800 | H53: 800 | I53: CONTRATUAL | J53: 26020466809 | K53: JULIANA GUZZON BOSCHINI | L53: SÃO ROQUE | M53: SP | N53: SERGIANA | O53: JA POSSUI | R53: AUTORIZADO PAGAMENTO | S53: 8202618186 | T53: 5 DIAS ÚTEIS | U53: 46062 | V53: 46062 | W53: 46069 | X53: 46071 | Y53: NÃO | AC53: =IF($C53="","",IF(COUNTIF('Códigos Santander (ref)'!$A$2:$A$79,$C53)>0,"SANTANDER",IF(COUNTIF('Códigos Itaú (ref)'!$A$2:$A$44,$C53)>0,"ITAU",IF(AND(TRIM(UPPER($I53))="CONTRATUAL",ISNUMBER(SEARCH("INDIVIDUAL",SUBSTITUTE(UPPER($D53)," ","")))),"PREMIUM FREE",""))))
A54: TELA | B54: 53467 | C54: 1RUH3 | D54: BANCO SANTANDER BRASIL SA | E54: 10415944961 | F54: 1RUH3008165009 | G54: 324 | H54: 113.4 | I54: CONTRATUAL | J54: 7738896000150 | K54: CLINICA ODONTOLOGICA SCHERER LTDA | L54: FOZ DO IGUAÇU | M54: PR | N54: SERGIANA | O54: JA POSSUI | R54: AUTORIZADO PAGAMENTO | S54: 8202618187 | T54: 5 DIAS ÚTEIS | U54: 46062 | V54: 46062 | W54: 46069 | X54: 46071 | Y54: NÃO | AC54: =IF($C54="","",IF(COUNTIF('Códigos Santander (ref)'!$A$2:$A$79,$C54)>0,"SANTANDER",IF(COUNTIF('Códigos Itaú (ref)'!$A$2:$A$44,$C54)>0,"ITAU",IF(AND(TRIM(UPPER($I54))="CONTRATUAL",ISNUMBER(SEARCH("INDIVIDUAL",SUBSTITUTE(UPPER($D54)," ","")))),"PREMIUM FREE",""))))
A55: TELA | B55: 53527 | C55: 1RU54 | D55: BANCO SANTANDER BRASIL SA | E55: 64911500972 | F55: 1RU54000212016 | G55: 300 | H55: 212.19 | I55: CONTRATUAL | J55: 6918595822 | K55: SANDRA TERRA GARBELLOTO | L55: SÃO PAULO | M55: SP | N55: SERGIANA | O55: JA POSSUI | R55: AUTORIZADO PAGAMENTO | S55: 8202618188 | T55: 5 DIAS ÚTEIS | U55: 46062 | V55: 46062 | W55: 46069 | X55: 46071 | Y55: NÃO | AC55: =IF($C55="","",IF(COUNTIF('Códigos Santander (ref)'!$A$2:$A$79,$C55)>0,"SANTANDER",IF(COUNTIF('Códigos Itaú (ref)'!$A$2:$A$44,$C55)>0,"ITAU",IF(AND(TRIM(UPPER($I55))="CONTRATUAL",ISNUMBER(SEARCH("INDIVIDUAL",SUBSTITUTE(UPPER($D55)," ","")))),"PREMIUM FREE",""))))
A56: NIP | B56: 53355 | C56: 0B0N8 | D56: CENTRO CLINICO GAUCHO LTDA | E56: 1143074076 | F56: 0B0N8105503009 | G56: 880 | H56: 880 | I56: INSUFICIÊNCIA DE REDE | J56: 48043757000199 | K56: DENTAL MEDICA ODONTOLOGIA INTEGRADA LTDA | L56: ESTANCIA VELHA | M56: RS | N56: CIBELY | O56: 528879 | P56: 46062 | Q56: 46063 | R56: AUTORIZADO PAGAMENTO | S56: 8202618238 | T56: 30 DIAS CORRIDOS | U56: 46062 | V56: 46063 | W56: 46091 | X56: 46071 | Y56: SIM | AC56: =IF($C56="","",IF(COUNTIF('Códigos Santander (ref)'!$A$2:$A$79,$C56)>0,"SANTANDER",IF(COUNTIF('Códigos Itaú (ref)'!$A$2:$A$44,$C56)>0,"ITAU",IF(AND(TRIM(UPPER($I56))="CONTRATUAL",ISNUMBER(SEARCH("INDIVIDUAL",SUBSTITUTE(UPPER($D56)," ","")))),"PREMIUM FREE",""))))
A57: TELA | B57: 53392 | C57: 1RSX8 | D57: ITAU UNIBANCO SA | E57: 73126810772 | F57: 1RSX8000317004 | G57: 1250 | H57: 691.99 | I57: CONTRATUAL | J57: 7959716722 | K57: JULIANA VIEGAS SONEGHETI | L57: NITERÓI | M57: RJ | N57: SERGIANA | O57: JA POSSUI | R57: AUTORIZADO PAGAMENTO | S57: 8202618190 | T57: 5 DIAS ÚTEIS | U57: 46062 | V57: 46062 | W57: 46069 | X57: 46071 | Y57: NÃO | AC57: =IF($C57="","",IF(COUNTIF('Códigos Santander (ref)'!$A$2:$A$79,$C57)>0,"SANTANDER",IF(COUNTIF('Códigos Itaú (ref)'!$A$2:$A$44,$C57)>0,"ITAU",IF(AND(TRIM(UPPER($I57))="CONTRATUAL",ISNUMBER(SEARCH("INDIVIDUAL",SUBSTITUTE(UPPER($D57)," ","")))),"PREMIUM FREE",""))))
A58: TELA | B58: 53246 | C58: 1RSX8 | D58: ITAU UNIBANCO SA | E58: 73126810772 | F58: 1RSX8000317012 | G58: 1250 | H58: 691.99 | I58: CONTRATUAL | J58: 7959716722 | K58: JULIANA VIEGAS SONEGHETI | L58: NITERÓI | M58: RJ | N58: SERGIANA | O58: JA POSSUI | R58: AUTORIZADO PAGAMENTO | S58: 8202618191 | T58: 5 DIAS ÚTEIS | U58: 46062 | V58: 46062 | W58: 46069 | X58: 46071 | Y58: NÃO | AC58: =IF($C58="","",IF(COUNTIF('Códigos Santander (ref)'!$A$2:$A$79,$C58)>0,"SANTANDER",IF(COUNTIF('Códigos Itaú (ref)'!$A$2:$A$44,$C58)>0,"ITAU",IF(AND(TRIM(UPPER($I58))="CONTRATUAL",ISNUMBER(SEARCH("INDIVIDUAL",SUBSTITUTE(UPPER($D58)," ","")))),"PREMIUM FREE",""))))
A59: TELA | B59: 53351 | C59: 1RUH3 | D59: BANCO SANTANDER BRASIL SA | E59: 5523673706 | F59: 1RUH3036587010 | G59: 810 | H59: 83.8 | I59: CONTRATUAL | J59: 5899138750 | K59: ELLEN LACERDA DE FREITAS MENDES DA SILVA | L59: RIO DE JANEIRO | M59: RJ | N59: SERGIANA | O59: 528885 | P59: 46062 | Q59: 46063 | R59: AUTORIZADO PAGAMENTO | S59: 8202618252 | T59: 5 DIAS ÚTEIS | U59: 46062 | V59: 46063 | W59: 46070 | X59: 46071 | Y59: NÃO | AC59: =IF($C59="","",IF(COUNTIF('Códigos Santander (ref)'!$A$2:$A$79,$C59)>0,"SANTANDER",IF(COUNTIF('Códigos Itaú (ref)'!$A$2:$A$44,$C59)>0,"ITAU",IF(AND(TRIM(UPPER($I59))="CONTRATUAL",ISNUMBER(SEARCH("INDIVIDUAL",SUBSTITUTE(UPPER($D59)," ","")))),"PREMIUM FREE",""))))
A60: TELA | B60: 53388 | C60: S21FQ | D60: SANTANDER SERVICOS DIGITAIS BRASIL LTDA | E60: 15597936867 | F60: S21FQ000046027 | G60: 160 | H60: 160 | I60: CONTRATUAL | J60: 8040735890 | K60: AMAURI CARVALHO DE MORAIS | L60: SÃO PAULO | M60: SP | N60: SERGIANA | O60: JA POSSUI | R60: AUTORIZADO PAGAMENTO | S60: 8202618194 | T60: 5 DIAS ÚTEIS | U60: 46062 | V60: 46062 | W60: 46069 | X60: 46071 | Y60: NÃO | AC60: =IF($C60="","",IF(COUNTIF('Códigos Santander (ref)'!$A$2:$A$79,$C60)>0,"SANTANDER",IF(COUNTIF('Códigos Itaú (ref)'!$A$2:$A$44,$C60)>0,"ITAU",IF(AND(TRIM(UPPER($I60))="CONTRATUAL",ISNUMBER(SEARCH("INDIVIDUAL",SUBSTITUTE(UPPER($D60)," ","")))),"PREMIUM FREE",""))))
A61: TELA | B61: 53172 | C61: 4010X | D61: INDIVIDUAL | E61: 4072050393 | F61: 4010X070575002 | G61: 200 | H61: 200 | I61: COBRANÇA INDEVIDA | J61: 52558224000117 | K61: DNA ODONTOLOGIA KENNEDY LTDA | L61: FORTALEZA | M61: CE | N61: SERGIANA | O61: 529005 | P61: 46062 | Q61: 46063 | R61: AUTORIZADO PAGAMENTO | S61: 8202618290 | T61: 30 DIAS CORRIDOS | U61: 46062 | V61: 46064 | W61: 46092 | X61: 46071 | Y61: SIM | AC61: =IF($C61="","",IF(COUNTIF('Códigos Santander (ref)'!$A$2:$A$79,$C61)>0,"SANTANDER",IF(COUNTIF('Códigos Itaú (ref)'!$A$2:$A$44,$C61)>0,"ITAU",IF(AND(TRIM(UPPER($I61))="CONTRATUAL",ISNUMBER(SEARCH("INDIVIDUAL",SUBSTITUTE(UPPER($D61)," ","")))),"PREMIUM FREE",""))))
A62: LECOM | B62: 53361 | C62: 0ATGF | D62: ANDRESSA CRISTIANE BOHM ABRAHAO | E62: 68452357087 | F62: 0ATGF000007005 | G62: 70 | H62: 70 | I62: INSUFICIÊNCIA DE REDE | J62: 31674201000106 | K62: LUIZ OTAVIO RAPOSO | L62: LAGUNA CARAPA | M62: MS | N62: VITORIA | O62: 529037 | P62: 46062 | Q62: 46063 | R62: AUTORIZADO PAGAMENTO | S62: 8202618291 | T62: 30 DIAS CORRIDOS | U62: 46062 | V62: 46064 | W62: 46092 | X62: 46071 | Y62: SIM | AC62: =IF($C62="","",IF(COUNTIF('Códigos Santander (ref)'!$A$2:$A$79,$C62)>0,"SANTANDER",IF(COUNTIF('Códigos Itaú (ref)'!$A$2:$A$44,$C62)>0,"ITAU",IF(AND(TRIM(UPPER($I62))="CONTRATUAL",ISNUMBER(SEARCH("INDIVIDUAL",SUBSTITUTE(UPPER($D62)," ","")))),"PREMIUM FREE",""))))
A63: TELA | B63: 53434 | C63: 1RUD3 | D63: SANTANDER BRASIL GESTAO DE RECURSOS HUMANOS L | E63: 32429351870 | F63: 1RUD3000140007 | G63: 100 | H63: 90.94 | I63: CONTRATUAL | J63: 22789361000100 | K63: CRISTIANE MOREIRA DE OLIVEIRA CLINICA ODONTOLOGICA - EPP | L63: OSASCO | M63: SP | N63: SERGIANA | O63: JA POSSUI | R63: AUTORIZADO PAGAMENTO | S63: 8202618195 | T63: 5 DIAS ÚTEIS | U63: 46062 | V63: 46062 | W63: 46069 | X63: 46071 | Y63: NÃO | AC63: =IF($C63="","",IF(COUNTIF('Códigos Santander (ref)'!$A$2:$A$79,$C63)>0,"SANTANDER",IF(COUNTIF('Códigos Itaú (ref)'!$A$2:$A$44,$C63)>0,"ITAU",IF(AND(TRIM(UPPER($I63))="CONTRATUAL",ISNUMBER(SEARCH("INDIVIDUAL",SUBSTITUTE(UPPER($D63)," ","")))),"PREMIUM FREE",""))))
A64: TELA | B64: 52938 | C64: 1RU54 | D64: BANCO SANTANDER BRASIL SA | E64: 4109485860 | F64: 1RU54000019011 | G64: 636 | H64: 636 | I64: CONTRATUAL | J64: 5573342000114 | K64: VICENTE ESPERIDIAO ODONTOLOGIA AVANCADA LTDA | L64: SÃO PAULO | M64: SP | N64: SERGIANA | O64: JA POSSUI | R64: AUTORIZADO PAGAMENTO | S64: 8202618196 | T64: 5 DIAS ÚTEIS | U64: 46062 | V64: 46062 | W64: 46069 | X64: 46071 | Y64: NÃO | AC64: =IF($C64="","",IF(COUNTIF('Códigos Santander (ref)'!$A$2:$A$79,$C64)>0,"SANTANDER",IF(COUNTIF('Códigos Itaú (ref)'!$A$2:$A$44,$C64)>0,"ITAU",IF(AND(TRIM(UPPER($I64))="CONTRATUAL",ISNUMBER(SEARCH("INDIVIDUAL",SUBSTITUTE(UPPER($D64)," ","")))),"PREMIUM FREE",""))))
A65: TELA | B65: 52974 | C65: 1RUH3 | D65: BANCO SANTANDER BRASIL SA | E65: 12884513850 | F65: 1RUH3027479005 | G65: 636 | H65: 636 | I65: CONTRATUAL | J65: 5573342000114 | K65: VICENTE ESPERIDIAO ODONTOLOGIA AVANCADA LTDA | L65: SÃO PAULO | M65: SP | N65: SERGIANA | O65: JA POSSUI | R65: AUTORIZADO PAGAMENTO | S65: 8202618213 | T65: 5 DIAS ÚTEIS | U65: 46062 | V65: 46063 | W65: 46070 | X65: 46071 | Y65: NÃO | AC65: =IF($C65="","",IF(COUNTIF('Códigos Santander (ref)'!$A$2:$A$79,$C65)>0,"SANTANDER",IF(COUNTIF('Códigos Itaú (ref)'!$A$2:$A$44,$C65)>0,"ITAU",IF(AND(TRIM(UPPER($I65))="CONTRATUAL",ISNUMBER(SEARCH("INDIVIDUAL",SUBSTITUTE(UPPER($D65)," ","")))),"PREMIUM FREE",""))))
A66: TELA | B66: 52975 | C66: 1RUH3 | D66: BANCO SANTANDER BRASIL SA | E66: 17588453842 | F66: 1RUH3039328031 | G66: 636 | H66: 636 | I66: CONTRATUAL | J66: 5573342000114 | K66: VICENTE ESPERIDIAO ODONTOLOGIA AVANCADA LTDA | L66: SÃO PAULO | M66: SP | N66: SERGIANA | O66: JA POSSUI | R66: AUTORIZADO PAGAMENTO | S66: 8202618212 | T66: 5 DIAS ÚTEIS | U66: 46062 | V66: 46063 | W66: 46070 | X66: 46071 | Y66: NÃO | AC66: =IF($C66="","",IF(COUNTIF('Códigos Santander (ref)'!$A$2:$A$79,$C66)>0,"SANTANDER",IF(COUNTIF('Códigos Itaú (ref)'!$A$2:$A$44,$C66)>0,"ITAU",IF(AND(TRIM(UPPER($I66))="CONTRATUAL",ISNUMBER(SEARCH("INDIVIDUAL",SUBSTITUTE(UPPER($D66)," ","")))),"PREMIUM FREE",""))))
A67: TELA | B67: 52979 | C67: 1RSX8 | D67: ITAU UNIBANCO SA | E67: 50361414749 | F67: 1RSX8000316008 | G67: 7500 | H67: 2278.8 | I67: CONTRATUAL | J67: 7959716722 | K67: JULIANA VIEGAS SONEGHETI | L67: NITERÓI | M67: RJ | N67: SERGIANA | O67: JA POSSUI | R67: AUTORIZADO PAGAMENTO | S67: 8202618211 | T67: 5 DIAS ÚTEIS | U67: 46062 | V67: 46063 | W67: 46070 | X67: 46071 | Y67: NÃO | AC67: =IF($C67="","",IF(COUNTIF('Códigos Santander (ref)'!$A$2:$A$79,$C67)>0,"SANTANDER",IF(COUNTIF('Códigos Itaú (ref)'!$A$2:$A$44,$C67)>0,"ITAU",IF(AND(TRIM(UPPER($I67))="CONTRATUAL",ISNUMBER(SEARCH("INDIVIDUAL",SUBSTITUTE(UPPER($D67)," ","")))),"PREMIUM FREE",""))))
A68: TELA | B68: 52237 | C68: 3010E | D68: INDIVIDUAL | E68: 37254919843 | F68: 3010E039025012 | G68: 184.4 | H68: 184.4 | I68: DESLOCAMENTO | J68: 11647966000131 | K68: POSTO DE SERVICOS BETEL LTDA | L68: PIRASSUNUNGA | M68: SP | N68: SERGIANA | O68: JA POSSUI | R68: AUTORIZADO PAGAMENTO | S68: 8202618210 | T68: 30 DIAS CORRIDOS | U68: 46062 | V68: 46063 | W68: 46091 | X68: 46071 | Y68: SIM | AC68: =IF($C68="","",IF(COUNTIF('Códigos Santander (ref)'!$A$2:$A$79,$C68)>0,"SANTANDER",IF(COUNTIF('Códigos Itaú (ref)'!$A$2:$A$44,$C68)>0,"ITAU",IF(AND(TRIM(UPPER($I68))="CONTRATUAL",ISNUMBER(SEARCH("INDIVIDUAL",SUBSTITUTE(UPPER($D68)," ","")))),"PREMIUM FREE",""))))
A69: TELA | B69: 53054 | C69: 1RUGZ | D69: SX TOOLS SOLUC SERV COMPARTILHADOS LTDA | E69: 40533585821 | F69: 1RUGZ001300008 | G69: 170 | H69: 170 | I69: CONTRATUAL | J69: 43074054000104 | K69: CLINICA MAESTA ODONTOLOGIA ESPECIALIZADA LTDA | L69: PIRACICABA | M69: SP | N69: CIBELY | O69: JA POSSUI | R69: AUTORIZADO PAGAMENTO | S69: 8202618209 | T69: 5 DIAS ÚTEIS | U69: 46062 | V69: 46063 | W69: 46070 | X69: 46071 | Y69: NÃO | AC69: =IF($C69="","",IF(COUNTIF('Códigos Santander (ref)'!$A$2:$A$79,$C69)>0,"SANTANDER",IF(COUNTIF('Códigos Itaú (ref)'!$A$2:$A$44,$C69)>0,"ITAU",IF(AND(TRIM(UPPER($I69))="CONTRATUAL",ISNUMBER(SEARCH("INDIVIDUAL",SUBSTITUTE(UPPER($D69)," ","")))),"PREMIUM FREE",""))))
A70: SAC | B70: 51765 | C70: 0819Z | D70: ALLCARE ADMINISTRADORA DE BENEFICIOS SAO PAUL | E70: 2233040180 | F70: 0819Z000100005 | G70: 80 | H70: 80 | I70: COBRANÇA INDEVIDA | J70: 49936544000159 | K70: IPO - PREMIUM ODONTOLOGIA LTDA | L70: GOIANIA | M70: GO | N70: CIBELY | O70: 529202 | P70: 46063 | Q70: 46065 | R70: AUTORIZADO PAGAMENTO | S70: 8202618381 | T70: 30 DIAS CORRIDOS | U70: 46063 | V70: 46065 | W70: 46072 | X70: 46073 | Y70: SIM | AC70: =IF($C70="","",IF(COUNTIF('Códigos Santander (ref)'!$A$2:$A$79,$C70)>0,"SANTANDER",IF(COUNTIF('Códigos Itaú (ref)'!$A$2:$A$44,$C70)>0,"ITAU",IF(AND(TRIM(UPPER($I70))="CONTRATUAL",ISNUMBER(SEARCH("INDIVIDUAL",SUBSTITUTE(UPPER($D70)," ","")))),"PREMIUM FREE",""))))
A71: TELA | B71: 53358 | C71: 1RU51 | D71: BANCO SANTANDER BRASIL SA | E71: 53245881720 | F71: 1RU51000497029 | G71: 500 | H71: 267.65 | I71: CONTRATUAL | J71: 72216484768 | K71: RUBEM RIBEIRO MAURELL | L71: RIO DE JANEIRO | M71: RJ | N71: MARINA | O71: 529192 | P71: 46063 | Q71: 46065 | R71: AUTORIZADO PAGAMENTO | S71: 8202618383 | T71: 5 DIAS ÚTEIS | U71: 46063 | V71: 46065 | W71: 46072 | X71: 46073 | Y71: NÃO | AC71: =IF($C71="","",IF(COUNTIF('Códigos Santander (ref)'!$A$2:$A$79,$C71)>0,"SANTANDER",IF(COUNTIF('Códigos Itaú (ref)'!$A$2:$A$44,$C71)>0,"ITAU",IF(AND(TRIM(UPPER($I71))="CONTRATUAL",ISNUMBER(SEARCH("INDIVIDUAL",SUBSTITUTE(UPPER($D71)," ","")))),"PREMIUM FREE",""))))
A72: SAC | B72: 51972 | C72: 0700D | D72: I N D I V I D U A L | E72: 6223579489 | F72: 0700D925703017 | G72: 360 | H72: 360 | I72: COBRANÇA INDEVIDA | J72: 22575399000171 | K72: KAROLAINE FERREIRA FERNANDES | L72: MOSSORÓ | M72: RN | N72: CIBELY | O72: JA POSSUI | R72: AUTORIZADO PAGAMENTO | S72: 8202618255 | T72: 30 DIAS CORRIDOS | U72: 46063 | V72: 46063 | W72: 46091 | X72: 46071 | Y72: SIM | AC72: =IF($C72="","",IF(COUNTIF('Códigos Santander (ref)'!$A$2:$A$79,$C72)>0,"SANTANDER",IF(COUNTIF('Códigos Itaú (ref)'!$A$2:$A$44,$C72)>0,"ITAU",IF(AND(TRIM(UPPER($I72))="CONTRATUAL",ISNUMBER(SEARCH("INDIVIDUAL",SUBSTITUTE(UPPER($D72)," ","")))),"PREMIUM FREE",""))))
A73: TELA | B73: 53490 | C73: 1RU54 | D73: BANCO SANTANDER BRASIL SA | E73: 3315462801 | F73: 1RU54000230014 | G73: 145 | H73: 145 | I73: CONTRATUAL | J73: 55753335000172 | K73: CLINICA ODONTOLOGICA ODONTO BELLE LTDA | L73: SÃO PAULO | M73: SP | N73: MARINA | O73: JA POSSUI | R73: AUTORIZADO PAGAMENTO | S73: 8202618254 | T73: 5 DIAS ÚTEIS | U73: 46063 | V73: 46063 | W73: 46070 | X73: 46071 | Y73: NÃO | AC73: =IF($C73="","",IF(COUNTIF('Códigos Santander (ref)'!$A$2:$A$79,$C73)>0,"SANTANDER",IF(COUNTIF('Códigos Itaú (ref)'!$A$2:$A$44,$C73)>0,"ITAU",IF(AND(TRIM(UPPER($I73))="CONTRATUAL",ISNUMBER(SEARCH("INDIVIDUAL",SUBSTITUTE(UPPER($D73)," ","")))),"PREMIUM FREE",""))))
A74: SAC | B74: 53435 | C74: 92709 | D74: QUALICORP CLUBE DE SAUDE ADM DE BENEF LTDA | E74: 7674539300 | F74: 92709003336013 | G74: 120 | H74: 120 | I74: COBRANÇA INDEVIDA | J74: 40590996000157 | K74: ORTHOCLINIC CLINICA ODONTOLOGICA LTDA | L74: FORTALEZA | M74: CE | N74: CIBELY | O74: 529440 | P74: 46064 | Q74: 46065 | R74: AUTORIZADO PAGAMENTO | S74: 8202618384 | T74: 30 DIAS CORRIDOS | U74: 46063 | V74: 46065 | W74: 46072 | X74: 46073 | Y74: SIM | AC74: =IF($C74="","",IF(COUNTIF('Códigos Santander (ref)'!$A$2:$A$79,$C74)>0,"SANTANDER",IF(COUNTIF('Códigos Itaú (ref)'!$A$2:$A$44,$C74)>0,"ITAU",IF(AND(TRIM(UPPER($I74))="CONTRATUAL",ISNUMBER(SEARCH("INDIVIDUAL",SUBSTITUTE(UPPER($D74)," ","")))),"PREMIUM FREE",""))))
A75: TELA | B75: 52408 | C75: 1RSLN | D75: ITAU UNIBANCO SA | E75: 1010151789 | F75: 1RSLN019627009 | G75: 15210 | H75: 6570.76 | I75: CONTRATUAL | J75: 7319488744 | K75: SILVIO LAMBLET SCHUENCK RAMOS | L75: NITEROI | M75: RJ | N75: CIBELY | O75: JA POSSUI | R75: AUTORIZADO PAGAMENTO | S75: 8202618351 | T75: 5 DIAS ÚTEIS | U75: 46064 | V75: 46064 | W75: 46071 | X75: 46071 | Y75: SIM | AC75: =IF($C75="","",IF(COUNTIF('Códigos Santander (ref)'!$A$2:$A$79,$C75)>0,"SANTANDER",IF(COUNTIF('Códigos Itaú (ref)'!$A$2:$A$44,$C75)>0,"ITAU",IF(AND(TRIM(UPPER($I75))="CONTRATUAL",ISNUMBER(SEARCH("INDIVIDUAL",SUBSTITUTE(UPPER($D75)," ","")))),"PREMIUM FREE",""))))
A76: TELA | B76: 53509 | C76: 1RU54 | D76: BANCO SANTANDER BRASIL SA | E76: 2296983871 | F76: 1RU54000014010 | G76: 318.67 | H76: 318.67 | I76: CONTRATUAL | J76: 38260191000101 | K76: FREDERICO VICENTE CLINICA ODONTOLOGICA UNIPESSOAL LTDA | L76: SÃO PAULO | M76: SP | N76: MARINA | O76: JA POSSUI | R76: AUTORIZADO PAGAMENTO | S76: 8202618350 | T76: 5 DIAS ÚTEIS | U76: 46064 | V76: 46064 | W76: 46071 | X76: 46071 | Y76: SIM | AC76: =IF($C76="","",IF(COUNTIF('Códigos Santander (ref)'!$A$2:$A$79,$C76)>0,"SANTANDER",IF(COUNTIF('Códigos Itaú (ref)'!$A$2:$A$44,$C76)>0,"ITAU",IF(AND(TRIM(UPPER($I76))="CONTRATUAL",ISNUMBER(SEARCH("INDIVIDUAL",SUBSTITUTE(UPPER($D76)," ","")))),"PREMIUM FREE",""))))
A77: TELA | B77: 53528 | C77: 1RUH3 | D77: BANCO SANTANDER BRASIL SA | E77: 26501291828 | F77: 1RUH3030923026 | G77: 360 | H77: 173.51 | I77: CONTRATUAL | J77: 15739539897 | K77: MARCIA REGINA DE OLIVEIRA FARINA | L77: SÃO PAULO | M77: SP | N77: MARINA | O77: JA POSSUI | R77: AUTORIZADO PAGAMENTO | S77: 8202618349 | T77: 5 DIAS ÚTEIS | U77: 46064 | V77: 46064 | W77: 46071 | X77: 46071 | Y77: SIM | AC77: =IF($C77="","",IF(COUNTIF('Códigos Santander (ref)'!$A$2:$A$79,$C77)>0,"SANTANDER",IF(COUNTIF('Códigos Itaú (ref)'!$A$2:$A$44,$C77)>0,"ITAU",IF(AND(TRIM(UPPER($I77))="CONTRATUAL",ISNUMBER(SEARCH("INDIVIDUAL",SUBSTITUTE(UPPER($D77)," ","")))),"PREMIUM FREE",""))))
A78: SAC | B78: 53828 | C78: 0JMJQ | D78: ITAU UNIBANCO SA | E78: 70151296049 | F78: 0JMJQ014641020 | G78: 2100 | H78: 2100 | I78: COBRANÇA INDEVIDA | J78: 66726352034 | K78: YURI RAVANELLO | L78: LAJEADO | M78: RS | N78: CIBELY | O78: 531291 | P78: 46076 | Q78: 46077 | R78: AUTORIZADO PAGAMENTO | S78: 8202618751 | T78: 30 DIAS CORRIDOS | U78: 46064 | V78: 46078 | W78: 46106 | X78: 46085 | Y78: SIM | AC78: =IF($C78="","",IF(COUNTIF('Códigos Santander (ref)'!$A$2:$A$79,$C78)>0,"SANTANDER",IF(COUNTIF('Códigos Itaú (ref)'!$A$2:$A$44,$C78)>0,"ITAU",IF(AND(TRIM(UPPER($I78))="CONTRATUAL",ISNUMBER(SEARCH("INDIVIDUAL",SUBSTITUTE(UPPER($D78)," ","")))),"PREMIUM FREE",""))))
A79: SAC | B79: 53209 | C79: 1RCCA | D79: TEX COURIER LTDA | E79: 15459280702 | F79: 1RCCA013855026 | G79: 350 | H79: 350 | I79: COBRANÇA INDEVIDA | J79: 39936876000180 | K79: A2 FACILE CLINICAS ODONTOLOGICAS LTDA | L79: RIO DE JANEIRO | M79: RJ | N79: CIBELY | O79: 529905 | P79: 46065 | Q79: 46066 | R79: AUTORIZADO PAGAMENTO | S79: 8202618421 | T79: 30 DIAS CORRIDOS | U79: 46065 | V79: 46066 | W79: 46094 | X79: 46073 | Y79: SIM | AC79: =IF($C79="","",IF(COUNTIF('Códigos Santander (ref)'!$A$2:$A$79,$C79)>0,"SANTANDER",IF(COUNTIF('Códigos Itaú (ref)'!$A$2:$A$44,$C79)>0,"ITAU",IF(AND(TRIM(UPPER($I79))="CONTRATUAL",ISNUMBER(SEARCH("INDIVIDUAL",SUBSTITUTE(UPPER($D79)," ","")))),"PREMIUM FREE",""))))
A80: TELA | B80: 53300 | C80: 1RU54 | D80: BANCO SANTANDER BRASIL SA | E80: 24804827587 | F80: 1RU54000248002 | G80: 120 | H80: 67.43 | I80: CONTRATUAL | J80: 52270922000112 | K80: ODONTOLOGIA BARROS CARVALHO LTDA | L80: SALVADOR | M80: BA | N80: MARINA | O80: 529906 | P80: 46065 | Q80: 46066 | R80: AUTORIZADO PAGAMENTO | S80: 8202618422 | T80: 5 DIAS ÚTEIS | U80: 46065 | V80: 46066 | W80: 46073 | X80: 46073 | Y80: SIM | AC80: =IF($C80="","",IF(COUNTIF('Códigos Santander (ref)'!$A$2:$A$79,$C80)>0,"SANTANDER",IF(COUNTIF('Códigos Itaú (ref)'!$A$2:$A$44,$C80)>0,"ITAU",IF(AND(TRIM(UPPER($I80))="CONTRATUAL",ISNUMBER(SEARCH("INDIVIDUAL",SUBSTITUTE(UPPER($D80)," ","")))),"PREMIUM FREE",""))))
A81: TELA | B81: 53112 | C81: 1RSX8 | D81: ITAU UNIBANCO SA | E81: 50361414749 | F81: 1RSX8000316008 | G81: 1500 | H81: 723 | I81: CONTRATUAL | J81: 7959716722 | K81: JULIANA VIEGAS SONEGHETI | L81: NITEROI | M81: RJ | N81: CIBELY | O81: JAPOSSUI | R81: AUTORIZADO PAGAMENTO | S81: 8202618409 | T81: 5 DIAS ÚTEIS | U81: 46065 | V81: 46065 | W81: 46072 | X81: 46073 | Y81: NÃO | AC81: =IF($C81="","",IF(COUNTIF('Códigos Santander (ref)'!$A$2:$A$79,$C81)>0,"SANTANDER",IF(COUNTIF('Códigos Itaú (ref)'!$A$2:$A$44,$C81)>0,"ITAU",IF(AND(TRIM(UPPER($I81))="CONTRATUAL",ISNUMBER(SEARCH("INDIVIDUAL",SUBSTITUTE(UPPER($D81)," ","")))),"PREMIUM FREE",""))))
A82: TELA | B82: 53497 | C82: 1RUH3 | D82: BANCO SANTANDER BRASIL SA | E82: 29159893893 | F82: 1RUH3031163017 | G82: 500 | H82: 288.4 | I82: CONTRATUAL | J82: 24870458000160 | K82: EDWAL LOBOSCHI | L82: SÃO PAULO | M82: SP | N82: MARINA | O82: JA POSSUI | R82: AUTORIZADO PAGAMENTO | S82: 8202618408 | T82: 5 DIAS ÚTEIS | U82: 46065 | V82: 46065 | W82: 46072 | X82: 46073 | Y82: NÃO | AC82: =IF($C82="","",IF(COUNTIF('Códigos Santander (ref)'!$A$2:$A$79,$C82)>0,"SANTANDER",IF(COUNTIF('Códigos Itaú (ref)'!$A$2:$A$44,$C82)>0,"ITAU",IF(AND(TRIM(UPPER($I82))="CONTRATUAL",ISNUMBER(SEARCH("INDIVIDUAL",SUBSTITUTE(UPPER($D82)," ","")))),"PREMIUM FREE",""))))
A83: TELA | B83: 53140 | C83: 1RUH3 | D83: BANCO SANTANDER BRASIL SA | E83: 7043801613 | F83: 1RUH3001460005 | G83: 90 | H83: 71.81 | I83: CONTRATUAL | J83: 14244902000340 | K83: ODONTOLOGIA DE FRIBURGO LTDA | L83: NOVA FRIBURGO | M83: RJ | N83: CIBELY | O83: JA POSSUI | R83: AUTORIZADO PAGAMENTO | S83: 8202618407 | T83: 5 DIAS ÚTEIS | U83: 46065 | V83: 46065 | W83: 46072 | X83: 46073 | Y83: NÃO | AC83: =IF($C83="","",IF(COUNTIF('Códigos Santander (ref)'!$A$2:$A$79,$C83)>0,"SANTANDER",IF(COUNTIF('Códigos Itaú (ref)'!$A$2:$A$44,$C83)>0,"ITAU",IF(AND(TRIM(UPPER($I83))="CONTRATUAL",ISNUMBER(SEARCH("INDIVIDUAL",SUBSTITUTE(UPPER($D83)," ","")))),"PREMIUM FREE",""))))
A84: TELA | B84: 53568 | C84: 1RUH3 | D84: BANCO SANTANDER BRASIL SA | E84: 29159893893 | F84: 1RUH3031163017 | G84: 370 | H84: 243.88 | I84: CONTRATUAL | J84: 24870458000160 | K84: EDWAL LOBOSCHI | L84: SÃO PAULO | M84: SP | N84: MARINA | O84: JA POSSUI | R84: AUTORIZADO PAGAMENTO | S84: 8202618405 | T84: 5 DIAS ÚTEIS | U84: 46065 | V84: 46065 | W84: 46072 | X84: 46073 | Y84: NÃO | AC84: =IF($C84="","",IF(COUNTIF('Códigos Santander (ref)'!$A$2:$A$79,$C84)>0,"SANTANDER",IF(COUNTIF('Códigos Itaú (ref)'!$A$2:$A$44,$C84)>0,"ITAU",IF(AND(TRIM(UPPER($I84))="CONTRATUAL",ISNUMBER(SEARCH("INDIVIDUAL",SUBSTITUTE(UPPER($D84)," ","")))),"PREMIUM FREE",""))))
A85: TELA | B85: 53106 | C85: 1RUH3 | D85: BANCO SANTANDER BRASIL SA | E85: 7043801613 | F85: 1RUH3001460005 | G85: 1200 | H85: 174.98 | I85: CONTRATUAL | J85: 39876572000174 | K85: L H P MONNERAT | L85: NOVA FRIBURGO | M85: RJ | N85: CIBELY | O85: JA POSSUI | R85: AUTORIZADO PAGAMENTO | S85: 8202618404 | T85: 5 DIAS ÚTEIS | U85: 46065 | V85: 46065 | W85: 46072 | X85: 46073 | Y85: NÃO | AC85: =IF($C85="","",IF(COUNTIF('Códigos Santander (ref)'!$A$2:$A$79,$C85)>0,"SANTANDER",IF(COUNTIF('Códigos Itaú (ref)'!$A$2:$A$44,$C85)>0,"ITAU",IF(AND(TRIM(UPPER($I85))="CONTRATUAL",ISNUMBER(SEARCH("INDIVIDUAL",SUBSTITUTE(UPPER($D85)," ","")))),"PREMIUM FREE",""))))
A86: TELA | B86: 53109 | C86: 0700G | D86: I N D I V I D U A L | E86: 50455885168 | F86: 0700G520876018 | G86: 1800 | H86: 271.2 | I86: CONTRATUAL | J86: 43814309000128 | K86: R E W ODONTOLOGIA INTEGRADA LTDA | L86: BRASILIA | M86: DF | N86: CIBELY | O86: 529944 | P86: 46065 | Q86: 46066 | R86: AUTORIZADO PAGAMENTO | S86: 8202618424 | T86: 30 DIAS CORRIDOS | U86: 46065 | V86: 46066 | W86: 46094 | X86: 46073 | Y86: SIM | AC86: =IF($C86="","",IF(COUNTIF('Códigos Santander (ref)'!$A$2:$A$79,$C86)>0,"SANTANDER",IF(COUNTIF('Códigos Itaú (ref)'!$A$2:$A$44,$C86)>0,"ITAU",IF(AND(TRIM(UPPER($I86))="CONTRATUAL",ISNUMBER(SEARCH("INDIVIDUAL",SUBSTITUTE(UPPER($D86)," ","")))),"PREMIUM FREE",""))))
A87: TELA | B87: 53366 | C87: 0KGE5 | D87: BANCO SANTANDER BRASIL SA | E87: 7898151763 | F87: 0KGE5028783018 | G87: 1600 | H87: 1185 | I87: CONTRATUAL | J87: 229031781 | K87: LEONARDO LIMA BITTENCOURT COSTA | L87: SÃO GONÇALO | M87: RJ | N87: MARINA | O87: JA POSSUI | R87: AUTORIZADO PAGAMENTO | S87: 8202618436 | T87: 5 DIAS ÚTEIS | U87: 46065 | V87: 46066 | W87: 46073 | X87: 46073 | Y87: SIM | AC87: =IF($C87="","",IF(COUNTIF('Códigos Santander (ref)'!$A$2:$A$79,$C87)>0,"SANTANDER",IF(COUNTIF('Códigos Itaú (ref)'!$A$2:$A$44,$C87)>0,"ITAU",IF(AND(TRIM(UPPER($I87))="CONTRATUAL",ISNUMBER(SEARCH("INDIVIDUAL",SUBSTITUTE(UPPER($D87)," ","")))),"PREMIUM FREE",""))))
A88: TELA | B88: 53411 | C88: 1RUH3 | D88: BANCO SANTANDER BRASIL SA | E88: 33183282860 | F88: 1RUH3033827010 | G88: 160 | H88: 90.94 | I88: CONTRATUAL | J88: 35045007866 | K88: PRISCILA GOMES DA SILVA | L88: ATIBAIA | M88: SP | N88: CIBELY | O88: JA POSSUI | R88: AUTORIZADO PAGAMENTO | S88: 8202618435 | T88: 5 DIAS ÚTEIS | U88: 46065 | V88: 46066 | W88: 46073 | X88: 46073 | Y88: SIM | AC88: =IF($C88="","",IF(COUNTIF('Códigos Santander (ref)'!$A$2:$A$79,$C88)>0,"SANTANDER",IF(COUNTIF('Códigos Itaú (ref)'!$A$2:$A$44,$C88)>0,"ITAU",IF(AND(TRIM(UPPER($I88))="CONTRATUAL",ISNUMBER(SEARCH("INDIVIDUAL",SUBSTITUTE(UPPER($D88)," ","")))),"PREMIUM FREE",""))))
A89: TELA | B89: 53587 | C89: 0KGE5 | D89: BANCO SANTANDER BRASIL SA | E89: 7898151763 | F89: 0KGE5028783000 | G89: 1600 | H89: 1185 | I89: CONTRATUAL | J89: 229031781 | K89: LEONARDO LIMA BITTENCOURT COSTA | L89: SÃO GONÇALO | M89: RJ | N89: MARINA | O89: JA POSSUI | R89: AUTORIZADO PAGAMENTO | S89: 8202618434 | T89: 5 DIAS ÚTEIS | U89: 46065 | V89: 46066 | W89: 46073 | X89: 46073 | Y89: SIM | AC89: =IF($C89="","",IF(COUNTIF('Códigos Santander (ref)'!$A$2:$A$79,$C89)>0,"SANTANDER",IF(COUNTIF('Códigos Itaú (ref)'!$A$2:$A$44,$C89)>0,"ITAU",IF(AND(TRIM(UPPER($I89))="CONTRATUAL",ISNUMBER(SEARCH("INDIVIDUAL",SUBSTITUTE(UPPER($D89)," ","")))),"PREMIUM FREE",""))))
A90: TELA | B90: 51722 | C90: S21FQ | D90: SANTANDER SERVICOS DIGITAIS BRASIL LTDA | E90: 15597936867 | F90: S21FQ000046019 | G90: 112 | H90: 112 | I90: CONTRATUAL | J90: 8040735890 | K90: AMAURI CARVALHO DE MORAIS | L90: SÃO PAULO | M90: SP | N90: CIBELY | O90: JA POSSUI | R90: AUTORIZADO PAGAMENTO | S90: 8202618433 | T90: 5 DIAS ÚTEIS | U90: 46065 | V90: 46066 | W90: 46073 | X90: 46073 | Y90: SIM | AC90: =IF($C90="","",IF(COUNTIF('Códigos Santander (ref)'!$A$2:$A$79,$C90)>0,"SANTANDER",IF(COUNTIF('Códigos Itaú (ref)'!$A$2:$A$44,$C90)>0,"ITAU",IF(AND(TRIM(UPPER($I90))="CONTRATUAL",ISNUMBER(SEARCH("INDIVIDUAL",SUBSTITUTE(UPPER($D90)," ","")))),"PREMIUM FREE",""))))
A91: TELA | B91: 53299 | C91: S21FQ | D91: SANTANDER SERVICOS DIGITAIS BRASIL LTDA | E91: 15597936867 | F91: S21FQ000046019 | G91: 160 | H91: 160 | I91: CONTRATUAL | J91: 8040735890 | K91: AMAURI CARVALHO DE MORAIS | L91: SÃO PAULO | M91: SP | N91: CIBELY | O91: JA POSSUI | R91: AUTORIZADO PAGAMENTO | S91: 8202618432 | T91: 5 DIAS ÚTEIS | U91: 46065 | V91: 46066 | W91: 46073 | X91: 46073 | Y91: SIM | AC91: =IF($C91="","",IF(COUNTIF('Códigos Santander (ref)'!$A$2:$A$79,$C91)>0,"SANTANDER",IF(COUNTIF('Códigos Itaú (ref)'!$A$2:$A$44,$C91)>0,"ITAU",IF(AND(TRIM(UPPER($I91))="CONTRATUAL",ISNUMBER(SEARCH("INDIVIDUAL",SUBSTITUTE(UPPER($D91)," ","")))),"PREMIUM FREE",""))))
A92: TELA | B92: 52846 | C92: 50700 | D92: I N D I V I D U A L | E92: 10798975423 | F92: 50700441485001 | G92: 600 | H92: 600 | I92: COBRANÇA INDEVIDA | J92: 37732219000195 | K92: CENTRAL DO SORRISO CLINICA ODONTOLÓGICA | L92: JABOATÃO DOS GUARARAPES | M92: PE | N92: MARINA | O92: 530274 | P92: 46066 | Q92: 46073 | R92: AUTORIZADO PAGAMENTO | S92: 8202618632 | T92: 30 DIAS CORRIDOS | U92: 46065 | V92: 46076 | W92: 46104 | X92: 46080 | Y92: SIM | AC92: =IF($C92="","",IF(COUNTIF('Códigos Santander (ref)'!$A$2:$A$79,$C92)>0,"SANTANDER",IF(COUNTIF('Códigos Itaú (ref)'!$A$2:$A$44,$C92)>0,"ITAU",IF(AND(TRIM(UPPER($I92))="CONTRATUAL",ISNUMBER(SEARCH("INDIVIDUAL",SUBSTITUTE(UPPER($D92)," ","")))),"PREMIUM FREE",""))))
A93: TELA | B93: 53368 | C93: 1RSLN | D93: ITAU UNIBANCO SA | E93: 417200757 | F93: 1RSLN020180020 | G93: 600 | H93: 262.8 | I93: CONTRATUAL | J93: 83768890600 | K93: HELLEN ROSALEE SATHLER VIDAL | L93: NITEROI | M93: RJ | N93: CIBELY | O93: 530266 | P93: 46066 | Q93: 46072 | R93: AUTORIZADO PAGAMENTO | S93: 8202618513 | T93: 5 DIAS ÚTEIS | U93: 46065 | V93: 46072 | W93: 46079 | X93: 46078 | Y93: SIM | Z93: Solicitado alteração de pd e exclusão das outras conta cadastrada | AC93: =IF($C93="","",IF(COUNTIF('Códigos Santander (ref)'!$A$2:$A$79,$C93)>0,"SANTANDER",IF(COUNTIF('Códigos Itaú (ref)'!$A$2:$A$44,$C93)>0,"ITAU",IF(AND(TRIM(UPPER($I93))="CONTRATUAL",ISNUMBER(SEARCH("INDIVIDUAL",SUBSTITUTE(UPPER($D93)," ","")))),"PREMIUM FREE",""))))
A94: TELA | B94: 53090 | C94: 50700 | D94: INDIVIDUAL MAISODONTO | E94: 6274106189 | F94: 50700441317001 | G94: 900 | H94: 99.3 | I94: CONTRATUAL | J94: 52147029000102 | K94: N P CONSULTORIO ODONTOLOGICO | L94: GOIANIA | M94: GO | N94: CIBELY | O94: 530278 | P94: 46066 | Q94: 46072 | R94: AUTORIZADO PAGAMENTO | S94: 8202618530 | T94: 30 DIAS CORRIDOS | U94: 46066 | V94: 46072 | W94: 46079 | X94: 46078 | Y94: SIM | AC94: =IF($C94="","",IF(COUNTIF('Códigos Santander (ref)'!$A$2:$A$79,$C94)>0,"SANTANDER",IF(COUNTIF('Códigos Itaú (ref)'!$A$2:$A$44,$C94)>0,"ITAU",IF(AND(TRIM(UPPER($I94))="CONTRATUAL",ISNUMBER(SEARCH("INDIVIDUAL",SUBSTITUTE(UPPER($D94)," ","")))),"PREMIUM FREE",""))))
A95: TELA | B95: 52973 | C95: 0KGE5 | D95: BANCO SANTANDER BRASIL SA | E95: 7898151763 | F95: 0KGE5028783018 | G95: 280 | H95: 212.19 | I95: CONTRATUAL | J95: 229031781 | K95: LEONARDO LIMA BITTENCOURT COSTA | L95: SÃO GONÇALO | M95: RJ | N95: MARINA | O95: JA POSSUI | R95: AUTORIZADO PAGAMENTO | S95: 8202618431 | T95: 5 DIAS ÚTEIS | U95: 46066 | V95: 46066 | W95: 46073 | X95: 46073 | Y95: SIM | AC95: =IF($C95="","",IF(COUNTIF('Códigos Santander (ref)'!$A$2:$A$79,$C95)>0,"SANTANDER",IF(COUNTIF('Códigos Itaú (ref)'!$A$2:$A$44,$C95)>0,"ITAU",IF(AND(TRIM(UPPER($I95))="CONTRATUAL",ISNUMBER(SEARCH("INDIVIDUAL",SUBSTITUTE(UPPER($D95)," ","")))),"PREMIUM FREE",""))))
A96: TELA | B96: 53347 | C96: 1RUB1 | D96: F1RST TECNOLOGIA E INOVACAO LTDA | E96: 35369845840 | F96: 1RUB1002304015 | G96: 280 | H96: 85.4 | I96: CONTRATUAL | J96: 36897556890 | K96: INGRID CAROLINE CRUZ BUSSINE | L96: SÃO PAULO | M96: SP | N96: MARINA | O96: JA POSSUI | R96: AUTORIZADO PAGAMENTO | S96: 8202618430 | T96: 5 DIAS ÚTEIS | U96: 46066 | V96: 46066 | W96: 46073 | X96: 46073 | Y96: SIM | AC96: =IF($C96="","",IF(COUNTIF('Códigos Santander (ref)'!$A$2:$A$79,$C96)>0,"SANTANDER",IF(COUNTIF('Códigos Itaú (ref)'!$A$2:$A$44,$C96)>0,"ITAU",IF(AND(TRIM(UPPER($I96))="CONTRATUAL",ISNUMBER(SEARCH("INDIVIDUAL",SUBSTITUTE(UPPER($D96)," ","")))),"PREMIUM FREE",""))))
A97: TELA | B97: 53502 | C97: 0M19C | D97: BANCO CSF SA | E97: 35194378807 | F97: 0M19C000204013 | G97: 250 | H97: 250 | I97: CONTRATUAL | J97: 30548027000184 | K97: KPMF CENTRO DE SAÚDE LTDA | L97: PRAIA GRANDE | M97: SP | N97: MARINA | O97: 530502 | P97: 46072 | Q97: 46073 | R97: AUTORIZADO PAGAMENTO | S97: 8202618633 | T97: 8 DIAS ÚTEIS | U97: 46066 | V97: 46076 | W97: 46086 | X97: 46080 | Y97: SIM | AC97: =IF($C97="","",IF(COUNTIF('Códigos Santander (ref)'!$A$2:$A$79,$C97)>0,"SANTANDER",IF(COUNTIF('Códigos Itaú (ref)'!$A$2:$A$44,$C97)>0,"ITAU",IF(AND(TRIM(UPPER($I97))="CONTRATUAL",ISNUMBER(SEARCH("INDIVIDUAL",SUBSTITUTE(UPPER($D97)," ","")))),"PREMIUM FREE",""))))
A98: TELA | B98: 53570 | C98: S21FQ | D98: SANTANDER SERVICOS DIGITAIS BRASIL LTDA | E98: 21400310830 | F98: S21FQ000899020 | G98: 250 | H98: 212.19 | I98: CONTRATUAL | J98: 11186762896 | K98: ANA CLAUDIA GUIMARÃES COSTA | L98: CAMPINAS | M98: SP | N98: MARINA | O98: JA POSSUI | R98: AUTORIZADO PAGAMENTO | S98: 8202618531 | T98: 5 DIAS ÚTEIS | U98: 46066 | V98: 46072 | W98: 46079 | X98: 46078 | Y98: SIM | AC98: =IF($C98="","",IF(COUNTIF('Códigos Santander (ref)'!$A$2:$A$79,$C98)>0,"SANTANDER",IF(COUNTIF('Códigos Itaú (ref)'!$A$2:$A$44,$C98)>0,"ITAU",IF(AND(TRIM(UPPER($I98))="CONTRATUAL",ISNUMBER(SEARCH("INDIVIDUAL",SUBSTITUTE(UPPER($D98)," ","")))),"PREMIUM FREE",""))))
A99: TELA | B99: 53408 | C99: 1RSLN | D99: ITAU UNIBANCO SA | E99: 28732210892 | F99: 1RSLN016355016 | G99: 100 | H99: 100 | I99: CONTRATUAL | J99: 42153966000109 | K99: REIS ODONTOLOGIA | L99: SÃO PAULO | M99: SP | N99: CIBELY | O99: 530500 | P99: 46072 | Q99: 46072 | R99: AUTORIZADO PAGAMENTO | S99: 8202618555 | T99: 5 DIAS ÚTEIS | U99: 46066 | V99: 46072 | W99: 46079 | X99: 46078 | Y99: SIM | AC99: =IF($C99="","",IF(COUNTIF('Códigos Santander (ref)'!$A$2:$A$79,$C99)>0,"SANTANDER",IF(COUNTIF('Códigos Itaú (ref)'!$A$2:$A$44,$C99)>0,"ITAU",IF(AND(TRIM(UPPER($I99))="CONTRATUAL",ISNUMBER(SEARCH("INDIVIDUAL",SUBSTITUTE(UPPER($D99)," ","")))),"PREMIUM FREE",""))))
A100: TELA | B100: 53501 | C100: 1RU51 | D100: BANCO SANTANDER BRASIL SA | E100: 53245881720 | F100: 1RU51000497029 | G100: 2100 | H100: 512.4 | I100: CONTRATUAL | J100: 72216484768 | K100: RUBEM RIBEIRO MAURELL | L100: RIO DE JANEIRO | M100: RJ | N100: MARINA | O100: JA POSSUI | R100: AUTORIZADO PAGAMENTO | S100: 8202618715 | T100: 5 DIAS ÚTEIS | U100: 46066 | V100: 46077 | W100: 46084 | X100: 46085 | Y100: NÃO | AC100: =IF($C100="","",IF(COUNTIF('Códigos Santander (ref)'!$A$2:$A$79,$C100)>0,"SANTANDER",IF(COUNTIF('Códigos Itaú (ref)'!$A$2:$A$44,$C100)>0,"ITAU",IF(AND(TRIM(UPPER($I100))="CONTRATUAL",ISNUMBER(SEARCH("INDIVIDUAL",SUBSTITUTE(UPPER($D100)," ","")))),"PREMIUM FREE",""))))
...

Sheet Março 2026
A1: CANAL | B1: N° SOLICITAÇÃO | C1: CÓD. EMPRESA | D1: EMPRESA | E1: CPF TITULAR | F1: COD. DO BENEFICIÁRIO | G1: VALOR SOLICITADO | H1: VALOR PAGO | I1: MOTIVO | J1: CPF/CNPJ DENTISTA | K1: NOME PRESTADOR DE SERVIÇO | L1: CIDADE PRESTADOR | M1: UF PRESTADOR | N1: AUDITOR | O1: ASTREIN | P1: DT SOLICITAÇÃO ASTREIN | Q1: DT LIBERAÇÃO ASTREIN | R1: STATUS DA SOLICITAÇÃO | S1: PROCESSO | T1: PRAZO CONTRATUAL | U1: DT AUDITORIA | V1: DT APROVAÇÃO | W1: DT PRAZO CONTRATUAL | X1: DATA DE PAGAMENTO SAP | Y1: PRAZO ATENDIDO | Z1: OBS | AC1: SEGMENTO (auxiliar automático)
A2: TELA | B2: 53753 | C2: 1RUH3 | D2: BANCO SANTANDER BRASIL SA | E2: 44360522819 | F2: 1RUH3003722007 | G2: 495 | H2: 368.48 | I2: CONTRATUAL | J2: 24870458000160 | K2: EDWAL LOBOSCHI | L2: SÃO PAULO | M2: SP | N2: SERGIANA | O2: 533802 | P2: 46083 | Q2: 46086 | R2: AUTORIZADO PAGAMENTO | S2: 8202625268 | T2: 5 DIAS ÚTEIS | U2: 46077 | V2: 46086 | W2: 46093 | X2: 46092 | Y2: =IF(AND(X2<>"",W2<>""),IF(X2<=W2,"SIM","NÃO"),"") | Z2: ALTERAÇÃO DE PD | AC2: =IF($C2="","",IF(COUNTIF('Códigos Santander (ref)'!$A$2:$A$79,$C2)>0,"SANTANDER",IF(COUNTIF('Códigos Itaú (ref)'!$A$2:$A$44,$C2)>0,"ITAU",IF(AND(TRIM(UPPER($I2))="CONTRATUAL",ISNUMBER(SEARCH("INDIVIDUAL",SUBSTITUTE(UPPER($D2)," ","")))),"PREMIUM FREE",""))))
A3: TELA | B3: 53907 | C3: 1RUH3 | D3: BANCO SANTANDER BRASIL SA | E3: 9068347918 | F3: 1RUH3000800007 | G3: 120 | H3: 120 | I3: CONTRATUAL | J3: 7494312000148 | K3: RADIOFACIAL CLINICA DE RADIOLOGIA ODONTOLOGICA LTDA ME | L3: SÃO JOSÉ | M3: SP | N3: SERGIANA | O3: 533119 | P3: 46080 | Q3: 46083 | R3: AUTORIZADO PAGAMENTO | S3: 8202625025 | T3: 5 DIAS ÚTEIS | U3: 46079 | V3: 46083 | W3: 46090 | X3: 46087 | Y3: =IF(AND(X3<>"",W3<>""),IF(X3<=W3,"SIM","NÃO"),"") | AC3: =IF($C3="","",IF(COUNTIF('Códigos Santander (ref)'!$A$2:$A$79,$C3)>0,"SANTANDER",IF(COUNTIF('Códigos Itaú (ref)'!$A$2:$A$44,$C3)>0,"ITAU",IF(AND(TRIM(UPPER($I3))="CONTRATUAL",ISNUMBER(SEARCH("INDIVIDUAL",SUBSTITUTE(UPPER($D3)," ","")))),"PREMIUM FREE",""))))
A4: TELA | B4: 53795 | C4: 1RUH3 | D4: BANCO SANTANDER BRASIL SA | E4: 9068347918 | F4: 1RUH3000800015 | G4: 120 | H4: 120 | I4: CONTRATUAL | J4: 7494312000148 | K4: RADIOFACIAL CLINICA DE RADIOLOGIA ODONTOLOGICA LTDA ME | L4: SÃO JOSÉ | M4: SC | N4: SERGIANA | O4: 533119 | P4: 46080 | Q4: 46083 | R4: AUTORIZADO PAGAMENTO | S4: 8202625023 | T4: 5 DIAS ÚTEIS | U4: 46079 | V4: 46083 | W4: 46090 | X4: 46087 | Y4: =IF(AND(X4<>"",W4<>""),IF(X4<=W4,"SIM","NÃO"),"") | AC4: =IF($C4="","",IF(COUNTIF('Códigos Santander (ref)'!$A$2:$A$79,$C4)>0,"SANTANDER",IF(COUNTIF('Códigos Itaú (ref)'!$A$2:$A$44,$C4)>0,"ITAU",IF(AND(TRIM(UPPER($I4))="CONTRATUAL",ISNUMBER(SEARCH("INDIVIDUAL",SUBSTITUTE(UPPER($D4)," ","")))),"PREMIUM FREE",""))))
A5: TELA | B5: 53635 | C5: 1RUF4 | D5: AYMORE CREDITO FINANCIAMENTO E INVESTIMENTO S | E5: 38578440862 | F5: 1RUF4000485004 | G5: 8650 | H5: 587.38 | I5: CONTRATUAL | J5: 30768599000179 | K5: ZANETTI E MARQUESINI ODONTOLOGIA ESPECIALIZADA LTDA | L5: PORTO FERREIRA | M5: SP | N5: SERGIANA | O5: 533108 | P5: 46080 | Q5: 46083 | R5: AUTORIZADO PAGAMENTO | S5: 8202625026 | T5: 5 DIAS ÚTEIS | U5: 46079 | V5: 46083 | W5: 46090 | X5: 46087 | Y5: =IF(AND(X5<>"",W5<>""),IF(X5<=W5,"SIM","NÃO"),"") | AC5: =IF($C5="","",IF(COUNTIF('Códigos Santander (ref)'!$A$2:$A$79,$C5)>0,"SANTANDER",IF(COUNTIF('Códigos Itaú (ref)'!$A$2:$A$44,$C5)>0,"ITAU",IF(AND(TRIM(UPPER($I5))="CONTRATUAL",ISNUMBER(SEARCH("INDIVIDUAL",SUBSTITUTE(UPPER($D5)," ","")))),"PREMIUM FREE",""))))
A6: TELA | B6: 53634 | C6: 1RUH3 | D6: BANCO SANTANDER BRASIL SA | E6: 22478528827 | F6: 1RUH3027404005 | G6: 4390 | H6: 261.03 | I6: CONTRATUAL | J6: 8604164000130 | K6: CENTRO DE TRATAMENTO E REABILITACAO ORAL ODONTO ALPHA | L6: PIRACICABA | M6: SP | N6: SERGIANA | O6: 532811 | P6: 46079 | Q6: 46083 | R6: AUTORIZADO PAGAMENTO | S6: 8202625028 | T6: 5 DIAS ÚTEIS | U6: 46079 | V6: 46083 | W6: 46090 | X6: 46087 | Y6: =IF(AND(X6<>"",W6<>""),IF(X6<=W6,"SIM","NÃO"),"") | AC6: =IF($C6="","",IF(COUNTIF('Códigos Santander (ref)'!$A$2:$A$79,$C6)>0,"SANTANDER",IF(COUNTIF('Códigos Itaú (ref)'!$A$2:$A$44,$C6)>0,"ITAU",IF(AND(TRIM(UPPER($I6))="CONTRATUAL",ISNUMBER(SEARCH("INDIVIDUAL",SUBSTITUTE(UPPER($D6)," ","")))),"PREMIUM FREE",""))))
A7: TELA | B7: 53395 | C7: 1RSLN | D7: ITAU UNIBANCO SA | E7: 43504739800 | F7: 1RSLN021733007 | G7: 1600 | H7: 1600 | I7: CONTRATUAL | J7: 26287220000131 | K7: CENTRO ODONTOLOGICO POLLI & VASO | L7: DOIS CORREGOS | M7: SP | N7: CIBELY | O7: 531723 | P7: 46077 | Q7: 46078 | R7: AUTORIZADO PAGAMENTO | S7: 8202625041 | T7: 5 DIAS ÚTEIS | U7: 46076 | V7: 46084 | W7: 46091 | X7: 46090 | Y7: =IF(AND(X7<>"",W7<>""),IF(X7<=W7,"SIM","NÃO"),"") | AC7: =IF($C7="","",IF(COUNTIF('Códigos Santander (ref)'!$A$2:$A$79,$C7)>0,"SANTANDER",IF(COUNTIF('Códigos Itaú (ref)'!$A$2:$A$44,$C7)>0,"ITAU",IF(AND(TRIM(UPPER($I7))="CONTRATUAL",ISNUMBER(SEARCH("INDIVIDUAL",SUBSTITUTE(UPPER($D7)," ","")))),"PREMIUM FREE",""))))
A8: TELA | B8: 53499 | C8: 1RUD0 | D8: SANTANDER ADVISORY SERVICES SA | E8: 36140455871 | F8: 1RUD0002675013 | G8: 250 | H8: 212.19 | I8: CONTRATUAL | J8: 56606768000168 | K8: AMYO CLINIC SERVICOS ODONTOLOGICOS LTDA | L8: CAMPINAS | M8: SP | N8: SERGIANA | O8: 531695 | P8: 46077 | Q8: 46079 | R8: AUTORIZADO PAGAMENTO | S8: 8202625105 | T8: 5 DIAS ÚTEIS | U8: 46072 | V8: 46084 | W8: 46091 | X8: 46090 | Y8: =IF(AND(X8<>"",W8<>""),IF(X8<=W8,"SIM","NÃO"),"") | Z8: (ALTERAÇÃO DE PD). | AC8: =IF($C8="","",IF(COUNTIF('Códigos Santander (ref)'!$A$2:$A$79,$C8)>0,"SANTANDER",IF(COUNTIF('Códigos Itaú (ref)'!$A$2:$A$44,$C8)>0,"ITAU",IF(AND(TRIM(UPPER($I8))="CONTRATUAL",ISNUMBER(SEARCH("INDIVIDUAL",SUBSTITUTE(UPPER($D8)," ","")))),"PREMIUM FREE",""))))
A9: TELA | B9: 51302 | C9: 1RU51 | D9: BANCO SANTANDER BRASIL SA | E9: 58080953015 | F9: 1RU51000784001 | G9: 14550 | H9: 3877.61 | I9: CONTRATUAL | J9: 8800821000114 | K9: CLINICA DINATO DE OODONTOLOGIA LTDA | L9: PORTO ALEGRE | M9: RS | N9: SERGIANA | O9: 532001 | P9: 46077 | Q9: 46078 | R9: AUTORIZADO PAGAMENTO | S9: 8202625106 | T9: 5 DIAS ÚTEIS | U9: 46077 | V9: 46084 | W9: 46091 | X9: 46090 | Y9: =IF(AND(X9<>"",W9<>""),IF(X9<=W9,"SIM","NÃO"),"") | AC9: =IF($C9="","",IF(COUNTIF('Códigos Santander (ref)'!$A$2:$A$79,$C9)>0,"SANTANDER",IF(COUNTIF('Códigos Itaú (ref)'!$A$2:$A$44,$C9)>0,"ITAU",IF(AND(TRIM(UPPER($I9))="CONTRATUAL",ISNUMBER(SEARCH("INDIVIDUAL",SUBSTITUTE(UPPER($D9)," ","")))),"PREMIUM FREE",""))))
A10: TELA | B10: 53254 | C10: 1RUH3 | D10: BANCO SANTANDER BRASIL SA | E10: 99421690672 | F10: 1RUH3040375021 | G10: 405 | H10: 308.67 | I10: CONTRATUAL | J10: 3944402340 | K10: MARINA BATISTA DE FIGUEIREDO MORAIS | L10: BELO HORIZONTE | M10: MG | N10: SERGIANA | O10: 531842 | P10: 46077 | Q10: 46085 | R10: AUTORIZADO PAGAMENTO | S10: 8202625271 | T10: 5 DIAS ÚTEIS | U10: 46077 | V10: 46086 | W10: 46093 | X10: 46092 | Y10: =IF(AND(X10<>"",W10<>""),IF(X10<=W10,"SIM","NÃO"),"") | AC10: =IF($C10="","",IF(COUNTIF('Códigos Santander (ref)'!$A$2:$A$79,$C10)>0,"SANTANDER",IF(COUNTIF('Códigos Itaú (ref)'!$A$2:$A$44,$C10)>0,"ITAU",IF(AND(TRIM(UPPER($I10))="CONTRATUAL",ISNUMBER(SEARCH("INDIVIDUAL",SUBSTITUTE(UPPER($D10)," ","")))),"PREMIUM FREE",""))))
A11: TELA | B11: 53807 | C11: 1RUH3 | D11: BANCO SANTANDER BRASIL SA | E11: 99421690672 | F11: 1RUH3040375005 | G11: 270 | H11: 173.67 | I11: CONTRATUAL | J11: 3944402340 | K11: MARINA BATISTA DE FIGUEIREDO MORAIS | L11: BELO HORIZONTE | M11: MG | N11: SERGIANA | O11: 531842 | P11: 46077 | Q11: 46085 | R11: AUTORIZADO PAGAMENTO | S11: 8202625272 | T11: 5 DIAS ÚTEIS | U11: 46077 | V11: 46086 | W11: 46093 | X11: 46092 | Y11: =IF(AND(X11<>"",W11<>""),IF(X11<=W11,"SIM","NÃO"),"") | AC11: =IF($C11="","",IF(COUNTIF('Códigos Santander (ref)'!$A$2:$A$79,$C11)>0,"SANTANDER",IF(COUNTIF('Códigos Itaú (ref)'!$A$2:$A$44,$C11)>0,"ITAU",IF(AND(TRIM(UPPER($I11))="CONTRATUAL",ISNUMBER(SEARCH("INDIVIDUAL",SUBSTITUTE(UPPER($D11)," ","")))),"PREMIUM FREE",""))))
A12: TELA | B12: 53798 | C12: 1RUH3 | D12: BANCO SANTANDER BRASIL SA | E12: 1082757012 | F12: 1RUH3039457028 | G12: 120 | H12: 120 | I12: CONTRATUAL | J12: 15410011000389 | K12: RADIOLOGIA ODONTOLOGICA DOS VALES LTDA | L12: SANTA CRUZ DO SUL | M12: RS | N12: SERGIANA | O12: 533844 | P12: 46084 | Q12: 46085 | R12: AUTORIZADO PAGAMENTO | S12: 8202625202 | T12: 5 DIAS UTEIS | U12: 46083 | V12: 46085 | W12: 46092 | X12: 46090 | Y12: =IF(AND(X12<>"",W12<>""),IF(X12<=W12,"SIM","NÃO"),"") | AC12: =IF($C12="","",IF(COUNTIF('Códigos Santander (ref)'!$A$2:$A$79,$C12)>0,"SANTANDER",IF(COUNTIF('Códigos Itaú (ref)'!$A$2:$A$44,$C12)>0,"ITAU",IF(AND(TRIM(UPPER($I12))="CONTRATUAL",ISNUMBER(SEARCH("INDIVIDUAL",SUBSTITUTE(UPPER($D12)," ","")))),"PREMIUM FREE",""))))
A13: TELA | B13: 53877 | C13: 1RSX8 | D13: ITAU UNIBANCO SA | E13: 86498584734 | F13: 1RSX8000168025 | G13: 450 | H13: 450 | I13: CONTRATUAL | J13: 229031781 | K13: LEONARDO LIMA BITTENCOURT COSTA | L13: SÃO GONÇALO | M13: RJ | N13: SERGIANA | O13: JA POSSUI | R13: AUTORIZADO PAGAMENTO | S13: 8202625008 | T13: 5 DIAS UTEIS | U13: 46083 | V13: 46083 | W13: 46090 | X13: 46087 | Y13: =IF(AND(X13<>"",W13<>""),IF(X13<=W13,"SIM","NÃO"),"") | AC13: =IF($C13="","",IF(COUNTIF('Códigos Santander (ref)'!$A$2:$A$79,$C13)>0,"SANTANDER",IF(COUNTIF('Códigos Itaú (ref)'!$A$2:$A$44,$C13)>0,"ITAU",IF(AND(TRIM(UPPER($I13))="CONTRATUAL",ISNUMBER(SEARCH("INDIVIDUAL",SUBSTITUTE(UPPER($D13)," ","")))),"PREMIUM FREE",""))))
A14: TELA | B14: 53175 | C14: 1RSX8 | D14: ITAU UNIBANCO SA | E14: 86498584734 | F14: 1RSX8000168025 | G14: 450 | H14: 450 | I14: CONTRATUAL | J14: 229031781 | K14: LEONARDO LIMA BITTENCOURT COSTA | L14: SÃO GONÇALO | M14: RJ | N14: SERGIANA | O14: JA POSSUI | R14: AUTORIZADO PAGAMENTO | S14: 8202625011 | T14: 5 DIAS UTEIS | U14: 46083 | V14: 46083 | W14: 46090 | X14: 46087 | Y14: =IF(AND(X14<>"",W14<>""),IF(X14<=W14,"SIM","NÃO"),"") | AC14: =IF($C14="","",IF(COUNTIF('Códigos Santander (ref)'!$A$2:$A$79,$C14)>0,"SANTANDER",IF(COUNTIF('Códigos Itaú (ref)'!$A$2:$A$44,$C14)>0,"ITAU",IF(AND(TRIM(UPPER($I14))="CONTRATUAL",ISNUMBER(SEARCH("INDIVIDUAL",SUBSTITUTE(UPPER($D14)," ","")))),"PREMIUM FREE",""))))
A15: TELA | B15: 53141 | C15: 1RSX8 | D15: ITAU UNIBANCO SA | E15: 86498584734 | F15: 1RSX8000168025 | G15: 450 | H15: 450 | I15: CONTRATUAL | J15: 229031781 | K15: LEONARDO LIMA BITTENCOURT COSTA | L15: SÃO GONÇALO | M15: RJ | N15: SERGIANA | O15: JA POSSUI | R15: AUTORIZADO PAGAMENTO | S15: 8202625012 | T15: 5 DIAS UTEIS | U15: 46083 | V15: 46083 | W15: 46090 | X15: 46087 | Y15: =IF(AND(X15<>"",W15<>""),IF(X15<=W15,"SIM","NÃO"),"") | AC15: =IF($C15="","",IF(COUNTIF('Códigos Santander (ref)'!$A$2:$A$79,$C15)>0,"SANTANDER",IF(COUNTIF('Códigos Itaú (ref)'!$A$2:$A$44,$C15)>0,"ITAU",IF(AND(TRIM(UPPER($I15))="CONTRATUAL",ISNUMBER(SEARCH("INDIVIDUAL",SUBSTITUTE(UPPER($D15)," ","")))),"PREMIUM FREE",""))))
A16: TELA | B16: 53200 | C16: 1RSX8 | D16: ITAU UNIBANCO SA | E16: 86498584734 | F16: 1RSX8000168025 | G16: 450 | H16: 450 | I16: CONTRATUAL | J16: 229031781 | K16: LEONARDO LIMA BITTENCOURT COSTA | L16: SÃO GONÇALO | M16: RJ | N16: SERGIANA | O16: JA POSSUI | R16: AUTORIZADO PAGAMENTO | S16: 8202625014 | T16: 5 DIAS UTEIS | U16: 46083 | V16: 46083 | W16: 46090 | X16: 46087 | Y16: =IF(AND(X16<>"",W16<>""),IF(X16<=W16,"SIM","NÃO"),"") | AC16: =IF($C16="","",IF(COUNTIF('Códigos Santander (ref)'!$A$2:$A$79,$C16)>0,"SANTANDER",IF(COUNTIF('Códigos Itaú (ref)'!$A$2:$A$44,$C16)>0,"ITAU",IF(AND(TRIM(UPPER($I16))="CONTRATUAL",ISNUMBER(SEARCH("INDIVIDUAL",SUBSTITUTE(UPPER($D16)," ","")))),"PREMIUM FREE",""))))
A17: TELA | B17: 53938 | C17: S21FQ | D17: SANTANDER SERVICOS DIGITAIS BRASIL LTDA | E17: 8166309688 | F17: S21FQ001220020 | G17: 200 | H17: 170.8 | I17: CONTRATUAL | J17: 8604164000130 | K17: CENTRO DE TRATAMENTO E REABILITACAO ORAL ODONTO ALPHA LTDA | L17: PIRACICABA | M17: SP | N17: SERGIANA | O17: 533846 | P17: 46084 | Q17: 46085 | R17: AUTORIZADO PAGAMENTO | S17: 8202625214 | T17: 5 DIAS UTEIS | U17: 46083 | V17: 46085 | W17: 46092 | X17: 46090 | Y17: =IF(AND(X17<>"",W17<>""),IF(X17<=W17,"SIM","NÃO"),"") | AC17: =IF($C17="","",IF(COUNTIF('Códigos Santander (ref)'!$A$2:$A$79,$C17)>0,"SANTANDER",IF(COUNTIF('Códigos Itaú (ref)'!$A$2:$A$44,$C17)>0,"ITAU",IF(AND(TRIM(UPPER($I17))="CONTRATUAL",ISNUMBER(SEARCH("INDIVIDUAL",SUBSTITUTE(UPPER($D17)," ","")))),"PREMIUM FREE",""))))
A18: TELA | B18: 53931 | C18: 1RU54 | D18: BANCO SANTANDER BRASIL SA | E18: 24804827587 | F18: 1RU54000248002 | G18: 30 | H18: 7.43 | I18: CONTRATUAL | J18: 52270922000112 | K18: ODONTOLOGIA BARROS CARVALHO LTDA | L18: SALVADOR | M18: BA | N18: SERGIANA | O18: JA POSSUI | R18: AUTORIZADO PAGAMENTO | S18: 8202625017 | T18: 5 DIAS UTEIS | U18: 46083 | V18: 46083 | W18: 46090 | X18: 46087 | Y18: =IF(AND(X18<>"",W18<>""),IF(X18<=W18,"SIM","NÃO"),"") | AC18: =IF($C18="","",IF(COUNTIF('Códigos Santander (ref)'!$A$2:$A$79,$C18)>0,"SANTANDER",IF(COUNTIF('Códigos Itaú (ref)'!$A$2:$A$44,$C18)>0,"ITAU",IF(AND(TRIM(UPPER($I18))="CONTRATUAL",ISNUMBER(SEARCH("INDIVIDUAL",SUBSTITUTE(UPPER($D18)," ","")))),"PREMIUM FREE",""))))
A19: TELA | B19: 53284 | C19: 1RU54 | D19: BANCO SANTANDER BRASIL SA | E19: 24804827587 | F19: 1RU54000248002 | G19: 300 | H19: 35 | I19: CONTRATUAL | J19: 54116505000145 | K19: TAVARES ODONTOLOGIA INTEGRADA LTDA | L19: SALVADOR | M19: BA | N19: SERGIANA | O19: JA POSSUI | R19: AUTORIZADO PAGAMENTO | S19: 8202625018 | T19: 5 DIAS UTEIS | U19: 46083 | V19: 46083 | W19: 46090 | X19: 46087 | Y19: =IF(AND(X19<>"",W19<>""),IF(X19<=W19,"SIM","NÃO"),"") | AC19: =IF($C19="","",IF(COUNTIF('Códigos Santander (ref)'!$A$2:$A$79,$C19)>0,"SANTANDER",IF(COUNTIF('Códigos Itaú (ref)'!$A$2:$A$44,$C19)>0,"ITAU",IF(AND(TRIM(UPPER($I19))="CONTRATUAL",ISNUMBER(SEARCH("INDIVIDUAL",SUBSTITUTE(UPPER($D19)," ","")))),"PREMIUM FREE",""))))
A20: TELA | B20: 53892 | C20: 1RUH3 | D20: BANCO SANTANDER BRASIL SA | E20: 25297720885 | F20: 1RUH3032877005 | G20: 350 | H20: 163.8 | I20: CONTRATUAL | J20: 24870458000160 | K20: EDWAL LOBOSCHI | L20: SÃO PAULO | M20: SP | N20: SERGIANA | O20: JA POSSUI | R20: AUTORIZADO PAGAMENTO | S20: 8202625021 | T20: 5 DIAS UTEIS | U20: 46083 | V20: 46083 | W20: 46090 | X20: 46087 | Y20: =IF(AND(X20<>"",W20<>""),IF(X20<=W20,"SIM","NÃO"),"") | AC20: =IF($C20="","",IF(COUNTIF('Códigos Santander (ref)'!$A$2:$A$79,$C20)>0,"SANTANDER",IF(COUNTIF('Códigos Itaú (ref)'!$A$2:$A$44,$C20)>0,"ITAU",IF(AND(TRIM(UPPER($I20))="CONTRATUAL",ISNUMBER(SEARCH("INDIVIDUAL",SUBSTITUTE(UPPER($D20)," ","")))),"PREMIUM FREE",""))))
A21: TELA | B21: 53803 | C21: 1RSLN | D21: ITAU UNIBANCO SA | E21: 16039128780 | F21: 1RSLN008271003 | G21: 450 | H21: 450 | I21: CONTRATUAL | J21: 5950466730 | K21: ZULMA FLORES BLANCO QUEIROZ | L21: SÃO GONÇALO | M21: RJ | N21: CIBELY | O21: JA POSSUI | R21: AUTORIZADO PAGAMENTO | S21: 8202625022 | T21: 5 DIAS ÚTEIS | U21: 46083 | V21: 46083 | W21: 46090 | X21: 46087 | Y21: =IF(AND(X21<>"",W21<>""),IF(X21<=W21,"SIM","NÃO"),"") | AC21: =IF($C21="","",IF(COUNTIF('Códigos Santander (ref)'!$A$2:$A$79,$C21)>0,"SANTANDER",IF(COUNTIF('Códigos Itaú (ref)'!$A$2:$A$44,$C21)>0,"ITAU",IF(AND(TRIM(UPPER($I21))="CONTRATUAL",ISNUMBER(SEARCH("INDIVIDUAL",SUBSTITUTE(UPPER($D21)," ","")))),"PREMIUM FREE",""))))
A22: TELA | B22: 53967 | C22: 1RSLN | D22: ITAU UNIBANCO SA | E22: 16039128780 | F22: 1RSLN008271003 | G22: 450 | H22: 450 | I22: CONTRATUAL | J22: 5950466730 | K22: ZULMA FLORES BLANCO QUEIROZ | L22: SÃO GONÇALO | M22: RJ | N22: CIBELY | O22: JA POSSUI | R22: AUTORIZADO PAGAMENTO | S22: 8202625020 | T22: 5 DIAS ÚTEIS | U22: 46083 | V22: 46083 | W22: 46090 | X22: 46087 | Y22: =IF(AND(X22<>"",W22<>""),IF(X22<=W22,"SIM","NÃO"),"") | AC22: =IF($C22="","",IF(COUNTIF('Códigos Santander (ref)'!$A$2:$A$79,$C22)>0,"SANTANDER",IF(COUNTIF('Códigos Itaú (ref)'!$A$2:$A$44,$C22)>0,"ITAU",IF(AND(TRIM(UPPER($I22))="CONTRATUAL",ISNUMBER(SEARCH("INDIVIDUAL",SUBSTITUTE(UPPER($D22)," ","")))),"PREMIUM FREE",""))))
A23: TELA | B23: 53644 | C23: 1RSLN | D23: ITAU UNIBANCO SA | E23: 16039128780 | F23: 1RSLN008271003 | G23: 450 | H23: 450 | I23: CONTRATUAL | J23: 5950466730 | K23: ZULMA FLORES BLANCO QUEIROZ | L23: SÃO GONÇALO | M23: RJ | N23: CIBELY | O23: JA POSSUI | R23: AUTORIZADO PAGAMENTO | S23: 8202625013 | T23: 5 DIAS ÚTEIS | U23: 46083 | V23: 46083 | W23: 46090 | X23: 46087 | Y23: =IF(AND(X23<>"",W23<>""),IF(X23<=W23,"SIM","NÃO"),"") | AC23: =IF($C23="","",IF(COUNTIF('Códigos Santander (ref)'!$A$2:$A$79,$C23)>0,"SANTANDER",IF(COUNTIF('Códigos Itaú (ref)'!$A$2:$A$44,$C23)>0,"ITAU",IF(AND(TRIM(UPPER($I23))="CONTRATUAL",ISNUMBER(SEARCH("INDIVIDUAL",SUBSTITUTE(UPPER($D23)," ","")))),"PREMIUM FREE",""))))
A24: TELA | B24: 53801 | C24: 1RUH3 | D24: BANCO SANTANDER BRASIL SA | E24: 2243809745 | F24: 1RUH3040396029 | G24: 260 | H24: 90.94 | I24: CONTRATUAL | J24: 5950466730 | K24: ZULMA FLORES BLANCO QUEIROZ | L24: SÃO GONÇALO | M24: RJ | N24: SERGIANA | O24: JA POSSUI | R24: AUTORIZADO PAGAMENTO | S24: 8202625010 | T24: 5 DIAS ÚTEIS | U24: 46083 | V24: 46083 | W24: 46090 | X24: 46087 | Y24: =IF(AND(X24<>"",W24<>""),IF(X24<=W24,"SIM","NÃO"),"") | AC24: =IF($C24="","",IF(COUNTIF('Códigos Santander (ref)'!$A$2:$A$79,$C24)>0,"SANTANDER",IF(COUNTIF('Códigos Itaú (ref)'!$A$2:$A$44,$C24)>0,"ITAU",IF(AND(TRIM(UPPER($I24))="CONTRATUAL",ISNUMBER(SEARCH("INDIVIDUAL",SUBSTITUTE(UPPER($D24)," ","")))),"PREMIUM FREE",""))))
A25: TELA | B25: 53802 | C25: 1RUB1 | D25: F1RST TECNOLOGIA E INOVACAO LTDA | E25: 35303316866 | F25: 1RUB1004107004 | G25: 1200 | H25: 144.35 | I25: CONTRATUAL | J25: 31483879000101 | K25: AARTE ODONTOLOGIA ESPECIALIZADA LTDA | L25: OSASCO | M25: SP | N25: SERGIANA | O25: 533851 | P25: 46084 | Q25: 46085 | R25: AUTORIZADO PAGAMENTO | S25: 8202625205 | T25: 5 DIAS ÚTEIS | U25: 46083 | V25: 46085 | W25: 46092 | X25: 46090 | Y25: =IF(AND(X25<>"",W25<>""),IF(X25<=W25,"SIM","NÃO"),"") | AC25: =IF($C25="","",IF(COUNTIF('Códigos Santander (ref)'!$A$2:$A$79,$C25)>0,"SANTANDER",IF(COUNTIF('Códigos Itaú (ref)'!$A$2:$A$44,$C25)>0,"ITAU",IF(AND(TRIM(UPPER($I25))="CONTRATUAL",ISNUMBER(SEARCH("INDIVIDUAL",SUBSTITUTE(UPPER($D25)," ","")))),"PREMIUM FREE",""))))
A26: TELA | B26: 53857 | C26: 1RUH3 | D26: BANCO SANTANDER BRASIL SA | E26: 43673362801 | F26: 1RUH3018872000 | G26: 350 | H26: 19.54 | I26: CONTRATUAL | J26: 40735644000142 | K26: DOT ODONTOLOGIA LTDA | L26: CAMPINAS | M26: SP | N26: SERGIANA | O26: 534173 | P26: 46084 | Q26: 46085 | R26: AUTORIZADO PAGAMENTO | S26: 8202625269 | T26: 5 DIAS ÚTEIS | U26: 46083 | V26: 46086 | W26: 46093 | X26: 46092 | Y26: =IF(AND(X26<>"",W26<>""),IF(X26<=W26,"SIM","NÃO"),"") | AC26: =IF($C26="","",IF(COUNTIF('Códigos Santander (ref)'!$A$2:$A$79,$C26)>0,"SANTANDER",IF(COUNTIF('Códigos Itaú (ref)'!$A$2:$A$44,$C26)>0,"ITAU",IF(AND(TRIM(UPPER($I26))="CONTRATUAL",ISNUMBER(SEARCH("INDIVIDUAL",SUBSTITUTE(UPPER($D26)," ","")))),"PREMIUM FREE",""))))
A27: TELA | B27: 53227 | C27: 0CRYZ | D27: ASSOC COM E EMP DE ITAU DE MINAS ACEIM | E27: 3965883879 | F27: 0CRYZ000003000 | G27: 190 | H27: 190 | I27: PÓS PAGAMENTO | J27: 27872288000140 | K27: ORALMAX RADIOLOGIA LTDA | L27: PASSOS | M27: MG | N27: CIBELY | O27: 534189 | P27: 46084 | Q27: 46085 | R27: AUTORIZADO PAGAMENTO | S27: 8202625245 | T27: 30 DIAS CORRIDOS | U27: 46083 | V27: 46086 | W27: 46117 | X27: 46092 | Y27: =IF(AND(X27<>"",W27<>""),IF(X27<=W27,"SIM","NÃO"),"") | AC27: =IF($C27="","",IF(COUNTIF('Códigos Santander (ref)'!$A$2:$A$79,$C27)>0,"SANTANDER",IF(COUNTIF('Códigos Itaú (ref)'!$A$2:$A$44,$C27)>0,"ITAU",IF(AND(TRIM(UPPER($I27))="CONTRATUAL",ISNUMBER(SEARCH("INDIVIDUAL",SUBSTITUTE(UPPER($D27)," ","")))),"PREMIUM FREE",""))))
A28: TELA | B28: 53876 | C28: 0CRYZ | D28: ASSOC COM E EMP DE ITAU DE MINAS ACEIM | E28: 3965883879 | F28: 0CRYZ000003000 | G28: 130 | H28: 130 | I28: PÓS PAGAMENTO | J28: 9997103629 | K28: MARIELE CARDOSO | L28: PASSOS | M28: MG | N28: CIBELY | O28: 534189 | P28: 46084 | Q28: 46085 | R28: AUTORIZADO PAGAMENTO | S28: 8202625247 | T28: 30 DIAS CORRIDOS | U28: 46083 | V28: 46086 | W28: 46117 | X28: 46092 | Y28: =IF(AND(X28<>"",W28<>""),IF(X28<=W28,"SIM","NÃO"),"") | AC28: =IF($C28="","",IF(COUNTIF('Códigos Santander (ref)'!$A$2:$A$79,$C28)>0,"SANTANDER",IF(COUNTIF('Códigos Itaú (ref)'!$A$2:$A$44,$C28)>0,"ITAU",IF(AND(TRIM(UPPER($I28))="CONTRATUAL",ISNUMBER(SEARCH("INDIVIDUAL",SUBSTITUTE(UPPER($D28)," ","")))),"PREMIUM FREE",""))))
A29: TELA | B29: 53135 | C29: 1RUAX | D29: ESFERA FIDELIDADE SA | E29: 22972796802 | F29: 1RUAX000071005 | G29: 600 | H29: 113.4 | I29: CONTRATUAL | J29: 26732536000195 | K29: SIDNEY KERR - ASSISTENCIA ODONTOLOGICA LTDA | L29: SÃO PAULO | M29: SP | N29: SERGIANA | O29: JA POSSUI | R29: AUTORIZADO PAGAMENTO | S29: 8202625111 | T29: 5 DIAS ÚTEIS | U29: 46083 | V29: 46084 | W29: 46091 | X29: 46090 | Y29: =IF(AND(X29<>"",W29<>""),IF(X29<=W29,"SIM","NÃO"),"") | AC29: =IF($C29="","",IF(COUNTIF('Códigos Santander (ref)'!$A$2:$A$79,$C29)>0,"SANTANDER",IF(COUNTIF('Códigos Itaú (ref)'!$A$2:$A$44,$C29)>0,"ITAU",IF(AND(TRIM(UPPER($I29))="CONTRATUAL",ISNUMBER(SEARCH("INDIVIDUAL",SUBSTITUTE(UPPER($D29)," ","")))),"PREMIUM FREE",""))))
A30: TELA | B30: 53913 | C30: 1RU51 | D30: BANCO SANTANDER BRASIL SA | E30: 11831051850 | F30: 1RU51000680001 | G30: 650 | H30: 267.65 | I30: CONTRATUAL | J30: 59880704000149 | K30: LIBURNUS ODONTOLOGIA LTDA | L30: SÃO PAULO | M30: SP | N30: SERGIANA | O30: JA POSSUI | R30: AUTORIZADO PAGAMENTO | S30: 8202625110 | T30: 5 DIAS ÚTEIS | U30: 46083 | V30: 46084 | W30: 46091 | X30: 46090 | Y30: =IF(AND(X30<>"",W30<>""),IF(X30<=W30,"SIM","NÃO"),"") | AC30: =IF($C30="","",IF(COUNTIF('Códigos Santander (ref)'!$A$2:$A$79,$C30)>0,"SANTANDER",IF(COUNTIF('Códigos Itaú (ref)'!$A$2:$A$44,$C30)>0,"ITAU",IF(AND(TRIM(UPPER($I30))="CONTRATUAL",ISNUMBER(SEARCH("INDIVIDUAL",SUBSTITUTE(UPPER($D30)," ","")))),"PREMIUM FREE",""))))
A31: TELA | B31: 53914 | C31: 1RU51 | D31: BANCO SANTANDER BRASIL SA | E31: 11831051850 | F31: 1RU51000680010 | G31: 650 | H31: 267.65 | I31: CONTRATUAL | J31: 59880704000149 | K31: LIBURNUS ODONTOLOGIA LTDA | L31: SÃO PAULO | M31: SP | N31: SERGIANA | O31: JA POSSUI | R31: AUTORIZADO PAGAMENTO | S31: 8202625109 | T31: 5 DIAS ÚTEIS | U31: 46083 | V31: 46084 | W31: 46091 | X31: 46090 | Y31: =IF(AND(X31<>"",W31<>""),IF(X31<=W31,"SIM","NÃO"),"") | AC31: =IF($C31="","",IF(COUNTIF('Códigos Santander (ref)'!$A$2:$A$79,$C31)>0,"SANTANDER",IF(COUNTIF('Códigos Itaú (ref)'!$A$2:$A$44,$C31)>0,"ITAU",IF(AND(TRIM(UPPER($I31))="CONTRATUAL",ISNUMBER(SEARCH("INDIVIDUAL",SUBSTITUTE(UPPER($D31)," ","")))),"PREMIUM FREE",""))))
A32: TELA | B32: 53229 | C32: 1RUH3 | D32: BANCO SANTANDER BRASIL SA | E32: 29923408809 | F32: 1RUH3030412005 | G32: 370 | H32: 243.88 | I32: CONTRATUAL | J32: 24870458000160 | K32: EDWAL LOBOSCHI | L32: SÃO PAULO | M32: SP | N32: SERGIANA | O32: JA POSSUI | R32: AUTORIZADO PAGAMENTO | S32: 8202625108 | T32: 5 DIAS ÚTEIS | U32: 46084 | V32: 46084 | W32: 46091 | X32: 46090 | Y32: =IF(AND(X32<>"",W32<>""),IF(X32<=W32,"SIM","NÃO"),"") | AC32: =IF($C32="","",IF(COUNTIF('Códigos Santander (ref)'!$A$2:$A$79,$C32)>0,"SANTANDER",IF(COUNTIF('Códigos Itaú (ref)'!$A$2:$A$44,$C32)>0,"ITAU",IF(AND(TRIM(UPPER($I32))="CONTRATUAL",ISNUMBER(SEARCH("INDIVIDUAL",SUBSTITUTE(UPPER($D32)," ","")))),"PREMIUM FREE",""))))
A33: TELA | B33: 53804 | C33: 1RUH3 | D33: BANCO SANTANDER BRASIL SA | E33: 22716592802 | F33: 1RUH3036459011 | G33: 100 | H33: 90.94 | I33: CONTRATUAL | J33: 43661294857 | K33: RAYSSA DE OLIVEIRA AMORIM SOBRAL | L33: SÃO PAULO | M33: SP | N33: SERGIANA | O33: JA POSSUI | R33: AUTORIZADO PAGAMENTO | S33: 8202625107 | T33: 5 DIAS ÚTEIS | U33: 46084 | V33: 46084 | W33: 46091 | X33: 46090 | Y33: =IF(AND(X33<>"",W33<>""),IF(X33<=W33,"SIM","NÃO"),"") | AC33: =IF($C33="","",IF(COUNTIF('Códigos Santander (ref)'!$A$2:$A$79,$C33)>0,"SANTANDER",IF(COUNTIF('Códigos Itaú (ref)'!$A$2:$A$44,$C33)>0,"ITAU",IF(AND(TRIM(UPPER($I33))="CONTRATUAL",ISNUMBER(SEARCH("INDIVIDUAL",SUBSTITUTE(UPPER($D33)," ","")))),"PREMIUM FREE",""))))
A34: TELA | B34: 53890 | C34: 1RUGZ | D34: SX TOOLS SOLUC SERV COMPARTILHADOS LTDA | E34: 28776802825 | F34: 1RUGZ002658020 | G34: 250 | H34: 212.19 | I34: CONTRATUAL | J34: 12974178871 | K34: MARCIA FERNANDES SARDINHA | L34: SÃO PAULO | M34: SP | N34: SERGIANA | O34: 534380 | P34: 46085 | Q34: 46087 | R34: AUTORIZADO PAGAMENTO | S34: 8202625308 | T34: 5 DIAS ÚTEIS | U34: 46084 | V34: 46087 | W34: 46094 | X34: 46094 | Y34: =IF(AND(X34<>"",W34<>""),IF(X34<=W34,"SIM","NÃO"),"") | Z34: ALTERAÇÃO DE PD | AC34: =IF($C34="","",IF(COUNTIF('Códigos Santander (ref)'!$A$2:$A$79,$C34)>0,"SANTANDER",IF(COUNTIF('Códigos Itaú (ref)'!$A$2:$A$44,$C34)>0,"ITAU",IF(AND(TRIM(UPPER($I34))="CONTRATUAL",ISNUMBER(SEARCH("INDIVIDUAL",SUBSTITUTE(UPPER($D34)," ","")))),"PREMIUM FREE",""))))
A35: TELA | B35: 53859 | C35: 0M1CA | D35: CARREFOUR COMERCIO E INDUSTRIA LTDA | E35: 40460022806 | F35: 0M1CA008670013 | G35: 506 | H35: 12 | I35: CONTRATUAL | J35: 9267310000141 | K35: PREZ ODONTO CLINICA ODONTOLOGICA LTDA | L35: SÃO PAULO | M35: SP | N35: SERGIANA | O35: 534425 | P35: 46085 | Q35: 46086 | R35: AUTORIZADO PAGAMENTO | S35: 8202625273 | T35: 8 DIAS ÚTEIS | U35: 46084 | V35: 46086 | W35: 46098 | X35: 46092 | Y35: =IF(AND(X35<>"",W35<>""),IF(X35<=W35,"SIM","NÃO"),"") | AC35: =IF($C35="","",IF(COUNTIF('Códigos Santander (ref)'!$A$2:$A$79,$C35)>0,"SANTANDER",IF(COUNTIF('Códigos Itaú (ref)'!$A$2:$A$44,$C35)>0,"ITAU",IF(AND(TRIM(UPPER($I35))="CONTRATUAL",ISNUMBER(SEARCH("INDIVIDUAL",SUBSTITUTE(UPPER($D35)," ","")))),"PREMIUM FREE",""))))
A36: TELA | B36: 53909 | C36: 0AR15 | D36: TEREOS ACUCAR E ENERGIA BRASIL S.A. | E36: 34353652850 | F36: 0AR15005368006 | G36: 200 | H36: 40.88 | I36: CONTRATUAL | J36: 29932340804 | K36: CELIA NEGRAO CORREA INACIO | L36: OLIMPIA | M36: SP | N36: SERGIANA | O36: JA POSSUI | R36: AUTORIZADO PAGAMENTO | S36: 8202625215 | T36: 30 DIAS CORRIDOS | U36: 46084 | V36: 46085 | W36: 46116 | X36: 46090 | Y36: =IF(AND(X36<>"",W36<>""),IF(X36<=W36,"SIM","NÃO"),"") | AC36: =IF($C36="","",IF(COUNTIF('Códigos Santander (ref)'!$A$2:$A$79,$C36)>0,"SANTANDER",IF(COUNTIF('Códigos Itaú (ref)'!$A$2:$A$44,$C36)>0,"ITAU",IF(AND(TRIM(UPPER($I36))="CONTRATUAL",ISNUMBER(SEARCH("INDIVIDUAL",SUBSTITUTE(UPPER($D36)," ","")))),"PREMIUM FREE",""))))
A37: LECOM | B37: 53933 | C37: 1RBB8 | D37: TBI SEGURANÇA EIRELI | E37: 6024321627 | F37: 1RBB8002644002 | G37: 70 | H37: 70 | I37: INSUFICIÊNCIA DE REDE | J37: 17765345000139 | K37: CLINICA ORAL IMAGEM LTDA | L37: TRES MARIAS | M37: MG | N37: VITORIA | O37: 533999 | P37: 46084 | Q37: 46087 | R37: AUTORIZADO PAGAMENTO | S37: 8202625331 | T37: 30 DIAS CORRIDOS | U37: 46084 | V37: 46087 | W37: 46118 | X37: 46094 | Y37: =IF(AND(X37<>"",W37<>""),IF(X37<=W37,"SIM","NÃO"),"") | AC37: =IF($C37="","",IF(COUNTIF('Códigos Santander (ref)'!$A$2:$A$79,$C37)>0,"SANTANDER",IF(COUNTIF('Códigos Itaú (ref)'!$A$2:$A$44,$C37)>0,"ITAU",IF(AND(TRIM(UPPER($I37))="CONTRATUAL",ISNUMBER(SEARCH("INDIVIDUAL",SUBSTITUTE(UPPER($D37)," ","")))),"PREMIUM FREE",""))))
A38: TELA | B38: 52197 | C38: 1RU54 | D38: BANCO SANTANDER BRASIL SA | E38: 36893404620 | F38: 1RU54000107000 | G38: 1720 | H38: 1321.92 | I38: CONTRATUAL | J38: 67069282672 | K38: LEONE RIBEIRO DE ALMEIDA | L38: SÃO PAULO | M38: SP | N38: SERGIANA | O38: JA POSSUI | R38: AUTORIZADO PAGAMENTO | S38: 8202625217 | T38: 5 DIAS ÚTEIS | U38: 46084 | V38: 46085 | W38: 46092 | X38: 46090 | Y38: =IF(AND(X38<>"",W38<>""),IF(X38<=W38,"SIM","NÃO"),"") | AC38: =IF($C38="","",IF(COUNTIF('Códigos Santander (ref)'!$A$2:$A$79,$C38)>0,"SANTANDER",IF(COUNTIF('Códigos Itaú (ref)'!$A$2:$A$44,$C38)>0,"ITAU",IF(AND(TRIM(UPPER($I38))="CONTRATUAL",ISNUMBER(SEARCH("INDIVIDUAL",SUBSTITUTE(UPPER($D38)," ","")))),"PREMIUM FREE",""))))
A39: TELA | B39: 53900 | C39: 0M1CA | D39: CARREFOUR COMERCIO E INDUSTRIA LTDA | E39: 40460022806 | F39: 0M1CA008670005 | G39: 600 | H39: 40.2 | I39: CONTRATUAL | J39: 9267310000141 | K39: PREZ ODONTO CLINICA ODONTOLOGICA LTDA | L39: SÃO PAULO | M39: SP | N39: SERGIANA | O39: 534425 | P39: 46085 | Q39: 46086 | R39: AUTORIZADO PAGAMENTO | S39: 8202625274 | T39: 8 DIAS ÚTEIS | U39: 46084 | V39: 46086 | W39: 46098 | X39: 46092 | Y39: =IF(AND(X39<>"",W39<>""),IF(X39<=W39,"SIM","NÃO"),"") | AC39: =IF($C39="","",IF(COUNTIF('Códigos Santander (ref)'!$A$2:$A$79,$C39)>0,"SANTANDER",IF(COUNTIF('Códigos Itaú (ref)'!$A$2:$A$44,$C39)>0,"ITAU",IF(AND(TRIM(UPPER($I39))="CONTRATUAL",ISNUMBER(SEARCH("INDIVIDUAL",SUBSTITUTE(UPPER($D39)," ","")))),"PREMIUM FREE",""))))
A40: TELA | B40: 53363 | C40: 4010X | D40: INDIVIDUAL | E40: 40516250876 | F40: 4010X019580002 | G40: 45 | H40: 45 | I40: COBRANÇA INDEVIDA | J40: 22427358000138 | K40: RADIOLOGIA ODONTOLOGICA LINS LTDA | L40: LINS | M40: SP | N40: SERGIANA | O40: 534426 | P40: 46085 | Q40: 46086 | R40: AUTORIZADO PAGAMENTO | S40: 8202625276 | T40: 30 DIAS CORRIDOS | U40: 46084 | V40: 46086 | W40: 46117 | X40: 46092 | Y40: =IF(AND(X40<>"",W40<>""),IF(X40<=W40,"SIM","NÃO"),"") | AC40: =IF($C40="","",IF(COUNTIF('Códigos Santander (ref)'!$A$2:$A$79,$C40)>0,"SANTANDER",IF(COUNTIF('Códigos Itaú (ref)'!$A$2:$A$44,$C40)>0,"ITAU",IF(AND(TRIM(UPPER($I40))="CONTRATUAL",ISNUMBER(SEARCH("INDIVIDUAL",SUBSTITUTE(UPPER($D40)," ","")))),"PREMIUM FREE",""))))
A41: TELA | B41: 53638 | C41: 0KGE5 | D41: BANCO SANTANDER BRASIL SA | E41: 25042081895 | F41: 0KGE5036313009 | G41: 1600 | H41: 437.45 | I41: CONTRATUAL | J41: 52678150000152 | K41: IMK ODONTOLOGIA ESPECIALIZADA LTDA | L41: SÃO PAULO | M41: SP | N41: SERGIANA | O41: 534432 | P41: 46085 | Q41: 46086 | R41: AUTORIZADO PAGAMENTO | S41: 8202625275 | T41: 5 DIAS ÚTEIS | U41: 46084 | V41: 46086 | W41: 46093 | X41: 46092 | Y41: =IF(AND(X41<>"",W41<>""),IF(X41<=W41,"SIM","NÃO"),"") | AC41: =IF($C41="","",IF(COUNTIF('Códigos Santander (ref)'!$A$2:$A$79,$C41)>0,"SANTANDER",IF(COUNTIF('Códigos Itaú (ref)'!$A$2:$A$44,$C41)>0,"ITAU",IF(AND(TRIM(UPPER($I41))="CONTRATUAL",ISNUMBER(SEARCH("INDIVIDUAL",SUBSTITUTE(UPPER($D41)," ","")))),"PREMIUM FREE",""))))
A42: TELA | B42: 53173 | C42: 1RUGZ | D42: SX TOOLS SOLUC SERV COMPARTILHADOS LTDA | E42: 11746503629 | F42: 1RUGZ001729012 | G42: 2180 | H42: 1600.34 | I42: CONTRATUAL | J42: 48643083000163 | K42: ODONTOLOGIA ESPECIALIZADA DR. RAPHAEL RIBEIRO LTDA | L42: BELO HORIZONTE | M42: MG | N42: SERGIANA | O42: JA POSSUI | R42: AUTORIZADO PAGAMENTO | S42: 8202625218 | T42: 5 DIAS ÚTEIS | U42: 46084 | V42: 46085 | W42: 46092 | X42: 46090 | Y42: =IF(AND(X42<>"",W42<>""),IF(X42<=W42,"SIM","NÃO"),"") | AC42: =IF($C42="","",IF(COUNTIF('Códigos Santander (ref)'!$A$2:$A$79,$C42)>0,"SANTANDER",IF(COUNTIF('Códigos Itaú (ref)'!$A$2:$A$44,$C42)>0,"ITAU",IF(AND(TRIM(UPPER($I42))="CONTRATUAL",ISNUMBER(SEARCH("INDIVIDUAL",SUBSTITUTE(UPPER($D42)," ","")))),"PREMIUM FREE",""))))
A43: TELA | B43: 51486 | C43: 1RUH3 | D43: BANCO SANTANDER BRASIL SA | E43: 85426067600 | F43: 1RUH3036497029 | G43: 2400 | H43: 699.9 | I43: CONTRATUAL | J43: 57106217000106 | K43: MAV ATELIE DENTAL LTDA | L43: SÃO PAULO | M43: SP | N43: SERGIANA | O43: 534467 | P43: 46085 | Q43: 46086 | R43: AUTORIZADO PAGAMENTO | S43: 8202625301 | T43: 5 DIAS ÚTEIS | U43: 46085 | V43: 46087 | W43: 46094 | X43: 46094 | Y43: =IF(AND(X43<>"",W43<>""),IF(X43<=W43,"SIM","NÃO"),"") | AC43: =IF($C43="","",IF(COUNTIF('Códigos Santander (ref)'!$A$2:$A$79,$C43)>0,"SANTANDER",IF(COUNTIF('Códigos Itaú (ref)'!$A$2:$A$44,$C43)>0,"ITAU",IF(AND(TRIM(UPPER($I43))="CONTRATUAL",ISNUMBER(SEARCH("INDIVIDUAL",SUBSTITUTE(UPPER($D43)," ","")))),"PREMIUM FREE",""))))
A44: SAC | B44: 53987 | C44: 50700 | D44: INDIVIDUAL MAISODONTO | E44: 98434047187 | F44: 50700286458015 | G44: 50 | H44: 6.6 | I44: CONTRATUAL | J44: 53493936000168 | K44: CAVALARI & DINIZ CABRAL RADIOLOGIA ODONTOLOGIA LTDA | L44: QUIRINÓPOLIS | M44: GO | N44: CIBELY | O44: 534481 | P44: 46085 | Q44: 46086 | R44: AUTORIZADO PAGAMENTO | S44: 8202625303 | T44: 30 DIAS CORRIDOS | U44: 46085 | V44: 46087 | W44: 46118 | X44: 46094 | Y44: =IF(AND(X44<>"",W44<>""),IF(X44<=W44,"SIM","NÃO"),"") | AC44: =IF($C44="","",IF(COUNTIF('Códigos Santander (ref)'!$A$2:$A$79,$C44)>0,"SANTANDER",IF(COUNTIF('Códigos Itaú (ref)'!$A$2:$A$44,$C44)>0,"ITAU",IF(AND(TRIM(UPPER($I44))="CONTRATUAL",ISNUMBER(SEARCH("INDIVIDUAL",SUBSTITUTE(UPPER($D44)," ","")))),"PREMIUM FREE",""))))
A45: TELA | B45: 53936 | C45: 1RUB1 | D45: F1RST TECNOLOGIA E INOVACAO LTDA | E45: 16240400807 | F45: 1RUB1000530000 | G45: 480 | H45: 163.8 | I45: CONTRATUAL | J45: 2627303163 | K45: LAURA GUIMARAES MELO COSTA | L45: SANTOS | M45: SP | N45: SERGIANA | O45: JA POSSUI | R45: AUTORIZADO PAGAMENTO | S45: 8202625219 | T45: 5 DIAS ÚTEIS | U45: 46085 | V45: 46085 | W45: 46092 | X45: 46090 | Y45: =IF(AND(X45<>"",W45<>""),IF(X45<=W45,"SIM","NÃO"),"") | AC45: =IF($C45="","",IF(COUNTIF('Códigos Santander (ref)'!$A$2:$A$79,$C45)>0,"SANTANDER",IF(COUNTIF('Códigos Itaú (ref)'!$A$2:$A$44,$C45)>0,"ITAU",IF(AND(TRIM(UPPER($I45))="CONTRATUAL",ISNUMBER(SEARCH("INDIVIDUAL",SUBSTITUTE(UPPER($D45)," ","")))),"PREMIUM FREE",""))))
A46: TELA | B46: 53901 | C46: 1RUH3 | D46: BANCO SANTANDER BRASIL SA | E46: 46992730843 | F46: 1RUH3006876021 | G46: 150 | H46: 150 | I46: CONTRATUAL | J46: 37710114857 | K46: LARISSA SANDY DA SILVA LEITE | L46: CRUZEIRO | M46: SP | N46: SERGIANA | O46: JA POSSUI | R46: AUTORIZADO PAGAMENTO | S46: 8202625220 | T46: 5 DIAS ÚTEIS | U46: 46085 | V46: 46085 | W46: 46092 | X46: 46090 | Y46: =IF(AND(X46<>"",W46<>""),IF(X46<=W46,"SIM","NÃO"),"") | AC46: =IF($C46="","",IF(COUNTIF('Códigos Santander (ref)'!$A$2:$A$79,$C46)>0,"SANTANDER",IF(COUNTIF('Códigos Itaú (ref)'!$A$2:$A$44,$C46)>0,"ITAU",IF(AND(TRIM(UPPER($I46))="CONTRATUAL",ISNUMBER(SEARCH("INDIVIDUAL",SUBSTITUTE(UPPER($D46)," ","")))),"PREMIUM FREE",""))))
